Workbook
Name Vendors_List: 'Lookups - Rates'!$H$2:$H$3
Name Scenario_Selected: Assumptions!$B$7
Name Scenario_Table: Assumptions!$A$9:$D$12
Name Milestone_Activities: Milestones!$B$2:$B$40
Name Complexity_Tasks: 'Lookups - Complexity'!$B$2:$B$26
Name Roles_List: 'Lookups - Rates'!$I$2:$I$100

Sheet Inputs
A1: Estimation Inputs
A3: Delivery Model | B3: Hybrid Service Delivery
A4: Journey | B4: 1 Journey
A5: Deployment | B5: 1 Deployment
A6: Default Complexity | B6: Medium
A7: Readiness/Maturity Multiplier | B7: =IFERROR('Readiness & Maturity'!$B$16,1)
A8: Readiness Level (calculated) | B8: =IFERROR('Readiness & Maturity'!$B$15,"-")

Sheet Lookups - JourneyDeployment
A1: Journey options | D1: Deployment options | G1: Complexity | I1: Delivery owner | K1: Role mapping (WBS → standard rate role)
A2: Journey | B2: Multiplier | D2: Deployment | E2: Multiplier | G2: Option | I2: Option | K2: WBS Role | L2: Standard Role
A3: 1 Journey | B3: 1 | D3: 1 Deployment | E3: 1 | G3: Low | I3: Knapsack | K3: CX Partner | L3: CX Partner
A4: 2–3 Journeys | B4: 1.5 | D4: 2 Deployments | E4: 1.4 | G4: Medium | I4: Client/SCE | K4: Project Manager | L4: Project Manager
A5: 4–6 Journeys | B5: 2 | D5: 3–5 Deployments | E5: 2 | G5: High | K5: Engineer | L5: Solution Analyst
A6: 7+ Journeys | B6: 3 | D6: 6+ Deployments | E6: 2.8 | K6: SME | L6: SME
K7: Design Lead | L7: Executive

Sheet Rates
A1: Standard Role | B1: Provider | C1: Rate ($/hr) | D1: Source | E1: Key
A2: CX Partner | B2: Knapsack | C2: 600 | D2: Knapsack bill rate | E2: CX Partner|Knapsack
A3: Senior Solution Analyst | B3: Knapsack | C3: 550 | D3: Knapsack bill rate | E3: Senior Solution Analyst|Knapsack
A4: Solution Analyst | B4: Knapsack | C4: 400 | D4: Knapsack bill rate | E4: Solution Analyst|Knapsack
A5: Project Manager | B5: Knapsack | C5: 400 | D5: Knapsack bill rate | E5: Project Manager|Knapsack
A6: SME | B6: Knapsack | C6: 750 | D6: Knapsack bill rate | E6: SME|Knapsack
A7: Executive | B7: Knapsack | C7: 825 | D7: Knapsack bill rate | E7: Executive|Knapsack
A8: CX Partner | B8: Client/SCE | C8: 140 | D8: Default CSE rate (edit) | E8: CX Partner|Client/SCE
A9: Senior Solution Analyst | B9: Client/SCE | C9: 140 | D9: Default CSE rate (edit) | E9: Senior Solution Analyst|Client/SCE
A10: Solution Analyst | B10: Client/SCE | C10: 140 | D10: Default CSE rate (edit) | E10: Solution Analyst|Client/SCE
A11: Project Manager | B11: Client/SCE | C11: 140 | D11: Default CSE rate (edit) | E11: Project Manager|Client/SCE
A12: SME | B12: Client/SCE | C12: 140 | D12: Default CSE rate (edit) | E12: SME|Client/SCE
A13: Executive | B13: Client/SCE | C13: 140 | D13: Default CSE rate (edit) | E13: Executive|Client/SCE

Sheet Readiness & Maturity
A1: Readiness & Maturity (PCRI-driven)
A3: PCRI is calculated on the 'PCRI Assessment' tab. Outputs below drive estimation multipliers and WBS prescription.
A5: PCRI Score | B5: ='PCRI Assessment'!$J$20 | D5: Archetype | E5: Default Multiplier | F5: Notes
A6: Archetype | B6: ='PCRI Assessment'!$J$21 | D6: Builder | E6: 1.5 | F6: More foundation + enablement
A7: Foundation (effective) | B7: ='PCRI Assessment'!$J$15 | D7: Adopter | E7: 1.2 | F7: Enablement sprint + adoption
A8: AI Readiness (effective) | B8: ='PCRI Assessment'!$J$16 | D8: Optimizer | E8: 1 | F8: Standard delivery
A9: Governance (effective) | B9: ='PCRI Assessment'!$J$17 | D9: Transformer | E9: 0.9 | F9: Less enablement; faster execution
A10: Delivery (effective) | B10: ='PCRI Assessment'!$J$18
A11: Culture (effective) | B11: ='PCRI Assessment'!$J$19
A12: AI Gate Applied? | B12: ='PCRI Assessment'!$J$13
A13: Delivery Gate Applied? | B13: ='PCRI Assessment'!$J$14
A14: Multiplier mapping (edit if needed) | D14: Archetype → Multiplier Mapping
A15: Readiness level (used by Inputs) | B15: =B6 | D15: Edit the multipliers in column E to calibrate by archetype.
A16: Multiplier | B16: =IFERROR(XLOOKUP(B6,$D$6:$D$9,$E$6:$E$9),1)

Sheet Activity Settings
A1: Phase | B1: Activity / Milestone | C1: # Subtasks | D1: Complexity (input) | E1: Base Hours (lookup) | F1: Readiness Mult | G1: Journey Mult | H1: Deployment Mult | I1: Adjusted Total Hours | J1: Adjusted Hours / Subtask | K1: Owner Override (Hybrid) | L1: Owner Used | M1: Activity Key | N1: PCRI Mult (include/prescribe)
A2: Implementation + Onboarding | B2: Stakeholder Alignment Workshops | C2: 5 | D2: =Inputs!$B$6 | E2: =IFERROR(INDEX('Lookups - Complexity'!$C$2:$E$200, MATCH(M2,'Lookups - Complexity'!$F$2:$F$200, 0), MATCH(D2, {"Low","Medium","High"}, 0)), 0) | F2: =Inputs!$B$7 | G2: =IFERROR(XLOOKUP(Inputs!$B$4,'Lookups - JourneyDeployment'!$A$3:$A$6,'Lookups - JourneyDeployment'!$B$3:$B$6),1) | H2: =IFERROR(XLOOKUP(Inputs!$B$5,'Lookups - JourneyDeployment'!$D$3:$D$6,'Lookups - JourneyDeployment'!$E$3:$E$6),1) | I2: =E2*F2*G2*H2*N2 | J2: =IF(C2=0,0,I2/C2) | K2: Knapsack | L2: =IF(Inputs!$B$3="Managed Service Delivery","Knapsack",IF(K2="","Knapsack",K2)) | M2: =A2&"|"&B2 | N2: =IFERROR(XLOOKUP(M2,'PCRI WBS Mapping'!$C$2:$C$200,'PCRI WBS Mapping'!$M$2:$M$200),1)
A3: Implementation + Onboarding | B3: Program management and coordination | C3: 5 | D3: =Inputs!$B$6 | E3: =IFERROR(INDEX('Lookups - Complexity'!$C$2:$E$200, MATCH(M3,'Lookups - Complexity'!$F$2:$F$200, 0), MATCH(D3, {"Low","Medium","High"}, 0)), 0) | F3: =Inputs!$B$7 | G3: =IFERROR(XLOOKUP(Inputs!$B$4,'Lookups - JourneyDeployment'!$A$3:$A$6,'Lookups - JourneyDeployment'!$B$3:$B$6),1) | H3: =IFERROR(XLOOKUP(Inputs!$B$5,'Lookups - JourneyDeployment'!$D$3:$D$6,'Lookups - JourneyDeployment'!$E$3:$E$6),1) | I3: =E3*F3*G3*H3*N3 | J3: =IF(C3=0,0,I3/C3) | K3: Knapsack | L3: =IF(Inputs!$B$3="Managed Service Delivery","Knapsack",IF(K3="","Knapsack",K3)) | M3: =A3&"|"&B3 | N3: =IFERROR(XLOOKUP(M3,'PCRI WBS Mapping'!$C$2:$C$200,'PCRI WBS Mapping'!$M$2:$M$200),1)
A4: Implementation + Onboarding | B4: Communication Launch Plan | C4: 5 | D4: =Inputs!$B$6 | E4: =IFERROR(INDEX('Lookups - Complexity'!$C$2:$E$200, MATCH(M4,'Lookups - Complexity'!$F$2:$F$200, 0), MATCH(D4, {"Low","Medium","High"}, 0)), 0) | F4: =Inputs!$B$7 | G4: =IFERROR(XLOOKUP(Inputs!$B$4,'Lookups - JourneyDeployment'!$A$3:$A$6,'Lookups - JourneyDeployment'!$B$3:$B$6),1) | H4: =IFERROR(XLOOKUP(Inputs!$B$5,'Lookups - JourneyDeployment'!$D$3:$D$6,'Lookups - JourneyDeployment'!$E$3:$E$6),1) | I4: =E4*F4*G4*H4*N4 | J4: =IF(C4=0,0,I4/C4) | K4: Knapsack | L4: =IF(Inputs!$B$3="Managed Service Delivery","Knapsack",IF(K4="","Knapsack",K4)) | M4: =A4&"|"&B4 | N4: =IFERROR(XLOOKUP(M4,'PCRI WBS Mapping'!$C$2:$C$200,'PCRI WBS Mapping'!$M$2:$M$200),1)
A5: Implementation + Onboarding | B5: Preparation | C5: 5 | D5: =Inputs!$B$6 | E5: =IFERROR(INDEX('Lookups - Complexity'!$C$2:$E$200, MATCH(M5,'Lookups - Complexity'!$F$2:$F$200, 0), MATCH(D5, {"Low","Medium","High"}, 0)), 0) | F5: =Inputs!$B$7 | G5: =IFERROR(XLOOKUP(Inputs!$B$4,'Lookups - JourneyDeployment'!$A$3:$A$6,'Lookups - JourneyDeployment'!$B$3:$B$6),1) | H5: =IFERROR(XLOOKUP(Inputs!$B$5,'Lookups - JourneyDeployment'!$D$3:$D$6,'Lookups - JourneyDeployment'!$E$3:$E$6),1) | I5: =E5*F5*G5*H5*N5 | J5: =IF(C5=0,0,I5/C5) | K5: Knapsack | L5: =IF(Inputs!$B$3="Managed Service Delivery","Knapsack",IF(K5="","Knapsack",K5)) | M5: =A5&"|"&B5 | N5: =IFERROR(XLOOKUP(M5,'PCRI WBS Mapping'!$C$2:$C$200,'PCRI WBS Mapping'!$M$2:$M$200),1)
A6: Implementation + Onboarding | B6: Local install support | C6: 5 | D6: =Inputs!$B$6 | E6: =IFERROR(INDEX('Lookups - Complexity'!$C$2:$E$200, MATCH(M6,'Lookups - Complexity'!$F$2:$F$200, 0), MATCH(D6, {"Low","Medium","High"}, 0)), 0) | F6: =Inputs!$B$7 | G6: =IFERROR(XLOOKUP(Inputs!$B$4,'Lookups - JourneyDeployment'!$A$3:$A$6,'Lookups - JourneyDeployment'!$B$3:$B$6),1) | H6: =IFERROR(XLOOKUP(Inputs!$B$5,'Lookups - JourneyDeployment'!$D$3:$D$6,'Lookups - JourneyDeployment'!$E$3:$E$6),1) | I6: =E6*F6*G6*H6*N6 | J6: =IF(C6=0,0,I6/C6) | K6: Knapsack | L6: =IF(Inputs!$B$3="Managed Service Delivery","Knapsack",IF(K6="","Knapsack",K6)) | M6: =A6&"|"&B6 | N6: =IFERROR(XLOOKUP(M6,'PCRI WBS Mapping'!$C$2:$C$200,'PCRI WBS Mapping'!$M$2:$M$200),1)
A7: Implementation + Onboarding | B7: Component rendering | C7: 5 | D7: =Inputs!$B$6 | E7: =IFERROR(INDEX('Lookups - Complexity'!$C$2:$E$200, MATCH(M7,'Lookups - Complexity'!$F$2:$F$200, 0), MATCH(D7, {"Low","Medium","High"}, 0)), 0) | F7: =Inputs!$B$7 | G7: =IFERROR(XLOOKUP(Inputs!$B$4,'Lookups - JourneyDeployment'!$A$3:$A$6,'Lookups - JourneyDeployment'!$B$3:$B$6),1) | H7: =IFERROR(XLOOKUP(Inputs!$B$5,'Lookups - JourneyDeployment'!$D$3:$D$6,'Lookups - JourneyDeployment'!$E$3:$E$6),1) | I7: =E7*F7*G7*H7*N7 | J7: =IF(C7=0,0,I7/C7) | K7: Knapsack | L7: =IF(Inputs!$B$3="Managed Service Delivery","Knapsack",IF(K7="","Knapsack",K7)) | M7: =A7&"|"&B7 | N7: =IFERROR(XLOOKUP(M7,'PCRI WBS Mapping'!$C$2:$C$200,'PCRI WBS Mapping'!$M$2:$M$200),1)
A8: Implementation + Onboarding | B8: SME support for rendering | C8: 5 | D8: =Inputs!$B$6 | E8: =IFERROR(INDEX('Lookups - Complexity'!$C$2:$E$200, MATCH(M8,'Lookups - Complexity'!$F$2:$F$200, 0), MATCH(D8, {"Low","Medium","High"}, 0)), 0) | F8: =Inputs!$B$7 | G8: =IFERROR(XLOOKUP(Inputs!$B$4,'Lookups - JourneyDeployment'!$A$3:$A$6,'Lookups - JourneyDeployment'!$B$3:$B$6),1) | H8: =IFERROR(XLOOKUP(Inputs!$B$5,'Lookups - JourneyDeployment'!$D$3:$D$6,'Lookups - JourneyDeployment'!$E$3:$E$6),1) | I8: =E8*F8*G8*H8*N8 | J8: =IF(C8=0,0,I8/C8) | K8: Knapsack | L8: =IF(Inputs!$B$3="Managed Service Delivery","Knapsack",IF(K8="","Knapsack",K8)) | M8: =A8&"|"&B8 | N8: =IFERROR(XLOOKUP(M8,'PCRI WBS Mapping'!$C$2:$C$200,'PCRI WBS Mapping'!$M$2:$M$200),1)
A9: Implementation + Onboarding | B9: Deployment support | C9: 5 | D9: =Inputs!$B$6 | E9: =IFERROR(INDEX('Lookups - Complexity'!$C$2:$E$200, MATCH(M9,'Lookups - Complexity'!$F$2:$F$200, 0), MATCH(D9, {"Low","Medium","High"}, 0)), 0) | F9: =Inputs!$B$7 | G9: =IFERROR(XLOOKUP(Inputs!$B$4,'Lookups - JourneyDeployment'!$A$3:$A$6,'Lookups - JourneyDeployment'!$B$3:$B$6),1) | H9: =IFERROR(XLOOKUP(Inputs!$B$5,'Lookups - JourneyDeployment'!$D$3:$D$6,'Lookups - JourneyDeployment'!$E$3:$E$6),1) | I9: =E9*F9*G9*H9*N9 | J9: =IF(C9=0,0,I9/C9) | K9: Knapsack | L9: =IF(Inputs!$B$3="Managed Service Delivery","Knapsack",IF(K9="","Knapsack",K9)) | M9: =A9&"|"&B9 | N9: =IFERROR(XLOOKUP(M9,'PCRI WBS Mapping'!$C$2:$C$200,'PCRI WBS Mapping'!$M$2:$M$200),1)
A10: Scaled Rollout and Adoption | B10: Program management and Steering Committee coordination | C10: 5 | D10: =Inputs!$B$6 | E10: =IFERROR(INDEX('Lookups - Complexity'!$C$2:$E$200, MATCH(M10,'Lookups - Complexity'!$F$2:$F$200, 0), MATCH(D10, {"Low","Medium","High"}, 0)), 0) | F10: =Inputs!$B$7 | G10: =IFERROR(XLOOKUP(Inputs!$B$4,'Lookups - JourneyDeployment'!$A$3:$A$6,'Lookups - JourneyDeployment'!$B$3:$B$6),1) | H10: =IFERROR(XLOOKUP(Inputs!$B$5,'Lookups - JourneyDeployment'!$D$3:$D$6,'Lookups - JourneyDeployment'!$E$3:$E$6),1) | I10: =E10*F10*G10*H10*N10 | J10: =IF(C10=0,0,I10/C10) | K10: Knapsack | L10: =IF(Inputs!$B$3="Managed Service Delivery","Knapsack",IF(K10="","Knapsack",K10)) | M10: =A10&"|"&B10 | N10: =IFERROR(XLOOKUP(M10,'PCRI WBS Mapping'!$C$2:$C$200,'PCRI WBS Mapping'!$M$2:$M$200),1)
A11: Scaled Rollout and Adoption | B11: Facilitating and supporting deliverables | C11: 5 | D11: =Inputs!$B$6 | E11: =IFERROR(INDEX('Lookups - Complexity'!$C$2:$E$200, MATCH(M11,'Lookups - Complexity'!$F$2:$F$200, 0), MATCH(D11, {"Low","Medium","High"}, 0)), 0) | F11: =Inputs!$B$7 | G11: =IFERROR(XLOOKUP(Inputs!$B$4,'Lookups - JourneyDeployment'!$A$3:$A$6,'Lookups - JourneyDeployment'!$B$3:$B$6),1) | H11: =IFERROR(XLOOKUP(Inputs!$B$5,'Lookups - JourneyDeployment'!$D$3:$D$6,'Lookups - JourneyDeployment'!$E$3:$E$6),1) | I11: =E11*F11*G11*H11*N11 | J11: =IF(C11=0,0,I11/C11) | K11: Knapsack | L11: =IF(Inputs!$B$3="Managed Service Delivery","Knapsack",IF(K11="","Knapsack",K11)) | M11: =A11&"|"&B11 | N11: =IFERROR(XLOOKUP(M11,'PCRI WBS Mapping'!$C$2:$C$200,'PCRI WBS Mapping'!$M$2:$M$200),1)
A12: Scaled Rollout and Adoption | B12: Change Readiness Assessment | C12: 5 | D12: =Inputs!$B$6 | E12: =IFERROR(INDEX('Lookups - Complexity'!$C$2:$E$200, MATCH(M12,'Lookups - Complexity'!$F$2:$F$200, 0), MATCH(D12, {"Low","Medium","High"}, 0)), 0) | F12: =Inputs!$B$7 | G12: =IFERROR(XLOOKUP(Inputs!$B$4,'Lookups - JourneyDeployment'!$A$3:$A$6,'Lookups - JourneyDeployment'!$B$3:$B$6),1) | H12: =IFERROR(XLOOKUP(Inputs!$B$5,'Lookups - JourneyDeployment'!$D$3:$D$6,'Lookups - JourneyDeployment'!$E$3:$E$6),1) | I12: =E12*F12*G12*H12*N12 | J12: =IF(C12=0,0,I12/C12) | K12: Knapsack | L12: =IF(Inputs!$B$3="Managed Service Delivery","Knapsack",IF(K12="","Knapsack",K12)) | M12: =A12&"|"&B12 | N12: =IFERROR(XLOOKUP(M12,'PCRI WBS Mapping'!$C$2:$C$200,'PCRI WBS Mapping'!$M$2:$M$200),1)
A13: Scaled Rollout and Adoption | B13: FDE led Implementation + Architecture + Governance | C13: 4 | D13: =Inputs!$B$6 | E13: =IFERROR(INDEX('Lookups - Complexity'!$C$2:$E$200, MATCH(M13,'Lookups - Complexity'!$F$2:$F$200, 0), MATCH(D13, {"Low","Medium","High"}, 0)), 0) | F13: =Inputs!$B$7 | G13: =IFERROR(XLOOKUP(Inputs!$B$4,'Lookups - JourneyDeployment'!$A$3:$A$6,'Lookups - JourneyDeployment'!$B$3:$B$6),1) | H13: =IFERROR(XLOOKUP(Inputs!$B$5,'Lookups - JourneyDeployment'!$D$3:$D$6,'Lookups - JourneyDeployment'!$E$3:$E$6),1) | I13: =E13*F13*G13*H13*N13 | J13: =IF(C13=0,0,I13/C13) | K13: Knapsack | L13: =IF(Inputs!$B$3="Managed Service Delivery","Knapsack",IF(K13="","Knapsack",K13)) | M13: =A13&"|"&B13 | N13: =IFERROR(XLOOKUP(M13,'PCRI WBS Mapping'!$C$2:$C$200,'PCRI WBS Mapping'!$M$2:$M$200),1)
... A60: Optimization and Continued Support | B60: AI Contextual Capabilities – Feedback Loop + Knowledge Refresh | C60: 4 | D60: =Inputs!$B$6 | E60: =IFERROR(INDEX('Lookups - Complexity'!$C$2:$E$200, MATCH(M60,'Lookups - Complexity'!$F$2:$F$200, 0), MATCH(D60, {"Low","Medium","High"}, 0)), 0) | F60: =Inputs!$B$7 | G60: =IFERROR(XLOOKUP(Inputs!$B$4,'Lookups - JourneyDeployment'!$A$3:$A$6,'Lookups - JourneyDeployment'!$B$3:$B$6),1) | H60: =IFERROR(XLOOKUP(Inputs!$B$5,'Lookups - JourneyDeployment'!$D$3:$D$6,'Lookups - JourneyDeployment'!$E$3:$E$6),1) | I60: =E60*F60*G60*H60*N60 | J60: =IF(C60=0,0,I60/C60) | K60: Knapsack | L60: =IF(Inputs!$B$3="Managed Service Delivery","Knapsack",IF(K60="","Knapsack",K60)) | M60: =A60&"|"&B60 | N60: =IFERROR(XLOOKUP(M60,'PCRI WBS Mapping'!$C$2:$C$200,'PCRI WBS Mapping'!$M$2:$M$200),1)

Sheet WBS - Estimate
A1: Phase | B1: Activity / Milestone | C1: Subtask | D1: Deliverable | E1: Deliverable Description | F1: Knapsack Role Description | G1: Accountable Party | H1: Role | I1: Timeline (Weeks) | J1: Standard Role | K1: Activity Key | L1: Hours / Subtask (adjusted) | M1: Owner Used | N1: Rate ($/hr) | O1: Est. Cost
A2: Implementation + Onboarding | B2: Stakeholder Alignment Workshops | C2: Identify executive and operational stakeholders | F2: CX Partner - Change Management SME | G2: Adobe | H2: CX Partner | I2: 1–2 | J2: =IFERROR(XLOOKUP(H2,'Lookups - JourneyDeployment'!$K$3:$K$7,'Lookups - JourneyDeployment'!$L$3:$L$7),"") | K2: =A2&"|"&B2 | L2: =IFERROR(XLOOKUP(K2,'Activity Settings'!$M$2:$M$200,'Activity Settings'!$J$2:$J$200),0) | M2: =IFERROR(XLOOKUP(K2,'Activity Settings'!$M$2:$M$200,'Activity Settings'!$L$2:$L$200),"Knapsack") | N2: =IFERROR(XLOOKUP(J2&"|"&M2,Rates!$E$2:$E$13,Rates!$C$2:$C$13),0) | O2: =L2*N2
A3: Implementation + Onboarding | B3: Stakeholder Alignment Workshops | C3: Conduct alignment workshops and capture insights | F3: CX Partner - Change Management SME | G3: Adobe | H3: CX Partner | I3: 1–2 | J3: =IFERROR(XLOOKUP(H3,'Lookups - JourneyDeployment'!$K$3:$K$7,'Lookups - JourneyDeployment'!$L$3:$L$7),"") | K3: =A3&"|"&B3 | L3: =IFERROR(XLOOKUP(K3,'Activity Settings'!$M$2:$M$200,'Activity Settings'!$J$2:$J$200),0) | M3: =IFERROR(XLOOKUP(K3,'Activity Settings'!$M$2:$M$200,'Activity Settings'!$L$2:$L$200),"Knapsack") | N3: =IFERROR(XLOOKUP(J3&"|"&M3,Rates!$E$2:$E$13,Rates!$C$2:$C$13),0) | O3: =L3*N3
A4: Implementation + Onboarding | B4: Stakeholder Alignment Workshops | C4: Develop stakeholder map and influence matrix | F4: CX Partner - Change Management SME | G4: Adobe | H4: CX Partner | I4: 1–2 | J4: =IFERROR(XLOOKUP(H4,'Lookups - JourneyDeployment'!$K$3:$K$7,'Lookups - JourneyDeployment'!$L$3:$L$7),"") | K4: =A4&"|"&B4 | L4: =IFERROR(XLOOKUP(K4,'Activity Settings'!$M$2:$M$200,'Activity Settings'!$J$2:$J$200),0) | M4: =IFERROR(XLOOKUP(K4,'Activity Settings'!$M$2:$M$200,'Activity Settings'!$L$2:$L$200),"Knapsack") | N4: =IFERROR(XLOOKUP(J4&"|"&M4,Rates!$E$2:$E$13,Rates!$C$2:$C$13),0) | O4: =L4*N4
A5: Implementation + Onboarding | B5: Stakeholder Alignment Workshops | C5: Draft communication strategy and feedback cadence | F5: CX Partner - Change Management SME | G5: Adobe | H5: CX Partner | I5: 1–2 | J5: =IFERROR(XLOOKUP(H5,'Lookups - JourneyDeployment'!$K$3:$K$7,'Lookups - JourneyDeployment'!$L$3:$L$7),"") | K5: =A5&"|"&B5 | L5: =IFERROR(XLOOKUP(K5,'Activity Settings'!$M$2:$M$200,'Activity Settings'!$J$2:$J$200),0) | M5: =IFERROR(XLOOKUP(K5,'Activity Settings'!$M$2:$M$200,'Activity Settings'!$L$2:$L$200),"Knapsack") | N5: =IFERROR(XLOOKUP(J5&"|"&M5,Rates!$E$2:$E$13,Rates!$C$2:$C$13),0) | O5: =L5*N5
A6: Implementation + Onboarding | B6: Stakeholder Alignment Workshops | C6: Review and sign off communication plan with Steering Committee | D6: Stakeholder Map, Communication Strategy Draft | E6: Ensure executive and stakeholder alignment before kickoff. | F6: CX Partner - Change Management SME | G6: Adobe | H6: CX Partner | I6: 1–2 | J6: =IFERROR(XLOOKUP(H6,'Lookups - JourneyDeployment'!$K$3:$K$7,'Lookups - JourneyDeployment'!$L$3:$L$7),"") | K6: =A6&"|"&B6 | L6: =IFERROR(XLOOKUP(K6,'Activity Settings'!$M$2:$M$200,'Activity Settings'!$J$2:$J$200),0) | M6: =IFERROR(XLOOKUP(K6,'Activity Settings'!$M$2:$M$200,'Activity Settings'!$L$2:$L$200),"Knapsack") | N6: =IFERROR(XLOOKUP(J6&"|"&M6,Rates!$E$2:$E$13,Rates!$C$2:$C$13),0) | O6: =L6*N6
A7: Implementation + Onboarding | B7: Program management and coordination | C7: Establish governance tracker and cadence calendar | F7: Project Manager | G7: Knapsack | H7: Project Manager | I7: 1–20 | J7: =IFERROR(XLOOKUP(H7,'Lookups - JourneyDeployment'!$K$3:$K$7,'Lookups - JourneyDeployment'!$L$3:$L$7),"") | K7: =A7&"|"&B7 | L7: =IFERROR(XLOOKUP(K7,'Activity Settings'!$M$2:$M$200,'Activity Settings'!$J$2:$J$200),0) | M7: =IFERROR(XLOOKUP(K7,'Activity Settings'!$M$2:$M$200,'Activity Settings'!$L$2:$L$200),"Knapsack") | N7: =IFERROR(XLOOKUP(J7&"|"&M7,Rates!$E$2:$E$13,Rates!$C$2:$C$13),0) | O7: =L7*N7
A8: Implementation + Onboarding | B8: Program management and coordination | C8: Schedule weekly syncs and milestone reviews | F8: Project Manager | G8: Knapsack | H8: Project Manager | I8: 1–20 | J8: =IFERROR(XLOOKUP(H8,'Lookups - JourneyDeployment'!$K$3:$K$7,'Lookups - JourneyDeployment'!$L$3:$L$7),"") | K8: =A8&"|"&B8 | L8: =IFERROR(XLOOKUP(K8,'Activity Settings'!$M$2:$M$200,'Activity Settings'!$J$2:$J$200),0) | M8: =IFERROR(XLOOKUP(K8,'Activity Settings'!$M$2:$M$200,'Activity Settings'!$L$2:$L$200),"Knapsack") | N8: =IFERROR(XLOOKUP(J8&"|"&M8,Rates!$E$2:$E$13,Rates!$C$2:$C$13),0) | O8: =L8*N8
A9: Implementation + Onboarding | B9: Program management and coordination | C9: Maintain RAID log | F9: Project Manager | G9: Knapsack | H9: Project Manager | I9: 1–20 | J9: =IFERROR(XLOOKUP(H9,'Lookups - JourneyDeployment'!$K$3:$K$7,'Lookups - JourneyDeployment'!$L$3:$L$7),"") | K9: =A9&"|"&B9 | L9: =IFERROR(XLOOKUP(K9,'Activity Settings'!$M$2:$M$200,'Activity Settings'!$J$2:$J$200),0) | M9: =IFERROR(XLOOKUP(K9,'Activity Settings'!$M$2:$M$200,'Activity Settings'!$L$2:$L$200),"Knapsack") | N9: =IFERROR(XLOOKUP(J9&"|"&M9,Rates!$E$2:$E$13,Rates!$C$2:$C$13),0) | O9: =L9*N9
A10: Implementation + Onboarding | B10: Program management and coordination | C10: Prepare Phase 1 exit and readiness report | F10: Project Manager | G10: Knapsack | H10: Project Manager | I10: 1–20 | J10: =IFERROR(XLOOKUP(H10,'Lookups - JourneyDeployment'!$K$3:$K$7,'Lookups - JourneyDeployment'!$L$3:$L$7),"") | K10: =A10&"|"&B10 | L10: =IFERROR(XLOOKUP(K10,'Activity Settings'!$M$2:$M$200,'Activity Settings'!$J$2:$J$200),0) | M10: =IFERROR(XLOOKUP(K10,'Activity Settings'!$M$2:$M$200,'Activity Settings'!$L$2:$L$200),"Knapsack") | N10: =IFERROR(XLOOKUP(J10&"|"&M10,Rates!$E$2:$E$13,Rates!$C$2:$C$13),0) | O10: =L10*N10
A11: Implementation + Onboarding | B11: Program management and coordination | C11: Present status updates to Adobe Steering Committee | D11: Project Governance Tracker, Phase 1 Exit Report | E11: Program coordination, kickoff, and phase review oversight. | F11: Project Manager | G11: Knapsack | H11: Project Manager | I11: 1–20 | J11: =IFERROR(XLOOKUP(H11,'Lookups - JourneyDeployment'!$K$3:$K$7,'Lookups - JourneyDeployment'!$L$3:$L$7),"") | K11: =A11&"|"&B11 | L11: =IFERROR(XLOOKUP(K11,'Activity Settings'!$M$2:$M$200,'Activity Settings'!$J$2:$J$200),0) | M11: =IFERROR(XLOOKUP(K11,'Activity Settings'!$M$2:$M$200,'Activity Settings'!$L$2:$L$200),"Knapsack") | N11: =IFERROR(XLOOKUP(J11&"|"&M11,Rates!$E$2:$E$13,Rates!$C$2:$C$13),0) | O11: =L11*N11
A12: Implementation + Onboarding | B12: Communication Launch Plan | C12: Create internal messaging and visual identity kit | F12: CX Partner - Change Management SME | G12: Adobe | H12: CX Partner | I12: 3–6 | J12: =IFERROR(XLOOKUP(H12,'Lookups - JourneyDeployment'!$K$3:$K$7,'Lookups - JourneyDeployment'!$L$3:$L$7),"") | K12: =A12&"|"&B12 | L12: =IFERROR(XLOOKUP(K12,'Activity Settings'!$M$2:$M$200,'Activity Settings'!$J$2:$J$200),0) | M12: =IFERROR(XLOOKUP(K12,'Activity Settings'!$M$2:$M$200,'Activity Settings'!$L$2:$L$200),"Knapsack") | N12: =IFERROR(XLOOKUP(J12&"|"&M12,Rates!$E$2:$E$13,Rates!$C$2:$C$13),0) | O12: =L12*N12
A13: Implementation + Onboarding | B13: Communication Launch Plan | C13: Develop launch materials (FAQ, deck, announcement) | F13: CX Partner - Change Management SME | G13: Adobe | H13: CX Partner | I13: 3–6 | J13: =IFERROR(XLOOKUP(H13,'Lookups - JourneyDeployment'!$K$3:$K$7,'Lookups - JourneyDeployment'!$L$3:$L$7),"") | K13: =A13&"|"&B13 | L13: =IFERROR(XLOOKUP(K13,'Activity Settings'!$M$2:$M$200,'Activity Settings'!$J$2:$J$200),0) | M13: =IFERROR(XLOOKUP(K13,'Activity Settings'!$M$2:$M$200,'Activity Settings'!$L$2:$L$200),"Knapsack") | N13: =IFERROR(XLOOKUP(J13&"|"&M13,Rates!$E$2:$E$13,Rates!$C$2:$C$13),0) | O13: =L13*N13
A14: Implementation + Onboarding | B14: Communication Launch Plan | C14: Align with design ops for internal brand tone and channels | F14: CX Partner - Change Management SME | G14: Adobe | H14: CX Partner | I14: 3–6 | J14: =IFERROR(XLOOKUP(H14,'Lookups - JourneyDeployment'!$K$3:$K$7,'Lookups - JourneyDeployment'!$L$3:$L$7),"") | K14: =A14&"|"&B14 | L14: =IFERROR(XLOOKUP(K14,'Activity Settings'!$M$2:$M$200,'Activity Settings'!$J$2:$J$200),0) | M14: =IFERROR(XLOOKUP(K14,'Activity Settings'!$M$2:$M$200,'Activity Settings'!$L$2:$L$200),"Knapsack") | N14: =IFERROR(XLOOKUP(J14&"|"&M14,Rates!$E$2:$E$13,Rates!$C$2:$C$13),0) | O14: =L14*N14
A15: Implementation + Onboarding | B15: Communication Launch Plan | C15: Distribute campaign via Adobe internal comms | F15: CX Partner - Change Management SME | G15: Adobe | H15: CX Partner | I15: 3–6 | J15: =IFERROR(XLOOKUP(H15,'Lookups - JourneyDeployment'!$K$3:$K$7,'Lookups - JourneyDeployment'!$L$3:$L$7),"") | K15: =A15&"|"&B15 | L15: =IFERROR(XLOOKUP(K15,'Activity Settings'!$M$2:$M$200,'Activity Settings'!$J$2:$J$200),0) | M15: =IFERROR(XLOOKUP(K15,'Activity Settings'!$M$2:$M$200,'Activity Settings'!$L$2:$L$200),"Knapsack") | N15: =IFERROR(XLOOKUP(J15&"|"&M15,Rates!$E$2:$E$13,Rates!$C$2:$C$13),0) | O15: =L15*N15
A16: Implementation + Onboarding | B16: Communication Launch Plan | C16: Gather feedback and refine messaging | D16: Internal Communication Plan, Branding Package | E16: Launch program messaging, goals, and brand identity across teams. | F16: CX Partner - Change Management SME | G16: Adobe | H16: CX Partner | I16: 3–6 | J16: =IFERROR(XLOOKUP(H16,'Lookups - JourneyDeployment'!$K$3:$K$7,'Lookups - JourneyDeployment'!$L$3:$L$7),"") | K16: =A16&"|"&B16 | L16: =IFERROR(XLOOKUP(K16,'Activity Settings'!$M$2:$M$200,'Activity Settings'!$J$2:$J$200),0) | M16: =IFERROR(XLOOKUP(K16,'Activity Settings'!$M$2:$M$200,'Activity Settings'!$L$2:$L$200),"Knapsack") | N16: =IFERROR(XLOOKUP(J16&"|"&M16,Rates!$E$2:$E$13,Rates!$C$2:$C$13),0) | O16: =L16*N16
A17: Implementation + Onboarding | B17: Preparation | C17: Conduct environment readiness check | F17: Project Manager | G17: Knapsack | H17: Project Manager | I17: 7–10 | J17: =IFERROR(XLOOKUP(H17,'Lookups - JourneyDeployment'!$K$3:$K$7,'Lookups - JourneyDeployment'!$L$3:$L$7),"") | K17: =A17&"|"&B17 | L17: =IFERROR(XLOOKUP(K17,'Activity Settings'!$M$2:$M$200,'Activity Settings'!$J$2:$J$200),0) | M17: =IFERROR(XLOOKUP(K17,'Activity Settings'!$M$2:$M$200,'Activity Settings'!$L$2:$L$200),"Knapsack") | N17: =IFERROR(XLOOKUP(J17&"|"&M17,Rates!$E$2:$E$13,Rates!$C$2:$C$13),0) | O17: =L17*N17
A18: Implementation + Onboarding | B18: Preparation | C18: Validate API and endpoint configuration | F18: Project Manager | G18: Knapsack | H18: Project Manager | I18: 7–10 | J18: =IFERROR(XLOOKUP(H18,'Lookups - JourneyDeployment'!$K$3:$K$7,'Lookups - JourneyDeployment'!$L$3:$L$7),"") | K18: =A18&"|"&B18 | L18: =IFERROR(XLOOKUP(K18,'Activity Settings'!$M$2:$M$200,'Activity Settings'!$J$2:$J$200),0) | M18: =IFERROR(XLOOKUP(K18,'Activity Settings'!$M$2:$M$200,'Activity Settings'!$L$2:$L$200),"Knapsack") | N18: =IFERROR(XLOOKUP(J18&"|"&M18,Rates!$E$2:$E$13,Rates!$C$2:$C$13),0) | O18: =L18*N18
A19: Implementation + Onboarding | B19: Preparation | C19: Verify authentication and permissions access | F19: Project Manager | G19: Knapsack | H19: Project Manager | I19: 7–10 | J19: =IFERROR(XLOOKUP(H19,'Lookups - JourneyDeployment'!$K$3:$K$7,'Lookups - JourneyDeployment'!$L$3:$L$7),"") | K19: =A19&"|"&B19 | L19: =IFERROR(XLOOKUP(K19,'Activity Settings'!$M$2:$M$200,'Activity Settings'!$J$2:$J$200),0) | M19: =IFERROR(XLOOKUP(K19,'Activity Settings'!$M$2:$M$200,'Activity Settings'!$L$2:$L$200),"Knapsack") | N19: =IFERROR(XLOOKUP(J19&"|"&M19,Rates!$E$2:$E$13,Rates!$C$2:$C$13),0) | O19: =L19*N19
A20: Implementation + Onboarding | B20: Preparation | C20: Confirm hosting and network compliance | F20: Project Manager | G20: Knapsack | H20: Project Manager | I20: 7–10 | J20: =IFERROR(XLOOKUP(H20,'Lookups - JourneyDeployment'!$K$3:$K$7,'Lookups - JourneyDeployment'!$L$3:$L$7),"") | K20: =A20&"|"&B20 | L20: =IFERROR(XLOOKUP(K20,'Activity Settings'!$M$2:$M$200,'Activity Settings'!$J$2:$J$200),0) | M20: =IFERROR(XLOOKUP(K20,'Activity Settings'!$M$2:$M$200,'Activity Settings'!$L$2:$L$200),"Knapsack") | N20: =IFERROR(XLOOKUP(J20&"|"&M20,Rates!$E$2:$E$13,Rates!$C$2:$C$13),0) | O20: =L20*N20
A21: Implementation + Onboarding | B21: Preparation | C21: Document results in Technical Readiness Checklist | D21: Technical Readiness Checklist | E21: Verify infrastructure readiness, environment setup, and permissions. | F21: Project Manager | G21: Knapsack | H21: Project Manager | I21: 7–10 | J21: =IFERROR(XLOOKUP(H21,'Lookups - JourneyDeployment'!$K$3:$K$7,'Lookups - JourneyDeployment'!$L$3:$L$7),"") | K21: =A21&"|"&B21 | L21: =IFERROR(XLOOKUP(K21,'Activity Settings'!$M$2:$M$200,'Activity Settings'!$J$2:$J$200),0) | M21: =IFERROR(XLOOKUP(K21,'Activity Settings'!$M$2:$M$200,'Activity Settings'!$L$2:$L$200),"Knapsack") | N21: =IFERROR(XLOOKUP(J21&"|"&M21,Rates!$E$2:$E$13,Rates!$C$2:$C$13),0) | O21: =L21*N21
A22: Implementation + Onboarding | B22: Local install support | C22: Provide installation guide and validation checklist | F22: Senior Solutions Engineer | G22: Knapsack | H22: Engineer | I22: 7–10 | J22: =IFERROR(XLOOKUP(H22,'Lookups - JourneyDeployment'!$K$3:$K$7,'Lookups - JourneyDeployment'!$L$3:$L$7),"") | K22: =A22&"|"&B22 | L22: =IFERROR(XLOOKUP(K22,'Activity Settings'!$M$2:$M$200,'Activity Settings'!$J$2:$J$200),0) | M22: =IFERROR(XLOOKUP(K22,'Activity Settings'!$M$2:$M$200,'Activity Settings'!$L$2:$L$200),"Knapsack") | N22: =IFERROR(XLOOKUP(J22&"|"&M22,Rates!$E$2:$E$13,Rates!$C$2:$C$13),0) | O22: =L22*N22
A23: Implementation + Onboarding | B23: Local install support | C23: Support local environment configuration | F23: Senior Solutions Engineer | G23: Knapsack | H23: Engineer | I23: 7–10 | J23: =IFERROR(XLOOKUP(H23,'Lookups - JourneyDeployment'!$K$3:$K$7,'Lookups - JourneyDeployment'!$L$3:$L$7),"") | K23: =A23&"|"&B23 | L23: =IFERROR(XLOOKUP(K23,'Activity Settings'!$M$2:$M$200,'Activity Settings'!$J$2:$J$200),0) | M23: =IFERROR(XLOOKUP(K23,'Activity Settings'!$M$2:$M$200,'Activity Settings'!$L$2:$L$200),"Knapsack") | N23: =IFERROR(XLOOKUP(J23&"|"&M23,Rates!$E$2:$E$13,Rates!$C$2:$C$13),0) | O23: =L23*N23
A24: Implementation + Onboarding | B24: Local install support | C24: Troubleshoot integration issues | F24: Senior Solutions Engineer | G24: Knapsack | H24: Engineer | I24: 7–10 | J24: =IFERROR(XLOOKUP(H24,'Lookups - JourneyDeployment'!$K$3:$K$7,'Lookups - JourneyDeployment'!$L$3:$L$7),"") | K24: =A24&"|"&B24 | L24: =IFERROR(XLOOKUP(K24,'Activity Settings'!$M$2:$M$200,'Activity Settings'!$J$2:$J$200),0) | M24: =IFERROR(XLOOKUP(K24,'Activity Settings'!$M$2:$M$200,'Activity Settings'!$L$2:$L$200),"Knapsack") | N24: =IFERROR(XLOOKUP(J24&"|"&M24,Rates!$E$2:$E$13,Rates!$C$2:$C$13),0) | O24: =L24*N24
A25: Implementation + Onboarding | B25: Local install support | C25: Validate connectivity with IPE components | F25: Senior Solutions Engineer | G25: Knapsack | H25: Engineer | I25: 7–10 | J25: =IFERROR(XLOOKUP(H25,'Lookups - JourneyDeployment'!$K$3:$K$7,'Lookups - JourneyDeployment'!$L$3:$L$7),"") | K25: =A25&"|"&B25 | L25: =IFERROR(XLOOKUP(K25,'Activity Settings'!$M$2:$M$200,'Activity Settings'!$J$2:$J$200),0) | M25: =IFERROR(XLOOKUP(K25,'Activity Settings'!$M$2:$M$200,'Activity Settings'!$L$2:$L$200),"Knapsack") | N25: =IFERROR(XLOOKUP(J25&"|"&M25,Rates!$E$2:$E$13,Rates!$C$2:$C$13),0) | O25: =L25*N25
A26: Implementation + Onboarding | B26: Local install support | C26: Log and close install-related tickets | D26: Installation Validation Report | E26: Validate local environment setup for Knapsack and IPE components. | F26: Senior Solutions Engineer | G26: Knapsack | H26: Engineer | I26: 7–10 | J26: =IFERROR(XLOOKUP(H26,'Lookups - JourneyDeployment'!$K$3:$K$7,'Lookups - JourneyDeployment'!$L$3:$L$7),"") | K26: =A26&"|"&B26 | L26: =IFERROR(XLOOKUP(K26,'Activity Settings'!$M$2:$M$200,'Activity Settings'!$J$2:$J$200),0) | M26: =IFERROR(XLOOKUP(K26,'Activity Settings'!$M$2:$M$200,'Activity Settings'!$L$2:$L$200),"Knapsack") | N26: =IFERROR(XLOOKUP(J26&"|"&M26,Rates!$E$2:$E$13,Rates!$C$2:$C$13),0) | O26: =L26*N26
A27: Implementation + Onboarding | B27: Component rendering | C27: Validate core Spectrum components rendering | F27: Senior Solutions Engineer | G27: Knapsack | H27: Engineer | I27: 7–10 | J27: =IFERROR(XLOOKUP(H27,'Lookups - JourneyDeployment'!$K$3:$K$7,'Lookups - JourneyDeployment'!$L$3:$L$7),"") | K27: =A27&"|"&B27 | L27: =IFERROR(XLOOKUP(K27,'Activity Settings'!$M$2:$M$200,'Activity Settings'!$J$2:$J$200),0) | M27: =IFERROR(XLOOKUP(K27,'Activity Settings'!$M$2:$M$200,'Activity Settings'!$L$2:$L$200),"Knapsack") | N27: =IFERROR(XLOOKUP(J27&"|"&M27,Rates!$E$2:$E$13,Rates!$C$2:$C$13),0) | O27: =L27*N27
A28: Implementation + Onboarding | B28: Component rendering | C28: Conduct visual and functional QA across environments | F28: Senior Solutions Engineer | G28: Knapsack | H28: Engineer | I28: 7–10 | J28: =IFERROR(XLOOKUP(H28,'Lookups - JourneyDeployment'!$K$3:$K$7,'Lookups - JourneyDeployment'!$L$3:$L$7),"") | K28: =A28&"|"&B28 | L28: =IFERROR(XLOOKUP(K28,'Activity Settings'!$M$2:$M$200,'Activity Settings'!$J$2:$J$200),0) | M28: =IFERROR(XLOOKUP(K28,'Activity Settings'!$M$2:$M$200,'Activity Settings'!$L$2:$L$200),"Knapsack") | N28: =IFERROR(XLOOKUP(J28&"|"&M28,Rates!$E$2:$E$13,Rates!$C$2:$C$13),0) | O28: =L28*N28
A29: Implementation + Onboarding | B29: Component rendering | C29: Compare results with baseline expectations | F29: Senior Solutions Engineer | G29: Knapsack | H29: Engineer | I29: 7–10 | J29: =IFERROR(XLOOKUP(H29,'Lookups - JourneyDeployment'!$K$3:$K$7,'Lookups - JourneyDeployment'!$L$3:$L$7),"") | K29: =A29&"|"&B29 | L29: =IFERROR(XLOOKUP(K29,'Activity Settings'!$M$2:$M$200,'Activity Settings'!$J$2:$J$200),0) | M29: =IFERROR(XLOOKUP(K29,'Activity Settings'!$M$2:$M$200,'Activity Settings'!$L$2:$L$200),"Knapsack") | N29: =IFERROR(XLOOKUP(J29&"|"&M29,Rates!$E$2:$E$13,Rates!$C$2:$C$13),0) | O29: =L29*N29
A30: Implementation + Onboarding | B30: Component rendering | C30: Document rendering test summary report | F30: Senior Solutions Engineer | G30: Knapsack | H30: Engineer | I30: 7–10 | J30: =IFERROR(XLOOKUP(H30,'Lookups - JourneyDeployment'!$K$3:$K$7,'Lookups - JourneyDeployment'!$L$3:$L$7),"") | K30: =A30&"|"&B30 | L30: =IFERROR(XLOOKUP(K30,'Activity Settings'!$M$2:$M$200,'Activity Settings'!$J$2:$J$200),0) | M30: =IFERROR(XLOOKUP(K30,'Activity Settings'!$M$2:$M$200,'Activity Settings'!$L$2:$L$200),"Knapsack") | N30: =IFERROR(XLOOKUP(J30&"|"&M30,Rates!$E$2:$E$13,Rates!$C$2:$C$13),0) | O30: =L30*N30
A31: Implementation + Onboarding | B31: Component rendering | C31: Submit remediation recommendations | D31: Rendering QA Report | E31: Validate successful rendering of Spectrum components across environments. | F31: Senior Solutions Engineer | G31: Knapsack | H31: Engineer | I31: 7–10 | J31: =IFERROR(XLOOKUP(H31,'Lookups - JourneyDeployment'!$K$3:$K$7,'Lookups - JourneyDeployment'!$L$3:$L$7),"") | K31: =A31&"|"&B31 | L31: =IFERROR(XLOOKUP(K31,'Activity Settings'!$M$2:$M$200,'Activity Settings'!$J$2:$J$200),0) | M31: =IFERROR(XLOOKUP(K31,'Activity Settings'!$M$2:$M$200,'Activity Settings'!$L$2:$L$200),"Knapsack") | N31: =IFERROR(XLOOKUP(J31&"|"&M31,Rates!$E$2:$E$13,Rates!$C$2:$C$13),0) | O31: =L31*N31
A32: Implementation + Onboarding | B32: SME support for rendering | C32: Review component architecture and consistency | F32: Subject Matter Expert | G32: Knapsack | H32: SME | I32: 7–10 | J32: =IFERROR(XLOOKUP(H32,'Lookups - JourneyDeployment'!$K$3:$K$7,'Lookups - JourneyDeployment'!$L$3:$L$7),"") | K32: =A32&"|"&B32 | L32: =IFERROR(XLOOKUP(K32,'Activity Settings'!$M$2:$M$200,'Activity Settings'!$J$2:$J$200),0) | M32: =IFERROR(XLOOKUP(K32,'Activity Settings'!$M$2:$M$200,'Activity Settings'!$L$2:$L$200),"Knapsack") | N32: =IFERROR(XLOOKUP(J32&"|"&M32,Rates!$E$2:$E$13,Rates!$C$2:$C$13),0) | O32: =L32*N32
A33: Implementation + Onboarding | B33: SME support for rendering | C33: Audit rendering pipeline and dependency mapping | F33: Subject Matter Expert | G33: Knapsack | H33: SME | I33: 7–10 | J33: =IFERROR(XLOOKUP(H33,'Lookups - JourneyDeployment'!$K$3:$K$7,'Lookups - JourneyDeployment'!$L$3:$L$7),"") | K33: =A33&"|"&B33 | L33: =IFERROR(XLOOKUP(K33,'Activity Settings'!$M$2:$M$200,'Activity Settings'!$J$2:$J$200),0) | M33: =IFERROR(XLOOKUP(K33,'Activity Settings'!$M$2:$M$200,'Activity Settings'!$L$2:$L$200),"Knapsack") | N33: =IFERROR(XLOOKUP(J33&"|"&M33,Rates!$E$2:$E$13,Rates!$C$2:$C$13),0) | O33: =L33*N33
A34: Implementation + Onboarding | B34: SME support for rendering | C34: Validate accessibility compliance | F34: Subject Matter Expert | G34: Knapsack | H34: SME | I34: 7–10 | J34: =IFERROR(XLOOKUP(H34,'Lookups - JourneyDeployment'!$K$3:$K$7,'Lookups - JourneyDeployment'!$L$3:$L$7),"") | K34: =A34&"|"&B34 | L34: =IFERROR(XLOOKUP(K34,'Activity Settings'!$M$2:$M$200,'Activity Settings'!$J$2:$J$200),0) | M34: =IFERROR(XLOOKUP(K34,'Activity Settings'!$M$2:$M$200,'Activity Settings'!$L$2:$L$200),"Knapsack") | N34: =IFERROR(XLOOKUP(J34&"|"&M34,Rates!$E$2:$E$13,Rates!$C$2:$C$13),0) | O34: =L34*N34
A35: Implementation + Onboarding | B35: SME support for rendering | C35: Provide expert input to engineering team | F35: Subject Matter Expert | G35: Knapsack | H35: SME | I35: 7–10 | J35: =IFERROR(XLOOKUP(H35,'Lookups - JourneyDeployment'!$K$3:$K$7,'Lookups - JourneyDeployment'!$L$3:$L$7),"") | K35: =A35&"|"&B35 | L35: =IFERROR(XLOOKUP(K35,'Activity Settings'!$M$2:$M$200,'Activity Settings'!$J$2:$J$200),0) | M35: =IFERROR(XLOOKUP(K35,'Activity Settings'!$M$2:$M$200,'Activity Settings'!$L$2:$L$200),"Knapsack") | N35: =IFERROR(XLOOKUP(J35&"|"&M35,Rates!$E$2:$E$13,Rates!$C$2:$C$13),0) | O35: =L35*N35
A36: Implementation + Onboarding | B36: SME support for rendering | C36: Approve Architecture Validation Log | D36: Architecture Validation Log | E36: SME oversight of rendering logic and architectural consistency. | F36: Subject Matter Expert | G36: Knapsack | H36: SME | I36: 7–10 | J36: =IFERROR(XLOOKUP(H36,'Lookups - JourneyDeployment'!$K$3:$K$7,'Lookups - JourneyDeployment'!$L$3:$L$7),"") | K36: =A36&"|"&B36 | L36: =IFERROR(XLOOKUP(K36,'Activity Settings'!$M$2:$M$200,'Activity Settings'!$J$2:$J$200),0) | M36: =IFERROR(XLOOKUP(K36,'Activity Settings'!$M$2:$M$200,'Activity Settings'!$L$2:$L$200),"Knapsack") | N36: =IFERROR(XLOOKUP(J36&"|"&M36,Rates!$E$2:$E$13,Rates!$C$2:$C$13),0) | O36: =L36*N36
A37: Implementation + Onboarding | B37: Deployment support | C37: Define deployment workflow and CI/CD configuration | F37: Senior Solutions Engineer | G37: Knapsack | H37: Engineer | I37: 15–20 | J37: =IFERROR(XLOOKUP(H37,'Lookups - JourneyDeployment'!$K$3:$K$7,'Lookups - JourneyDeployment'!$L$3:$L$7),"") | K37: =A37&"|"&B37 | L37: =IFERROR(XLOOKUP(K37,'Activity Settings'!$M$2:$M$200,'Activity Settings'!$J$2:$J$200),0) | M37: =IFERROR(XLOOKUP(K37,'Activity Settings'!$M$2:$M$200,'Activity Settings'!$L$2:$L$200),"Knapsack") | N37: =IFERROR(XLOOKUP(J37&"|"&M37,Rates!$E$2:$E$13,Rates!$C$2:$C$13),0) | O37: =L37*N37
A38: Implementation + Onboarding | B38: Deployment support | C38: Create rollback and versioning process | F38: Senior Solutions Engineer | G38: Knapsack | H38: Engineer | I38: 15–20 | J38: =IFERROR(XLOOKUP(H38,'Lookups - JourneyDeployment'!$K$3:$K$7,'Lookups - JourneyDeployment'!$L$3:$L$7),"") | K38: =A38&"|"&B38 | L38: =IFERROR(XLOOKUP(K38,'Activity Settings'!$M$2:$M$200,'Activity Settings'!$J$2:$J$200),0) | M38: =IFERROR(XLOOKUP(K38,'Activity Settings'!$M$2:$M$200,'Activity Settings'!$L$2:$L$200),"Knapsack") | N38: =IFERROR(XLOOKUP(J38&"|"&M38,Rates!$E$2:$E$13,Rates!$C$2:$C$13),0) | O38: =L38*N38
A39: Implementation + Onboarding | B39: Deployment support | C39: Run initial deployment test | F39: Senior Solutions Engineer | G39: Knapsack | H39: Engineer | I39: 15–20 | J39: =IFERROR(XLOOKUP(H39,'Lookups - JourneyDeployment'!$K$3:$K$7,'Lookups - JourneyDeployment'!$L$3:$L$7),"") | K39: =A39&"|"&B39 | L39: =IFERROR(XLOOKUP(K39,'Activity Settings'!$M$2:$M$200,'Activity Settings'!$J$2:$J$200),0) | M39: =IFERROR(XLOOKUP(K39,'Activity Settings'!$M$2:$M$200,'Activity Settings'!$L$2:$L$200),"Knapsack") | N39: =IFERROR(XLOOKUP(J39&"|"&M39,Rates!$E$2:$E$13,Rates!$C$2:$C$13),0) | O39: =L39*N39
A40: Implementation + Onboarding | B40: Deployment support | C40: Record metrics against success criteria | F40: Senior Solutions Engineer | G40: Knapsack | H40: Engineer | I40: 15–20 | J40: =IFERROR(XLOOKUP(H40,'Lookups - JourneyDeployment'!$K$3:$K$7,'Lookups - JourneyDeployment'!$L$3:$L$7),"") | K40: =A40&"|"&B40 | L40: =IFERROR(XLOOKUP(K40,'Activity Settings'!$M$2:$M$200,'Activity Settings'!$J$2:$J$200),0) | M40: =IFERROR(XLOOKUP(K40,'Activity Settings'!$M$2:$M$200,'Activity Settings'!$L$2:$L$200),"Knapsack") | N40: =IFERROR(XLOOKUP(J40&"|"&M40,Rates!$E$2:$E$13,Rates!$C$2:$C$13),0) | O40: =L40*N40
A41: Implementation + Onboarding | B41: Deployment support | C41: Approve Deployment Plan and Success Metrics | D41: Deployment Plan + Success Metrics | E41: Plan and validate deployment pipelines with measurable success criteria. | F41: Senior Solutions Engineer | G41: Knapsack | H41: Engineer | I41: 15–20 | J41: =IFERROR(XLOOKUP(H41,'Lookups - JourneyDeployment'!$K$3:$K$7,'Lookups - JourneyDeployment'!$L$3:$L$7),"") | K41: =A41&"|"&B41 | L41: =IFERROR(XLOOKUP(K41,'Activity Settings'!$M$2:$M$200,'Activity Settings'!$J$2:$J$200),0) | M41: =IFERROR(XLOOKUP(K41,'Activity Settings'!$M$2:$M$200,'Activity Settings'!$L$2:$L$200),"Knapsack") | N41: =IFERROR(XLOOKUP(J41&"|"&M41,Rates!$E$2:$E$13,Rates!$C$2:$C$13),0) | O41: =L41*N41
A42: Scaled Rollout and Adoption | B42: Program management and Steering Committee coordination | C42: Conduct bi-weekly stand-ups with stakeholders | F42: Project Manager | G42: Adobe | H42: Project Manager | I42: 21–32 | J42: =IFERROR(XLOOKUP(H42,'Lookups - JourneyDeployment'!$K$3:$K$7,'Lookups - JourneyDeployment'!$L$3:$L$7),"") | K42: =A42&"|"&B42 | L42: =IFERROR(XLOOKUP(K42,'Activity Settings'!$M$2:$M$200,'Activity Settings'!$J$2:$J$200),0) | M42: =IFERROR(XLOOKUP(K42,'Activity Settings'!$M$2:$M$200,'Activity Settings'!$L$2:$L$200),"Knapsack") | N42: =IFERROR(XLOOKUP(J42&"|"&M42,Rates!$E$2:$E$13,Rates!$C$2:$C$13),0) | O42: =L42*N42
A43: Scaled Rollout and Adoption | B43: Program management and Steering Committee coordination | C43: Prepare monthly summary reports | F43: Project Manager | G43: Adobe | H43: Project Manager | I43: 21–32 | J43: =IFERROR(XLOOKUP(H43,'Lookups - JourneyDeployment'!$K$3:$K$7,'Lookups - JourneyDeployment'!$L$3:$L$7),"") | K43: =A43&"|"&B43 | L43: =IFERROR(XLOOKUP(K43,'Activity Settings'!$M$2:$M$200,'Activity Settings'!$J$2:$J$200),0) | M43: =IFERROR(XLOOKUP(K43,'Activity Settings'!$M$2:$M$200,'Activity Settings'!$L$2:$L$200),"Knapsack") | N43: =IFERROR(XLOOKUP(J43&"|"&M43,Rates!$E$2:$E$13,Rates!$C$2:$C$13),0) | O43: =L43*N43
A44: Scaled Rollout and Adoption | B44: Program management and Steering Committee coordination | C44: Track progress against milestones | F44: Project Manager | G44: Adobe | H44: Project Manager | I44: 21–32 | J44: =IFERROR(XLOOKUP(H44,'Lookups - JourneyDeployment'!$K$3:$K$7,'Lookups - JourneyDeployment'!$L$3:$L$7),"") | K44: =A44&"|"&B44 | L44: =IFERROR(XLOOKUP(K44,'Activity Settings'!$M$2:$M$200,'Activity Settings'!$J$2:$J$200),0) | M44: =IFERROR(XLOOKUP(K44,'Activity Settings'!$M$2:$M$200,'Activity Settings'!$L$2:$L$200),"Knapsack") | N44: =IFERROR(XLOOKUP(J44&"|"&M44,Rates!$E$2:$E$13,Rates!$C$2:$C$13),0) | O44: =L44*N44
A45: Scaled Rollout and Adoption | B45: Program management and Steering Committee coordination | C45: Facilitate phase-gate review sessions | F45: Project Manager | G45: Adobe | H45: Project Manager | I45: 21–32 | J45: =IFERROR(XLOOKUP(H45,'Lookups - JourneyDeployment'!$K$3:$K$7,'Lookups - JourneyDeployment'!$L$3:$L$7),"") | K45: =A45&"|"&B45 | L45: =IFERROR(XLOOKUP(K45,'Activity Settings'!$M$2:$M$200,'Activity Settings'!$J$2:$J$200),0) | M45: =IFERROR(XLOOKUP(K45,'Activity Settings'!$M$2:$M$200,'Activity Settings'!$L$2:$L$200),"Knapsack") | N45: =IFERROR(XLOOKUP(J45&"|"&M45,Rates!$E$2:$E$13,Rates!$C$2:$C$13),0) | O45: =L45*N45
A46: Scaled Rollout and Adoption | B46: Program management and Steering Committee coordination | C46: Update Governance Toolkit documents | D46: Governance Toolkit + Monthly Summary Reports | E46: Kickoff, bi-weekly stand-ups, monthly reports, phase gate reviews. | F46: Project Manager | G46: Adobe | H46: Project Manager | I46: 21–32 | J46: =IFERROR(XLOOKUP(H46,'Lookups - JourneyDeployment'!$K$3:$K$7,'Lookups - JourneyDeployment'!$L$3:$L$7),"") | K46: =A46&"|"&B46 | L46: =IFERROR(XLOOKUP(K46,'Activity Settings'!$M$2:$M$200,'Activity Settings'!$J$2:$J$200),0) | M46: =IFERROR(XLOOKUP(K46,'Activity Settings'!$M$2:$M$200,'Activity Settings'!$L$2:$L$200),"Knapsack") | N46: =IFERROR(XLOOKUP(J46&"|"&M46,Rates!$E$2:$E$13,Rates!$C$2:$C$13),0) | O46: =L46*N46
A47: Scaled Rollout and Adoption | B47: Facilitating and supporting deliverables | C47: Collect adoption and engagement metrics | F47: CX Partner - Change Management SME | G47: Adobe | H47: CX Partner | I47: 21–32 | J47: =IFERROR(XLOOKUP(H47,'Lookups - JourneyDeployment'!$K$3:$K$7,'Lookups - JourneyDeployment'!$L$3:$L$7),"") | K47: =A47&"|"&B47 | L47: =IFERROR(XLOOKUP(K47,'Activity Settings'!$M$2:$M$200,'Activity Settings'!$J$2:$J$200),0) | M47: =IFERROR(XLOOKUP(K47,'Activity Settings'!$M$2:$M$200,'Activity Settings'!$L$2:$L$200),"Knapsack") | N47: =IFERROR(XLOOKUP(J47&"|"&M47,Rates!$E$2:$E$13,Rates!$C$2:$C$13),0) | O47: =L47*N47
A48: Scaled Rollout and Adoption | B48: Facilitating and supporting deliverables | C48: Populate dashboard with KPIs | F48: CX Partner - Change Management SME | G48: Adobe | H48: CX Partner | I48: 21–32 | J48: =IFERROR(XLOOKUP(H48,'Lookups - JourneyDeployment'!$K$3:$K$7,'Lookups - JourneyDeployment'!$L$3:$L$7),"") | K48: =A48&"|"&B48 | L48: =IFERROR(XLOOKUP(K48,'Activity Settings'!$M$2:$M$200,'Activity Settings'!$J$2:$J$200),0) | M48: =IFERROR(XLOOKUP(K48,'Activity Settings'!$M$2:$M$200,'Activity Settings'!$L$2:$L$200),"Knapsack") | N48: =IFERROR(XLOOKUP(J48&"|"&M48,Rates!$E$2:$E$13,Rates!$C$2:$C$13),0) | O48: =L48*N48
A49: Scaled Rollout and Adoption | B49: Facilitating and supporting deliverables | C49: Review metrics with CX Partner and PM | F49: CX Partner - Change Management SME | G49: Adobe | H49: CX Partner | I49: 21–32 | J49: =IFERROR(XLOOKUP(H49,'Lookups - JourneyDeployment'!$K$3:$K$7,'Lookups - JourneyDeployment'!$L$3:$L$7),"") | K49: =A49&"|"&B49 | L49: =IFERROR(XLOOKUP(K49,'Activity Settings'!$M$2:$M$200,'Activity Settings'!$J$2:$J$200),0) | M49: =IFERROR(XLOOKUP(K49,'Activity Settings'!$M$2:$M$200,'Activity Settings'!$L$2:$L$200),"Knapsack") | N49: =IFERROR(XLOOKUP(J49&"|"&M49,Rates!$E$2:$E$13,Rates!$C$2:$C$13),0) | O49: =L49*N49
A50: Scaled Rollout and Adoption | B50: Facilitating and supporting deliverables | C50: Recommend improvements for lagging metrics | F50: CX Partner - Change Management SME | G50: Adobe | H50: CX Partner | I50: 21–32 | J50: =IFERROR(XLOOKUP(H50,'Lookups - JourneyDeployment'!$K$3:$K$7,'Lookups - JourneyDeployment'!$L$3:$L$7),"") | K50: =A50&"|"&B50 | L50: =IFERROR(XLOOKUP(K50,'Activity Settings'!$M$2:$M$200,'Activity Settings'!$J$2:$J$200),0) | M50: =IFERROR(XLOOKUP(K50,'Activity Settings'!$M$2:$M$200,'Activity Settings'!$L$2:$L$200),"Knapsack") | N50: =IFERROR(XLOOKUP(J50&"|"&M50,Rates!$E$2:$E$13,Rates!$C$2:$C$13),0) | O50: =L50*N50
A51: Scaled Rollout and Adoption | B51: Facilitating and supporting deliverables | C51: Share monthly change-management insights | D51: Change Management Dashboard | E51: Track adoption metrics, stakeholder engagement, and training completion. | F51: CX Partner - Change Management SME | G51: Adobe | H51: CX Partner | I51: 21–32 | J51: =IFERROR(XLOOKUP(H51,'Lookups - JourneyDeployment'!$K$3:$K$7,'Lookups - JourneyDeployment'!$L$3:$L$7),"") | K51: =A51&"|"&B51 | L51: =IFERROR(XLOOKUP(K51,'Activity Settings'!$M$2:$M$200,'Activity Settings'!$J$2:$J$200),0) | M51: =IFERROR(XLOOKUP(K51,'Activity Settings'!$M$2:$M$200,'Activity Settings'!$L$2:$L$200),"Knapsack") | N51: =IFERROR(XLOOKUP(J51&"|"&M51,Rates!$E$2:$E$13,Rates!$C$2:$C$13),0) | O51: =L51*N51
A52: Scaled Rollout and Adoption | B52: Change Readiness Assessment | C52: Draft readiness survey and baseline questions | F52: CX Partner - Change Management SME | G52: Adobe | H52: CX Partner | I52: 21–24 | J52: =IFERROR(XLOOKUP(H52,'Lookups - JourneyDeployment'!$K$3:$K$7,'Lookups - JourneyDeployment'!$L$3:$L$7),"") | K52: =A52&"|"&B52 | L52: =IFERROR(XLOOKUP(K52,'Activity Settings'!$M$2:$M$200,'Activity Settings'!$J$2:$J$200),0) | M52: =IFERROR(XLOOKUP(K52,'Activity Settings'!$M$2:$M$200,'Activity Settings'!$L$2:$L$200),"Knapsack") | N52: =IFERROR(XLOOKUP(J52&"|"&M52,Rates!$E$2:$E$13,Rates!$C$2:$C$13),0) | O52: =L52*N52
A53: Scaled Rollout and Adoption | B53: Change Readiness Assessment | C53: Conduct assessment sessions | F53: CX Partner - Change Management SME | G53: Adobe | H53: CX Partner | I53: 21–24 | J53: =IFERROR(XLOOKUP(H53,'Lookups - JourneyDeployment'!$K$3:$K$7,'Lookups - JourneyDeployment'!$L$3:$L$7),"") | K53: =A53&"|"&B53 | L53: =IFERROR(XLOOKUP(K53,'Activity Settings'!$M$2:$M$200,'Activity Settings'!$J$2:$J$200),0) | M53: =IFERROR(XLOOKUP(K53,'Activity Settings'!$M$2:$M$200,'Activity Settings'!$L$2:$L$200),"Knapsack") | N53: =IFERROR(XLOOKUP(J53&"|"&M53,Rates!$E$2:$E$13,Rates!$C$2:$C$13),0) | O53: =L53*N53
A54: Scaled Rollout and Adoption | B54: Change Readiness Assessment | C54: Analyze cultural and operational preparedness | F54: CX Partner - Change Management SME | G54: Adobe | H54: CX Partner | I54: 21–24 | J54: =IFERROR(XLOOKUP(H54,'Lookups - JourneyDeployment'!$K$3:$K$7,'Lookups - JourneyDeployment'!$L$3:$L$7),"") | K54: =A54&"|"&B54 | L54: =IFERROR(XLOOKUP(K54,'Activity Settings'!$M$2:$M$200,'Activity Settings'!$J$2:$J$200),0) | M54: =IFERROR(XLOOKUP(K54,'Activity Settings'!$M$2:$M$200,'Activity Settings'!$L$2:$L$200),"Knapsack") | N54: =IFERROR(XLOOKUP(J54&"|"&M54,Rates!$E$2:$E$13,Rates!$C$2:$C$13),0) | O54: =L54*N54
A55: Scaled Rollout and Adoption | B55: Change Readiness Assessment | C55: Summarize results in Readiness Index | F55: CX Partner - Change Management SME | G55: Adobe | H55: CX Partner | I55: 21–24 | J55: =IFERROR(XLOOKUP(H55,'Lookups - JourneyDeployment'!$K$3:$K$7,'Lookups - JourneyDeployment'!$L$3:$L$7),"") | K55: =A55&"|"&B55 | L55: =IFERROR(XLOOKUP(K55,'Activity Settings'!$M$2:$M$200,'Activity Settings'!$J$2:$J$200),0) | M55: =IFERROR(XLOOKUP(K55,'Activity Settings'!$M$2:$M$200,'Activity Settings'!$L$2:$L$200),"Knapsack") | N55: =IFERROR(XLOOKUP(J55&"|"&M55,Rates!$E$2:$E$13,Rates!$C$2:$C$13),0) | O55: =L55*N55
A56: Scaled Rollout and Adoption | B56: Change Readiness Assessment | C56: Present findings to leadership | D56: Readiness Survey, Baseline Adoption Index | E56: Assess cultural, technical, and operational readiness prior to implementation. | F56: CX Partner - Change Management SME | G56: Adobe | H56: CX Partner | I56: 21–24 | J56: =IFERROR(XLOOKUP(H56,'Lookups - JourneyDeployment'!$K$3:$K$7,'Lookups - JourneyDeployment'!$L$3:$L$7),"") | K56: =A56&"|"&B56 | L56: =IFERROR(XLOOKUP(K56,'Activity Settings'!$M$2:$M$200,'Activity Settings'!$J$2:$J$200),0) | M56: =IFERROR(XLOOKUP(K56,'Activity Settings'!$M$2:$M$200,'Activity Settings'!$L$2:$L$200),"Knapsack") | N56: =IFERROR(XLOOKUP(J56&"|"&M56,Rates!$E$2:$E$13,Rates!$C$2:$C$13),0) | O56: =L56*N56
A57: Scaled Rollout and Adoption | B57: FDE led Implementation + Architecture + Governance | C57: Define system-of-systems architecture | F57: Senior Solutions Engineer | G57: Knapsack | H57: Engineer | I57: 21–24 | J57: =IFERROR(XLOOKUP(H57,'Lookups - JourneyDeployment'!$K$3:$K$7,'Lookups - JourneyDeployment'!$L$3:$L$7),"") | K57: =A57&"|"&B57 | L57: =IFERROR(XLOOKUP(K57,'Activity Settings'!$M$2:$M$200,'Activity Settings'!$J$2:$J$200),0) | M57: =IFERROR(XLOOKUP(K57,'Activity Settings'!$M$2:$M$200,'Activity Settings'!$L$2:$L$200),"Knapsack") | N57: =IFERROR(XLOOKUP(J57&"|"&M57,Rates!$E$2:$E$13,Rates!$C$2:$C$13),0) | O57: =L57*N57
A58: Scaled Rollout and Adoption | B58: FDE led Implementation + Architecture + Governance | C58: Document governance model and accessibility plan | F58: Senior Solutions Engineer | G58: Knapsack | H58: Engineer | I58: 21–24 | J58: =IFERROR(XLOOKUP(H58,'Lookups - JourneyDeployment'!$K$3:$K$7,'Lookups - JourneyDeployment'!$L$3:$L$7),"") | K58: =A58&"|"&B58 | L58: =IFERROR(XLOOKUP(K58,'Activity Settings'!$M$2:$M$200,'Activity Settings'!$J$2:$J$200),0) | M58: =IFERROR(XLOOKUP(K58,'Activity Settings'!$M$2:$M$200,'Activity Settings'!$L$2:$L$200),"Knapsack") | N58: =IFERROR(XLOOKUP(J58&"|"&M58,Rates!$E$2:$E$13,Rates!$C$2:$C$13),0) | O58: =L58*N58
A59: Scaled Rollout and Adoption | B59: FDE led Implementation + Architecture + Governance | C59: Review architecture with engineering leads | F59: Senior Solutions Engineer | G59: Knapsack | H59: Engineer | I59: 21–24 | J59: =IFERROR(XLOOKUP(H59,'Lookups - JourneyDeployment'!$K$3:$K$7,'Lookups - JourneyDeployment'!$L$3:$L$7),"") | K59: =A59&"|"&B59 | L59: =IFERROR(XLOOKUP(K59,'Activity Settings'!$M$2:$M$200,'Activity Settings'!$J$2:$J$200),0) | M59: =IFERROR(XLOOKUP(K59,'Activity Settings'!$M$2:$M$200,'Activity Settings'!$L$2:$L$200),"Knapsack") | N59: =IFERROR(XLOOKUP(J59&"|"&M59,Rates!$E$2:$E$13,Rates!$C$2:$C$13),0) | O59: =L59*N59
A60: Scaled Rollout and Adoption | B60: FDE led Implementation + Architecture + Governance | C60: Finalize and publish architecture document | D60: System of Systems Architecture Document | E60: Define architecture, component contribution model, accessibility, governance framework. | F60: Senior Solutions Engineer | G60: Knapsack | H60: Engineer | I60: 21–24 | J60: =IFERROR(XLOOKUP(H60,'Lookups - JourneyDeployment'!$K$3:$K$7,'Lookups - JourneyDeployment'!$L$3:$L$7),"") | K60: =A60&"|"&B60 | L60: =IFERROR(XLOOKUP(K60,'Activity Settings'!$M$2:$M$200,'Activity Settings'!$J$2:$J$200),0) | M60: =IFERROR(XLOOKUP(K60,'Activity Settings'!$M$2:$M$200,'Activity Settings'!$L$2:$L$200),"Knapsack") | N60: =IFERROR(XLOOKUP(J60&"|"&M60,Rates!$E$2:$E$13,Rates!$C$2:$C$13),0) | O60: =L60*N60
A61: Scaled Rollout and Adoption | B61: Stakeholder Interviews/Workshops | C61: Schedule interviews across departments | F61: Senior Solutions Engineer | G61: Knapsack | H61: Engineer | I61: 21–24 | J61: =IFERROR(XLOOKUP(H61,'Lookups - JourneyDeployment'!$K$3:$K$7,'Lookups - JourneyDeployment'!$L$3:$L$7),"") | K61: =A61&"|"&B61 | L61: =IFERROR(XLOOKUP(K61,'Activity Settings'!$M$2:$M$200,'Activity Settings'!$J$2:$J$200),0) | M61: =IFERROR(XLOOKUP(K61,'Activity Settings'!$M$2:$M$200,'Activity Settings'!$L$2:$L$200),"Knapsack") | N61: =IFERROR(XLOOKUP(J61&"|"&M61,Rates!$E$2:$E$13,Rates!$C$2:$C$13),0) | O61: =L61*N61
A62: Scaled Rollout and Adoption | B62: Stakeholder Interviews/Workshops | C62: Capture key challenges and opportunities | F62: Senior Solutions Engineer | G62: Knapsack | H62: Engineer | I62: 21–24 | J62: =IFERROR(XLOOKUP(H62,'Lookups - JourneyDeployment'!$K$3:$K$7,'Lookups - JourneyDeployment'!$L$3:$L$7),"") | K62: =A62&"|"&B62 | L62: =IFERROR(XLOOKUP(K62,'Activity Settings'!$M$2:$M$200,'Activity Settings'!$J$2:$J$200),0) | M62: =IFERROR(XLOOKUP(K62,'Activity Settings'!$M$2:$M$200,'Activity Settings'!$L$2:$L$200),"Knapsack") | N62: =IFERROR(XLOOKUP(J62&"|"&M62,Rates!$E$2:$E$13,Rates!$C$2:$C$13),0) | O62: =L62*N62
A63: Scaled Rollout and Adoption | B63: Stakeholder Interviews/Workshops | C63: Consolidate findings into themes | F63: Senior Solutions Engineer | G63: Knapsack | H63: Engineer | I63: 21–24 | J63: =IFERROR(XLOOKUP(H63,'Lookups - JourneyDeployment'!$K$3:$K$7,'Lookups - JourneyDeployment'!$L$3:$L$7),"") | K63: =A63&"|"&B63 | L63: =IFERROR(XLOOKUP(K63,'Activity Settings'!$M$2:$M$200,'Activity Settings'!$J$2:$J$200),0) | M63: =IFERROR(XLOOKUP(K63,'Activity Settings'!$M$2:$M$200,'Activity Settings'!$L$2:$L$200),"Knapsack") | N63: =IFERROR(XLOOKUP(J63&"|"&M63,Rates!$E$2:$E$13,Rates!$C$2:$C$13),0) | O63: =L63*N63
A64: Scaled Rollout and Adoption | B64: Stakeholder Interviews/Workshops | C64: Draft recommendations report | F64: Senior Solutions Engineer | G64: Knapsack | H64: Engineer | I64: 21–24 | J64: =IFERROR(XLOOKUP(H64,'Lookups - JourneyDeployment'!$K$3:$K$7,'Lookups - JourneyDeployment'!$L$3:$L$7),"") | K64: =A64&"|"&B64 | L64: =IFERROR(XLOOKUP(K64,'Activity Settings'!$M$2:$M$200,'Activity Settings'!$J$2:$J$200),0) | M64: =IFERROR(XLOOKUP(K64,'Activity Settings'!$M$2:$M$200,'Activity Settings'!$L$2:$L$200),"Knapsack") | N64: =IFERROR(XLOOKUP(J64&"|"&M64,Rates!$E$2:$E$13,Rates!$C$2:$C$13),0) | O64: =L64*N64
A65: Scaled Rollout and Adoption | B65: Stakeholder Interviews/Workshops | C65: Present Strategic Readout | D65: Strategic Readout and Recommendations | E65: Collect stakeholder inputs and align roadmap. | F65: Senior Solutions Engineer | G65: Knapsack | H65: Engineer | I65: 21–24 | J65: =IFERROR(XLOOKUP(H65,'Lookups - JourneyDeployment'!$K$3:$K$7,'Lookups - JourneyDeployment'!$L$3:$L$7),"") | K65: =A65&"|"&B65 | L65: =IFERROR(XLOOKUP(K65,'Activity Settings'!$M$2:$M$200,'Activity Settings'!$J$2:$J$200),0) | M65: =IFERROR(XLOOKUP(K65,'Activity Settings'!$M$2:$M$200,'Activity Settings'!$L$2:$L$200),"Knapsack") | N65: =IFERROR(XLOOKUP(J65&"|"&M65,Rates!$E$2:$E$13,Rates!$C$2:$C$13),0) | O65: =L65*N65
A66: Scaled Rollout and Adoption | B66: Pilot Enablement & Feedback Loop | C66: Identify pilot groups and roles | F66: CX Partner - Change Management SME | G66: Adobe | H66: CX Partner | I66: 23–26 | J66: =IFERROR(XLOOKUP(H66,'Lookups - JourneyDeployment'!$K$3:$K$7,'Lookups - JourneyDeployment'!$L$3:$L$7),"") | K66: =A66&"|"&B66 | L66: =IFERROR(XLOOKUP(K66,'Activity Settings'!$M$2:$M$200,'Activity Settings'!$J$2:$J$200),0) | M66: =IFERROR(XLOOKUP(K66,'Activity Settings'!$M$2:$M$200,'Activity Settings'!$L$2:$L$200),"Knapsack") | N66: =IFERROR(XLOOKUP(J66&"|"&M66,Rates!$E$2:$E$13,Rates!$C$2:$C$13),0) | O66: =L66*N66
A67: Scaled Rollout and Adoption | B67: Pilot Enablement & Feedback Loop | C67: Conduct onboarding sessions | F67: CX Partner - Change Management SME | G67: Adobe | H67: CX Partner | I67: 23–26 | J67: =IFERROR(XLOOKUP(H67,'Lookups - JourneyDeployment'!$K$3:$K$7,'Lookups - JourneyDeployment'!$L$3:$L$7),"") | K67: =A67&"|"&B67 | L67: =IFERROR(XLOOKUP(K67,'Activity Settings'!$M$2:$M$200,'Activity Settings'!$J$2:$J$200),0) | M67: =IFERROR(XLOOKUP(K67,'Activity Settings'!$M$2:$M$200,'Activity Settings'!$L$2:$L$200),"Knapsack") | N67: =IFERROR(XLOOKUP(J67&"|"&M67,Rates!$E$2:$E$13,Rates!$C$2:$C$13),0) | O67: =L67*N67
A68: Scaled Rollout and Adoption | B68: Pilot Enablement & Feedback Loop | C68: Gather qualitative feedback | F68: CX Partner - Change Management SME | G68: Adobe | H68: CX Partner | I68: 23–26 | J68: =IFERROR(XLOOKUP(H68,'Lookups - JourneyDeployment'!$K$3:$K$7,'Lookups - JourneyDeployment'!$L$3:$L$7),"") | K68: =A68&"|"&B68 | L68: =IFERROR(XLOOKUP(K68,'Activity Settings'!$M$2:$M$200,'Activity Settings'!$J$2:$J$200),0) | M68: =IFERROR(XLOOKUP(K68,'Activity Settings'!$M$2:$M$200,'Activity Settings'!$L$2:$L$200),"Knapsack") | N68: =IFERROR(XLOOKUP(J68&"|"&M68,Rates!$E$2:$E$13,Rates!$C$2:$C$13),0) | O68: =L68*N68
A69: Scaled Rollout and Adoption | B69: Pilot Enablement & Feedback Loop | C69: Build sentiment dashboard | F69: CX Partner - Change Management SME | G69: Adobe | H69: CX Partner | I69: 23–26 | J69: =IFERROR(XLOOKUP(H69,'Lookups - JourneyDeployment'!$K$3:$K$7,'Lookups - JourneyDeployment'!$L$3:$L$7),"") | K69: =A69&"|"&B69 | L69: =IFERROR(XLOOKUP(K69,'Activity Settings'!$M$2:$M$200,'Activity Settings'!$J$2:$J$200),0) | M69: =IFERROR(XLOOKUP(K69,'Activity Settings'!$M$2:$M$200,'Activity Settings'!$L$2:$L$200),"Knapsack") | N69: =IFERROR(XLOOKUP(J69&"|"&M69,Rates!$E$2:$E$13,Rates!$C$2:$C$13),0) | O69: =L69*N69
A70: Scaled Rollout and Adoption | B70: Pilot Enablement & Feedback Loop | C70: Review results and refine approach | D70: Pilot Feedback Summary, Sentiment Dashboard | E70: Gather early adopter feedback and adjust onboarding approach. | F70: CX Partner - Change Management SME | G70: Adobe | H70: CX Partner | I70: 23–26 | J70: =IFERROR(XLOOKUP(H70,'Lookups - JourneyDeployment'!$K$3:$K$7,'Lookups - JourneyDeployment'!$L$3:$L$7),"") | K70: =A70&"|"&B70 | L70: =IFERROR(XLOOKUP(K70,'Activity Settings'!$M$2:$M$200,'Activity Settings'!$J$2:$J$200),0) | M70: =IFERROR(XLOOKUP(K70,'Activity Settings'!$M$2:$M$200,'Activity Settings'!$L$2:$L$200),"Knapsack") | N70: =IFERROR(XLOOKUP(J70&"|"&M70,Rates!$E$2:$E$13,Rates!$C$2:$C$13),0) | O70: =L70*N70
A71: Scaled Rollout and Adoption | B71: Role-Based Training Enablement | C71: Segment audience (UX, Eng, Partners) | F71: CX Partner - Change Management SME | G71: Adobe | H71: CX Partner | I71: 25–28 | J71: =IFERROR(XLOOKUP(H71,'Lookups - JourneyDeployment'!$K$3:$K$7,'Lookups - JourneyDeployment'!$L$3:$L$7),"") | K71: =A71&"|"&B71 | L71: =IFERROR(XLOOKUP(K71,'Activity Settings'!$M$2:$M$200,'Activity Settings'!$J$2:$J$200),0) | M71: =IFERROR(XLOOKUP(K71,'Activity Settings'!$M$2:$M$200,'Activity Settings'!$L$2:$L$200),"Knapsack") | N71: =IFERROR(XLOOKUP(J71&"|"&M71,Rates!$E$2:$E$13,Rates!$C$2:$C$13),0) | O71: =L71*N71
A72: Scaled Rollout and Adoption | B72: Role-Based Training Enablement | C72: Develop persona-specific materials | F72: CX Partner - Change Management SME | G72: Adobe | H72: CX Partner | I72: 25–28 | J72: =IFERROR(XLOOKUP(H72,'Lookups - JourneyDeployment'!$K$3:$K$7,'Lookups - JourneyDeployment'!$L$3:$L$7),"") | K72: =A72&"|"&B72 | L72: =IFERROR(XLOOKUP(K72,'Activity Settings'!$M$2:$M$200,'Activity Settings'!$J$2:$J$200),0) | M72: =IFERROR(XLOOKUP(K72,'Activity Settings'!$M$2:$M$200,'Activity Settings'!$L$2:$L$200),"Knapsack") | N72: =IFERROR(XLOOKUP(J72&"|"&M72,Rates!$E$2:$E$13,Rates!$C$2:$C$13),0) | O72: =L72*N72
A73: Scaled Rollout and Adoption | B73: Role-Based Training Enablement | C73: Host training sessions | F73: CX Partner - Change Management SME | G73: Adobe | H73: CX Partner | I73: 25–28 | J73: =IFERROR(XLOOKUP(H73,'Lookups - JourneyDeployment'!$K$3:$K$7,'Lookups - JourneyDeployment'!$L$3:$L$7),"") | K73: =A73&"|"&B73 | L73: =IFERROR(XLOOKUP(K73,'Activity Settings'!$M$2:$M$200,'Activity Settings'!$J$2:$J$200),0) | M73: =IFERROR(XLOOKUP(K73,'Activity Settings'!$M$2:$M$200,'Activity Settings'!$L$2:$L$200),"Knapsack") | N73: =IFERROR(XLOOKUP(J73&"|"&M73,Rates!$E$2:$E$13,Rates!$C$2:$C$13),0) | O73: =L73*N73
A74: Scaled Rollout and Adoption | B74: Role-Based Training Enablement | C74: Assess comprehension via surveys | F74: CX Partner - Change Management SME | G74: Adobe | H74: CX Partner | I74: 25–28 | J74: =IFERROR(XLOOKUP(H74,'Lookups - JourneyDeployment'!$K$3:$K$7,'Lookups - JourneyDeployment'!$L$3:$L$7),"") | K74: =A74&"|"&B74 | L74: =IFERROR(XLOOKUP(K74,'Activity Settings'!$M$2:$M$200,'Activity Settings'!$J$2:$J$200),0) | M74: =IFERROR(XLOOKUP(K74,'Activity Settings'!$M$2:$M$200,'Activity Settings'!$L$2:$L$200),"Knapsack") | N74: =IFERROR(XLOOKUP(J74&"|"&M74,Rates!$E$2:$E$13,Rates!$C$2:$C$13),0) | O74: =L74*N74
A75: Scaled Rollout and Adoption | B75: Role-Based Training Enablement | C75: Update modules as needed | D75: Persona-Based Training Modules (UX, Eng, Partner) | E75: Deliver tailored enablement by persona to improve comprehension and adoption. | F75: CX Partner - Change Management SME | G75: Adobe | H75: CX Partner | I75: 25–28 | J75: =IFERROR(XLOOKUP(H75,'Lookups - JourneyDeployment'!$K$3:$K$7,'Lookups - JourneyDeployment'!$L$3:$L$7),"") | K75: =A75&"|"&B75 | L75: =IFERROR(XLOOKUP(K75,'Activity Settings'!$M$2:$M$200,'Activity Settings'!$J$2:$J$200),0) | M75: =IFERROR(XLOOKUP(K75,'Activity Settings'!$M$2:$M$200,'Activity Settings'!$L$2:$L$200),"Knapsack") | N75: =IFERROR(XLOOKUP(J75&"|"&M75,Rates!$E$2:$E$13,Rates!$C$2:$C$13),0) | O75: =L75*N75
A76: Scaled Rollout and Adoption | B76: SME support for Deployment/DevOps | C76: Review CI/CD pipelines for readiness | F76: Subject Matter Expert | G76: Knapsack | H76: SME | I76: 21–26 | J76: =IFERROR(XLOOKUP(H76,'Lookups - JourneyDeployment'!$K$3:$K$7,'Lookups - JourneyDeployment'!$L$3:$L$7),"") | K76: =A76&"|"&B76 | L76: =IFERROR(XLOOKUP(K76,'Activity Settings'!$M$2:$M$200,'Activity Settings'!$J$2:$J$200),0) | M76: =IFERROR(XLOOKUP(K76,'Activity Settings'!$M$2:$M$200,'Activity Settings'!$L$2:$L$200),"Knapsack") | N76: =IFERROR(XLOOKUP(J76&"|"&M76,Rates!$E$2:$E$13,Rates!$C$2:$C$13),0) | O76: =L76*N76
A77: Scaled Rollout and Adoption | B77: SME support for Deployment/DevOps | C77: Validate automation scripts | F77: Subject Matter Expert | G77: Knapsack | H77: SME | I77: 21–26 | J77: =IFERROR(XLOOKUP(H77,'Lookups - JourneyDeployment'!$K$3:$K$7,'Lookups - JourneyDeployment'!$L$3:$L$7),"") | K77: =A77&"|"&B77 | L77: =IFERROR(XLOOKUP(K77,'Activity Settings'!$M$2:$M$200,'Activity Settings'!$J$2:$J$200),0) | M77: =IFERROR(XLOOKUP(K77,'Activity Settings'!$M$2:$M$200,'Activity Settings'!$L$2:$L$200),"Knapsack") | N77: =IFERROR(XLOOKUP(J77&"|"&M77,Rates!$E$2:$E$13,Rates!$C$2:$C$13),0) | O77: =L77*N77
A78: Scaled Rollout and Adoption | B78: SME support for Deployment/DevOps | C78: Confirm test coverage completeness | F78: Subject Matter Expert | G78: Knapsack | H78: SME | I78: 21–26 | J78: =IFERROR(XLOOKUP(H78,'Lookups - JourneyDeployment'!$K$3:$K$7,'Lookups - JourneyDeployment'!$L$3:$L$7),"") | K78: =A78&"|"&B78 | L78: =IFERROR(XLOOKUP(K78,'Activity Settings'!$M$2:$M$200,'Activity Settings'!$J$2:$J$200),0) | M78: =IFERROR(XLOOKUP(K78,'Activity Settings'!$M$2:$M$200,'Activity Settings'!$L$2:$L$200),"Knapsack") | N78: =IFERROR(XLOOKUP(J78&"|"&M78,Rates!$E$2:$E$13,Rates!$C$2:$C$13),0) | O78: =L78*N78
A79: Scaled Rollout and Adoption | B79: SME support for Deployment/DevOps | C79: Document readiness report | D79: DevOps Readiness | E79: Validate CI/CD, cloud authoring, and deployment automation readiness. | F79: Subject Matter Expert | G79: Knapsack | H79: SME | I79: 21–26 | J79: =IFERROR(XLOOKUP(H79,'Lookups - JourneyDeployment'!$K$3:$K$7,'Lookups - JourneyDeployment'!$L$3:$L$7),"") | K79: =A79&"|"&B79 | L79: =IFERROR(XLOOKUP(K79,'Activity Settings'!$M$2:$M$200,'Activity Settings'!$J$2:$J$200),0) | M79: =IFERROR(XLOOKUP(K79,'Activity Settings'!$M$2:$M$200,'Activity Settings'!$L$2:$L$200),"Knapsack") | N79: =IFERROR(XLOOKUP(J79&"|"&M79,Rates!$E$2:$E$13,Rates!$C$2:$C$13),0) | O79: =L79*N79
A80: Scaled Rollout and Adoption | B80: Cloud authoring setup and testing | C80: Configure cloud authoring environment | F80: Senior Solutions Engineer | G80: Knapsack | H80: Engineer | I80: 25–28 | J80: =IFERROR(XLOOKUP(H80,'Lookups - JourneyDeployment'!$K$3:$K$7,'Lookups - JourneyDeployment'!$L$3:$L$7),"") | K80: =A80&"|"&B80 | L80: =IFERROR(XLOOKUP(K80,'Activity Settings'!$M$2:$M$200,'Activity Settings'!$J$2:$J$200),0) | M80: =IFERROR(XLOOKUP(K80,'Activity Settings'!$M$2:$M$200,'Activity Settings'!$L$2:$L$200),"Knapsack") | N80: =IFERROR(XLOOKUP(J80&"|"&M80,Rates!$E$2:$E$13,Rates!$C$2:$C$13),0) | O80: =L80*N80
A81: Scaled Rollout and Adoption | B81: Cloud authoring setup and testing | C81: Migrate initial content set | F81: Senior Solutions Engineer | G81: Knapsack | H81: Engineer | I81: 25–28 | J81: =IFERROR(XLOOKUP(H81,'Lookups - JourneyDeployment'!$K$3:$K$7,'Lookups - JourneyDeployment'!$L$3:$L$7),"") | K81: =A81&"|"&B81 | L81: =IFERROR(XLOOKUP(K81,'Activity Settings'!$M$2:$M$200,'Activity Settings'!$J$2:$J$200),0) | M81: =IFERROR(XLOOKUP(K81,'Activity Settings'!$M$2:$M$200,'Activity Settings'!$L$2:$L$200),"Knapsack") | N81: =IFERROR(XLOOKUP(J81&"|"&M81,Rates!$E$2:$E$13,Rates!$C$2:$C$13),0) | O81: =L81*N81
A82: Scaled Rollout and Adoption | B82: Cloud authoring setup and testing | C82: Validate performance and permissions | F82: Senior Solutions Engineer | G82: Knapsack | H82: Engineer | I82: 25–28 | J82: =IFERROR(XLOOKUP(H82,'Lookups - JourneyDeployment'!$K$3:$K$7,'Lookups - JourneyDeployment'!$L$3:$L$7),"") | K82: =A82&"|"&B82 | L82: =IFERROR(XLOOKUP(K82,'Activity Settings'!$M$2:$M$200,'Activity Settings'!$J$2:$J$200),0) | M82: =IFERROR(XLOOKUP(K82,'Activity Settings'!$M$2:$M$200,'Activity Settings'!$L$2:$L$200),"Knapsack") | N82: =IFERROR(XLOOKUP(J82&"|"&M82,Rates!$E$2:$E$13,Rates!$C$2:$C$13),0) | O82: =L82*N82
A83: Scaled Rollout and Adoption | B83: Cloud authoring setup and testing | C83: Document validation results | D83: Cloud Authoring Validation | E83: Setup and validate authoring in cloud environments. | F83: Senior Solutions Engineer | G83: Knapsack | H83: Engineer | I83: 25–28 | J83: =IFERROR(XLOOKUP(H83,'Lookups - JourneyDeployment'!$K$3:$K$7,'Lookups - JourneyDeployment'!$L$3:$L$7),"") | K83: =A83&"|"&B83 | L83: =IFERROR(XLOOKUP(K83,'Activity Settings'!$M$2:$M$200,'Activity Settings'!$J$2:$J$200),0) | M83: =IFERROR(XLOOKUP(K83,'Activity Settings'!$M$2:$M$200,'Activity Settings'!$L$2:$L$200),"Knapsack") | N83: =IFERROR(XLOOKUP(J83&"|"&M83,Rates!$E$2:$E$13,Rates!$C$2:$C$13),0) | O83: =L83*N83
A84: Scaled Rollout and Adoption | B84: SSO setup and testing | C84: Integrate with Adobe’s identity provider | F84: Subject Matter Expert | G84: Knapsack | H84: SME | I84: 25–28 | J84: =IFERROR(XLOOKUP(H84,'Lookups - JourneyDeployment'!$K$3:$K$7,'Lookups - JourneyDeployment'!$L$3:$L$7),"") | K84: =A84&"|"&B84 | L84: =IFERROR(XLOOKUP(K84,'Activity Settings'!$M$2:$M$200,'Activity Settings'!$J$2:$J$200),0) | M84: =IFERROR(XLOOKUP(K84,'Activity Settings'!$M$2:$M$200,'Activity Settings'!$L$2:$L$200),"Knapsack") | N84: =IFERROR(XLOOKUP(J84&"|"&M84,Rates!$E$2:$E$13,Rates!$C$2:$C$13),0) | O84: =L84*N84
A85: Scaled Rollout and Adoption | B85: SSO setup and testing | C85: Test authentication flow and failover | F85: Subject Matter Expert | G85: Knapsack | H85: SME | I85: 25–28 | J85: =IFERROR(XLOOKUP(H85,'Lookups - JourneyDeployment'!$K$3:$K$7,'Lookups - JourneyDeployment'!$L$3:$L$7),"") | K85: =A85&"|"&B85 | L85: =IFERROR(XLOOKUP(K85,'Activity Settings'!$M$2:$M$200,'Activity Settings'!$J$2:$J$200),0) | M85: =IFERROR(XLOOKUP(K85,'Activity Settings'!$M$2:$M$200,'Activity Settings'!$L$2:$L$200),"Knapsack") | N85: =IFERROR(XLOOKUP(J85&"|"&M85,Rates!$E$2:$E$13,Rates!$C$2:$C$13),0) | O85: =L85*N85
A86: Scaled Rollout and Adoption | B86: SSO setup and testing | C86: Validate group mapping | F86: Subject Matter Expert | G86: Knapsack | H86: SME | I86: 25–28 | J86: =IFERROR(XLOOKUP(H86,'Lookups - JourneyDeployment'!$K$3:$K$7,'Lookups - JourneyDeployment'!$L$3:$L$7),"") | K86: =A86&"|"&B86 | L86: =IFERROR(XLOOKUP(K86,'Activity Settings'!$M$2:$M$200,'Activity Settings'!$J$2:$J$200),0) | M86: =IFERROR(XLOOKUP(K86,'Activity Settings'!$M$2:$M$200,'Activity Settings'!$L$2:$L$200),"Knapsack") | N86: =IFERROR(XLOOKUP(J86&"|"&M86,Rates!$E$2:$E$13,Rates!$C$2:$C$13),0) | O86: =L86*N86
A87: Scaled Rollout and Adoption | B87: SSO setup and testing | C87: Document SSO integration results | D87: SSO Integration Checklist | E87: Configure and test single sign-on with enterprise identity provider. | F87: Subject Matter Expert | G87: Knapsack | H87: SME | I87: 25–28 | J87: =IFERROR(XLOOKUP(H87,'Lookups - JourneyDeployment'!$K$3:$K$7,'Lookups - JourneyDeployment'!$L$3:$L$7),"") | K87: =A87&"|"&B87 | L87: =IFERROR(XLOOKUP(K87,'Activity Settings'!$M$2:$M$200,'Activity Settings'!$J$2:$J$200),0) | M87: =IFERROR(XLOOKUP(K87,'Activity Settings'!$M$2:$M$200,'Activity Settings'!$L$2:$L$200),"Knapsack") | N87: =IFERROR(XLOOKUP(J87&"|"&M87,Rates!$E$2:$E$13,Rates!$C$2:$C$13),0) | O87: =L87*N87
A88: Scaled Rollout and Adoption | B88: Training - Eng / UX / Partners | C88: Develop unified curriculum | F88: Senior Solutions Engineer | G88: Adobe | H88: Engineer | I88: 29–32 | J88: =IFERROR(XLOOKUP(H88,'Lookups - JourneyDeployment'!$K$3:$K$7,'Lookups - JourneyDeployment'!$L$3:$L$7),"") | K88: =A88&"|"&B88 | L88: =IFERROR(XLOOKUP(K88,'Activity Settings'!$M$2:$M$200,'Activity Settings'!$J$2:$J$200),0) | M88: =IFERROR(XLOOKUP(K88,'Activity Settings'!$M$2:$M$200,'Activity Settings'!$L$2:$L$200),"Knapsack") | N88: =IFERROR(XLOOKUP(J88&"|"&M88,Rates!$E$2:$E$13,Rates!$C$2:$C$13),0) | O88: =L88*N88
A89: Scaled Rollout and Adoption | B89: Training - Eng / UX / Partners | C89: Schedule and deliver training | F89: Senior Solutions Engineer | G89: Adobe | H89: Engineer | I89: 29–32 | J89: =IFERROR(XLOOKUP(H89,'Lookups - JourneyDeployment'!$K$3:$K$7,'Lookups - JourneyDeployment'!$L$3:$L$7),"") | K89: =A89&"|"&B89 | L89: =IFERROR(XLOOKUP(K89,'Activity Settings'!$M$2:$M$200,'Activity Settings'!$J$2:$J$200),0) | M89: =IFERROR(XLOOKUP(K89,'Activity Settings'!$M$2:$M$200,'Activity Settings'!$L$2:$L$200),"Knapsack") | N89: =IFERROR(XLOOKUP(J89&"|"&M89,Rates!$E$2:$E$13,Rates!$C$2:$C$13),0) | O89: =L89*N89
A90: Scaled Rollout and Adoption | B90: Training - Eng / UX / Partners | C90: Track attendance and feedback | F90: Senior Solutions Engineer | G90: Adobe | H90: Engineer | I90: 29–32 | J90: =IFERROR(XLOOKUP(H90,'Lookups - JourneyDeployment'!$K$3:$K$7,'Lookups - JourneyDeployment'!$L$3:$L$7),"") | K90: =A90&"|"&B90 | L90: =IFERROR(XLOOKUP(K90,'Activity Settings'!$M$2:$M$200,'Activity Settings'!$J$2:$J$200),0) | M90: =IFERROR(XLOOKUP(K90,'Activity Settings'!$M$2:$M$200,'Activity Settings'!$L$2:$L$200),"Knapsack") | N90: =IFERROR(XLOOKUP(J90&"|"&M90,Rates!$E$2:$E$13,Rates!$C$2:$C$13),0) | O90: =L90*N90
A91: Scaled Rollout and Adoption | B91: Training - Eng / UX / Partners | C91: Refine enablement materials | D91: Unified Enablement Curriculum | E91: Integrated training for engineering, UX, and partner audiences. | F91: Senior Solutions Engineer | G91: Adobe | H91: Engineer | I91: 29–32 | J91: =IFERROR(XLOOKUP(H91,'Lookups - JourneyDeployment'!$K$3:$K$7,'Lookups - JourneyDeployment'!$L$3:$L$7),"") | K91: =A91&"|"&B91 | L91: =IFERROR(XLOOKUP(K91,'Activity Settings'!$M$2:$M$200,'Activity Settings'!$J$2:$J$200),0) | M91: =IFERROR(XLOOKUP(K91,'Activity Settings'!$M$2:$M$200,'Activity Settings'!$L$2:$L$200),"Knapsack") | N91: =IFERROR(XLOOKUP(J91&"|"&M91,Rates!$E$2:$E$13,Rates!$C$2:$C$13),0) | O91: =L91*N91
A92: Scaled Rollout and Adoption | B92: Workflow Diagrams | C92: Document self-service and contribution workflows | F92: Senior Solutions Engineer | G92: Knapsack | H92: Engineer | I92: 21–24 | J92: =IFERROR(XLOOKUP(H92,'Lookups - JourneyDeployment'!$K$3:$K$7,'Lookups - JourneyDeployment'!$L$3:$L$7),"") | K92: =A92&"|"&B92 | L92: =IFERROR(XLOOKUP(K92,'Activity Settings'!$M$2:$M$200,'Activity Settings'!$J$2:$J$200),0) | M92: =IFERROR(XLOOKUP(K92,'Activity Settings'!$M$2:$M$200,'Activity Settings'!$L$2:$L$200),"Knapsack") | N92: =IFERROR(XLOOKUP(J92&"|"&M92,Rates!$E$2:$E$13,Rates!$C$2:$C$13),0) | O92: =L92*N92
A93: Scaled Rollout and Adoption | B93: Workflow Diagrams | C93: Create FigJam diagrams | F93: Senior Solutions Engineer | G93: Knapsack | H93: Engineer | I93: 21–24 | J93: =IFERROR(XLOOKUP(H93,'Lookups - JourneyDeployment'!$K$3:$K$7,'Lookups - JourneyDeployment'!$L$3:$L$7),"") | K93: =A93&"|"&B93 | L93: =IFERROR(XLOOKUP(K93,'Activity Settings'!$M$2:$M$200,'Activity Settings'!$J$2:$J$200),0) | M93: =IFERROR(XLOOKUP(K93,'Activity Settings'!$M$2:$M$200,'Activity Settings'!$L$2:$L$200),"Knapsack") | N93: =IFERROR(XLOOKUP(J93&"|"&M93,Rates!$E$2:$E$13,Rates!$C$2:$C$13),0) | O93: =L93*N93
A94: Scaled Rollout and Adoption | B94: Workflow Diagrams | C94: Review with design ops and engineering | F94: Senior Solutions Engineer | G94: Knapsack | H94: Engineer | I94: 21–24 | J94: =IFERROR(XLOOKUP(H94,'Lookups - JourneyDeployment'!$K$3:$K$7,'Lookups - JourneyDeployment'!$L$3:$L$7),"") | K94: =A94&"|"&B94 | L94: =IFERROR(XLOOKUP(K94,'Activity Settings'!$M$2:$M$200,'Activity Settings'!$J$2:$J$200),0) | M94: =IFERROR(XLOOKUP(K94,'Activity Settings'!$M$2:$M$200,'Activity Settings'!$L$2:$L$200),"Knapsack") | N94: =IFERROR(XLOOKUP(J94&"|"&M94,Rates!$E$2:$E$13,Rates!$C$2:$C$13),0) | O94: =L94*N94
A95: Scaled Rollout and Adoption | B95: Workflow Diagrams | C95: Publish workflow package | D95: Workflow Documentation (FigJam, Token Studio, Contribution Workflows) | E95: Map self-service contribution and implementation workflows. | F95: Senior Solutions Engineer | G95: Knapsack | H95: Engineer | I95: 21–24 | J95: =IFERROR(XLOOKUP(H95,'Lookups - JourneyDeployment'!$K$3:$K$7,'Lookups - JourneyDeployment'!$L$3:$L$7),"") | K95: =A95&"|"&B95 | L95: =IFERROR(XLOOKUP(K95,'Activity Settings'!$M$2:$M$200,'Activity Settings'!$J$2:$J$200),0) | M95: =IFERROR(XLOOKUP(K95,'Activity Settings'!$M$2:$M$200,'Activity Settings'!$L$2:$L$200),"Knapsack") | N95: =IFERROR(XLOOKUP(J95&"|"&M95,Rates!$E$2:$E$13,Rates!$C$2:$C$13),0) | O95: =L95*N95
A96: Scaled Rollout and Adoption | B96: Content planning and integration | C96: Map documentation inventory | F96: Senior Solutions Engineer | G96: Knapsack | H96: Engineer | I96: 25–28 | J96: =IFERROR(XLOOKUP(H96,'Lookups - JourneyDeployment'!$K$3:$K$7,'Lookups - JourneyDeployment'!$L$3:$L$7),"") | K96: =A96&"|"&B96 | L96: =IFERROR(XLOOKUP(K96,'Activity Settings'!$M$2:$M$200,'Activity Settings'!$J$2:$J$200),0) | M96: =IFERROR(XLOOKUP(K96,'Activity Settings'!$M$2:$M$200,'Activity Settings'!$L$2:$L$200),"Knapsack") | N96: =IFERROR(XLOOKUP(J96&"|"&M96,Rates!$E$2:$E$13,Rates!$C$2:$C$13),0) | O96: =L96*N96
A97: Scaled Rollout and Adoption | B97: Content planning and integration | C97: Create cross-platform implementation guides | F97: Senior Solutions Engineer | G97: Knapsack | H97: Engineer | I97: 25–28 | J97: =IFERROR(XLOOKUP(H97,'Lookups - JourneyDeployment'!$K$3:$K$7,'Lookups - JourneyDeployment'!$L$3:$L$7),"") | K97: =A97&"|"&B97 | L97: =IFERROR(XLOOKUP(K97,'Activity Settings'!$M$2:$M$200,'Activity Settings'!$J$2:$J$200),0) | M97: =IFERROR(XLOOKUP(K97,'Activity Settings'!$M$2:$M$200,'Activity Settings'!$L$2:$L$200),"Knapsack") | N97: =IFERROR(XLOOKUP(J97&"|"&M97,Rates!$E$2:$E$13,Rates!$C$2:$C$13),0) | O97: =L97*N97
A98: Scaled Rollout and Adoption | B98: Content planning and integration | C98: Validate completeness and consistency | F98: Senior Solutions Engineer | G98: Knapsack | H98: Engineer | I98: 25–28 | J98: =IFERROR(XLOOKUP(H98,'Lookups - JourneyDeployment'!$K$3:$K$7,'Lookups - JourneyDeployment'!$L$3:$L$7),"") | K98: =A98&"|"&B98 | L98: =IFERROR(XLOOKUP(K98,'Activity Settings'!$M$2:$M$200,'Activity Settings'!$J$2:$J$200),0) | M98: =IFERROR(XLOOKUP(K98,'Activity Settings'!$M$2:$M$200,'Activity Settings'!$L$2:$L$200),"Knapsack") | N98: =IFERROR(XLOOKUP(J98&"|"&M98,Rates!$E$2:$E$13,Rates!$C$2:$C$13),0) | O98: =L98*N98
A99: Scaled Rollout and Adoption | B99: Content planning and integration | C99: Publish documentation set | D99: Multi-platform Implementation Guides | E99: Documentation for web, React, iOS, Android implementations. | F99: Senior Solutions Engineer | G99: Knapsack | H99: Engineer | I99: 25–28 | J99: =IFERROR(XLOOKUP(H99,'Lookups - JourneyDeployment'!$K$3:$K$7,'Lookups - JourneyDeployment'!$L$3:$L$7),"") | K99: =A99&"|"&B99 | L99: =IFERROR(XLOOKUP(K99,'Activity Settings'!$M$2:$M$200,'Activity Settings'!$J$2:$J$200),0) | M99: =IFERROR(XLOOKUP(K99,'Activity Settings'!$M$2:$M$200,'Activity Settings'!$L$2:$L$200),"Knapsack") | N99: =IFERROR(XLOOKUP(J99&"|"&M99,Rates!$E$2:$E$13,Rates!$C$2:$C$13),0) | O99: =L99*N99
A100: Scaled Rollout and Adoption | B100: Advanced Training - Partners + Contribution | C100: Identify advanced partner cohort | F100: Senior Solutions Engineer | G100: Adobe | H100: Engineer | I100: 29–32 | J100: =IFERROR(XLOOKUP(H100,'Lookups - JourneyDeployment'!$K$3:$K$7,'Lookups - JourneyDeployment'!$L$3:$L$7),"") | K100: =A100&"|"&B100 | L100: =IFERROR(XLOOKUP(K100,'Activity Settings'!$M$2:$M$200,'Activity Settings'!$J$2:$J$200),0) | M100: =IFERROR(XLOOKUP(K100,'Activity Settings'!$M$2:$M$200,'Activity Settings'!$L$2:$L$200),"Knapsack") | N100: =IFERROR(XLOOKUP(J100&"|"&M100,Rates!$E$2:$E$13,Rates!$C$2:$C$13),0) | O100: =L100*N100
...

Sheet Summary
A1: Estimation Summary
A3: Delivery Model | B3: =Inputs!$B$3 | D3: Total Hours | E3: =SUM('Activity Settings'!$I$2:$I$200)
A4: Journey | B4: =Inputs!$B$4 | D4: Total Cost | E4: =SUM('WBS - Estimate'!$O$2:$O$500)
A5: Deployment | B5: =Inputs!$B$5
A6: Default Complexity | B6: =Inputs!$B$6
A7: Readiness Level | B7: =Inputs!$B$8
A8: Readiness Multiplier | B8: =Inputs!$B$7
A11: Hours & Cost by Phase
A12: Phase | B12: Hours | C12: Cost
A13: Implementation + Onboarding | B13: =SUMIFS('Activity Settings'!$I$2:$I$200,'Activity Settings'!$A$2:$A$200,$A13) | C13: =SUMIFS('WBS - Estimate'!$O$2:$O$500,'WBS - Estimate'!$A$2:$A$500,$A13)
A14: Scaled Rollout and Adoption | B14: =SUMIFS('Activity Settings'!$I$2:$I$200,'Activity Settings'!$A$2:$A$200,$A14) | C14: =SUMIFS('WBS - Estimate'!$O$2:$O$500,'WBS - Estimate'!$A$2:$A$500,$A14)
A15: Optimization and Continued Support | B15: =SUMIFS('Activity Settings'!$I$2:$I$200,'Activity Settings'!$A$2:$A$200,$A15) | C15: =SUMIFS('WBS - Estimate'!$O$2:$O$500,'WBS - Estimate'!$A$2:$A$500,$A15)
A18: Hours & Cost by Provider
A19: Provider | B19: Hours | C19: Cost
A20: Knapsack | B20: =SUMIF('WBS - Estimate'!$M$2:$M$500,$A20,'WBS - Estimate'!$L$2:$L$500) | C20: =SUMIF('WBS - Estimate'!$M$2:$M$500,$A20,'WBS - Estimate'!$O$2:$O$500)
A21: Client/SCE | B21: =SUMIF('WBS - Estimate'!$M$2:$M$500,$A21,'WBS - Estimate'!$L$2:$L$500) | C21: =SUMIF('WBS - Estimate'!$M$2:$M$500,$A21,'WBS - Estimate'!$O$2:$O$500)
A24: Hours & Cost by Standard Role
A25: Standard Role | B25: Hours | C25: Cost
A26: CX Partner | B26: =SUMIF('WBS - Estimate'!$J$2:$J$500,$A26,'WBS - Estimate'!$L$2:$L$500) | C26: =SUMIF('WBS - Estimate'!$J$2:$J$500,$A26,'WBS - Estimate'!$O$2:$O$500)
A27: Project Manager | B27: =SUMIF('WBS - Estimate'!$J$2:$J$500,$A27,'WBS - Estimate'!$L$2:$L$500) | C27: =SUMIF('WBS - Estimate'!$J$2:$J$500,$A27,'WBS - Estimate'!$O$2:$O$500)
A28: Solution Analyst | B28: =SUMIF('WBS - Estimate'!$J$2:$J$500,$A28,'WBS - Estimate'!$L$2:$L$500) | C28: =SUMIF('WBS - Estimate'!$J$2:$J$500,$A28,'WBS - Estimate'!$O$2:$O$500)
A29: Senior Solution Analyst | B29: =SUMIF('WBS - Estimate'!$J$2:$J$500,$A29,'WBS - Estimate'!$L$2:$L$500) | C29: =SUMIF('WBS - Estimate'!$J$2:$J$500,$A29,'WBS - Estimate'!$O$2:$O$500)
A30: SME | B30: =SUMIF('WBS - Estimate'!$J$2:$J$500,$A30,'WBS - Estimate'!$L$2:$L$500) | C30: =SUMIF('WBS - Estimate'!$J$2:$J$500,$A30,'WBS - Estimate'!$O$2:$O$500)
A31: Executive | B31: =SUMIF('WBS - Estimate'!$J$2:$J$500,$A31,'WBS - Estimate'!$L$2:$L$500) | C31: =SUMIF('WBS - Estimate'!$J$2:$J$500,$A31,'WBS - Estimate'!$O$2:$O$500)

Sheet RAID Log
A1: ID | B1: Type | C1: Title | D1: Description | E1: Owner | F1: Impact (1-5) | G1: Probability (1-5) | H1: Score | I1: Status | J1: Mitigation / Next Steps | K1: Due Date | L1: Date Opened | M1: Date Closed | N1: Notes
A2: 1 | H2: =IF(OR(F2="",G2=""),"",F2*G2)
A3: 2 | H3: =IF(OR(F3="",G3=""),"",F3*G3)
A4: 3 | H4: =IF(OR(F4="",G4=""),"",F4*G4)
A5: 4 | H5: =IF(OR(F5="",G5=""),"",F5*G5)
A6: 5 | H6: =IF(OR(F6="",G6=""),"",F6*G6)
A7: 6 | H7: =IF(OR(F7="",G7=""),"",F7*G7)
A8: 7 | H8: =IF(OR(F8="",G8=""),"",F8*G8)
A9: 8 | H9: =IF(OR(F9="",G9=""),"",F9*G9)
A10: 9 | H10: =IF(OR(F10="",G10=""),"",F10*G10)
A11: 10 | H11: =IF(OR(F11="",G11=""),"",F11*G11)
A12: 11 | H12: =IF(OR(F12="",G12=""),"",F12*G12)
A13: 12 | H13: =IF(OR(F13="",G13=""),"",F13*G13)
... A201: 200 | H201: =IF(OR(F201="",G201=""),"",F201*G201)

Sheet Instructions - Adobe 
A1: Adobe Resource Planning Model v2.0 — How to:
A3: 1) Review the Plan Tab
A4: - Milestone Plan Tab drives the Proposed Solutions tab: Rollups by Role for review
A5: 2) Adjust the Accountable Party Column F
A6: - Amber took a first pass at the scrub - Angelie and team take it away!
A7: 3 ) Review the Summary Tab to understand the impact on the Resource Model
A8: - The RACI align with where we land on scope in the Procurement phase we are currently in

Sheet Milestone Plan
A1: Line # | B1: Milestone (Activity) | C1: Phase (auto) | D1: Deliverable (auto) | E1: Description | F1: Knapsack Role Description | G1: Accountable Party | H1: Role | I1: Effort Type | J1: Effort Value | K1: Complexity | L1: Calc Hours | M1: Weeks (FTE) | N1: Start Date | O1: End Date | P1: Hourly Rate | Q1: Daily Rate | R1: Cost (auto) | S1: Notes | T1: Scenario Hour Mult. | U1: Scenario Rate Mult. | V1: Contingency % | W1: Final Hours (auto) | X1: Adj. Hourly Rate | Y1: Adj. Cost (auto) | Z1: Review Notes
A2: 1 | B2: Program management and Steering Committee coordination | C2: {=IFERROR(INDEX(Milestones!$A:$A, MATCH($B2, Milestones!$B:$B, 0)), "")} | D2: {=IFERROR(INDEX(Milestones!$C:$C, MATCH($B2, Milestones!$B:$B, 0)), "")} | E2: Kickoff, bi-weekly stand-ups, monthly reports, phase gate reviews | F2: {=IFERROR(INDEX(Milestones!$E:$E, MATCH($B2, Milestones!$B:$B, 0)), "")} | G2: Adobe | H2: {=IFERROR(INDEX(Milestones!$E:$E, MATCH($B2, Milestones!$B:$B, 0)), "")} | I2: FTE | J2: 0.01 | K2: Low | L2: 100 | M2: =IF($I2="FTE", Assumptions!$B$3, "") | N2: {=IFERROR(INDEX(Milestones!$F:$F, MATCH($B2, Milestones!$B:$B, 0)), "")} | O2: {=IFERROR(INDEX(Milestones!$G:$G, MATCH($B2, Milestones!$B:$B, 0)), "")} | P2: {=IFERROR(INDEX('Lookups - Rates'!$D:$D, MATCH($G2&"|"&$H2, 'Lookups - Rates'!$Z:$Z, 0)), "")} | Q2: {=IFERROR(INDEX('Lookups - Rates'!$E:$E, MATCH($G2&"|"&$H2, 'Lookups - Rates'!$Z:$Z, 0)), "")} | R2: =LET(ev,$J2, ch,$L2, hr,$P2, dr,$Q2, hpday,Assumptions!$B$2, hpw,Assumptions!$B$3, w,$M2, hrs, IF($I2="Hours", ev, IF($I2="Days", ev*IF(dr>0, dr/hr, hpday), IF($I2="FTE", ev*hpw*w, ch))), IF(hrs="", "", hrs*hr)) | T2: {=XLOOKUP(Scenario_Selected, INDEX(Scenario_Table,0,1), INDEX(Scenario_Table,0,2))} | U2: {=XLOOKUP(Scenario_Selected, INDEX(Scenario_Table,0,1), INDEX(Scenario_Table,0,3))} | V2: {=XLOOKUP(Scenario_Selected, INDEX(Scenario_Table,0,1), INDEX(Scenario_Table,0,4))} | W2: {=LET(ev,$J2, ch,$L2, et,$I2, dr,$Q2, hpday,Assumptions!$B$2, hpw,Assumptions!$B$3, w,$M2,hm,INDIRECT("R[0]C[0]",FALSE),hrs, IF(et="Hours", ev, IF(et="Days", ev*IF(dr>0, dr/$P2, hpday), IF(et="FTE", ev*hpw*w, ch))), IF(hrs="", "", hrs*hm))} | X2: =IF($P2="","", $P2*INDIRECT("R[0]C[-3]",FALSE)) | Y2: =IF(INDIRECT("R[0]C[-1]",FALSE)="","", INDIRECT("R[0]C[-2]",FALSE)*INDIRECT("R[0]C[-1]",FALSE)*(1+INDIRECT("R[0]C[-3]",FALSE))) | Z2: potentially
A3: 2 | B3: Facilitating and supporting deliverables | C3: {=IFERROR(INDEX(Milestones!$A:$A, MATCH($B3, Milestones!$B:$B, 0)), "")} | D3: {=IFERROR(INDEX(Milestones!$C:$C, MATCH($B3, Milestones!$B:$B, 0)), "")} | E3: Track adoption metrics, stakeholder engagement, and training completion | F3: {=IFERROR(INDEX(Milestones!$E:$E, MATCH($B3, Milestones!$B:$B, 0)), "")} | G3: Adobe | H3: Adobe | I3: FTE | J3: 0.03 | K3: Medium | L3: {=IF($K3="","", IFERROR(IFS($K3="Low", INDEX('Lookups - Complexity'!$C:$C, MATCH($B3, 'Lookups - Complexity'!$B:$B,0)), $K3="Medium", INDEX('Lookups - Complexity'!$D:$D, MATCH($B3, 'Lookups - Complexity'!$B:$B,0)), $K3="High", INDEX('Lookups - Complexity'!$E:$E, MATCH($B3, 'Lookups - Complexity'!$B:$B,0))), ""))} | M3: =IF($I3="FTE", Assumptions!$B$3, "") | N3: {=IFERROR(INDEX(Milestones!$F:$F, MATCH($B3, Milestones!$B:$B, 0)), "")} | O3: {=IFERROR(INDEX(Milestones!$G:$G, MATCH($B3, Milestones!$B:$B, 0)), "")} | P3: {=IFERROR(INDEX('Lookups - Rates'!$D:$D, MATCH($G3&"|"&$H3, 'Lookups - Rates'!$Z:$Z, 0)), "")} | Q3: {=IFERROR(INDEX('Lookups - Rates'!$E:$E, MATCH($G3&"|"&$H3, 'Lookups - Rates'!$Z:$Z, 0)), "")} | R3: =LET(ev,$J3, ch,$L3, hr,$P3, dr,$Q3, hpday,Assumptions!$B$2, hpw,Assumptions!$B$3, w,$M3, hrs, IF($I3="Hours", ev, IF($I3="Days", ev*IF(dr>0, dr/hr, hpday), IF($I3="FTE", ev*hpw*w, ch))), IF(hrs="", "", hrs*hr)) | T3: {=XLOOKUP(Scenario_Selected, INDEX(Scenario_Table,0,1), INDEX(Scenario_Table,0,2))} | U3: {=XLOOKUP(Scenario_Selected, INDEX(Scenario_Table,0,1), INDEX(Scenario_Table,0,3))} | V3: {=XLOOKUP(Scenario_Selected, INDEX(Scenario_Table,0,1), INDEX(Scenario_Table,0,4))} | W3: {=LET(ev,$J3, ch,$L3, et,$I3, dr,$Q3, hpday,Assumptions!$B$2, hpw,Assumptions!$B$3, w,$M3,hm,INDIRECT("R[0]C[0]",FALSE),hrs, IF(et="Hours", ev, IF(et="Days", ev*IF(dr>0, dr/$P3, hpday), IF(et="FTE", ev*hpw*w, ch))), IF(hrs="", "", hrs*hm))} | X3: =IF($P3="","", $P3*INDIRECT("R[0]C[-3]",FALSE)) | Y3: =IF(INDIRECT("R[0]C[-1]",FALSE)="","", INDIRECT("R[0]C[-2]",FALSE)*INDIRECT("R[0]C[-1]",FALSE)*(1+INDIRECT("R[0]C[-3]",FALSE))) | Z3: typically owned by the team - partnership with Program management + leads
A4: 3 | B4: Stakeholder Alignment Workshops | C4: {=IFERROR(INDEX(Milestones!$A:$A, MATCH($B4, Milestones!$B:$B, 0)), "")} | D4: {=IFERROR(INDEX(Milestones!$C:$C, MATCH($B4, Milestones!$B:$B, 0)), "")} | E4: Ensure executive and stakeholder alignment before kickoff. | F4: {=IFERROR(INDEX(Milestones!$E:$E, MATCH($B4, Milestones!$B:$B, 0)), "")} | G4: Adobe | H4: Adobe | I4: FTE | J4: 0.03 | K4: Medium | L4: {=IF($K4="","", IFERROR(IFS($K4="Low", INDEX('Lookups - Complexity'!$C:$C, MATCH($B4, 'Lookups - Complexity'!$B:$B,0)), $K4="Medium", INDEX('Lookups - Complexity'!$D:$D, MATCH($B4, 'Lookups - Complexity'!$B:$B,0)), $K4="High", INDEX('Lookups - Complexity'!$E:$E, MATCH($B4, 'Lookups - Complexity'!$B:$B,0))), ""))} | M4: =IF($I4="FTE", Assumptions!$B$3, "") | N4: {=IFERROR(INDEX(Milestones!$F:$F, MATCH($B4, Milestones!$B:$B, 0)), "")} | O4: {=IFERROR(INDEX(Milestones!$G:$G, MATCH($B4, Milestones!$B:$B, 0)), "")} | P4: {=IFERROR(INDEX('Lookups - Rates'!$D:$D, MATCH($G4&"|"&$H4, 'Lookups - Rates'!$Z:$Z, 0)), "")} | Q4: {=IFERROR(INDEX('Lookups - Rates'!$E:$E, MATCH($G4&"|"&$H4, 'Lookups - Rates'!$Z:$Z, 0)), "")} | R4: =LET(ev,$J4, ch,$L4, hr,$P4, dr,$Q4, hpday,Assumptions!$B$2, hpw,Assumptions!$B$3, w,$M4, hrs, IF($I4="Hours", ev, IF($I4="Days", ev*IF(dr>0, dr/hr, hpday), IF($I4="FTE", ev*hpw*w, ch))), IF(hrs="", "", hrs*hr)) | T4: {=XLOOKUP(Scenario_Selected, INDEX(Scenario_Table,0,1), INDEX(Scenario_Table,0,2))} | U4: {=XLOOKUP(Scenario_Selected, INDEX(Scenario_Table,0,1), INDEX(Scenario_Table,0,3))} | V4: {=XLOOKUP(Scenario_Selected, INDEX(Scenario_Table,0,1), INDEX(Scenario_Table,0,4))} | W4: {=LET(ev,$J4, ch,$L4, et,$I4, dr,$Q4, hpday,Assumptions!$B$2, hpw,Assumptions!$B$3, w,$M4,hm,INDIRECT("R[0]C[0]",FALSE),hrs, IF(et="Hours", ev, IF(et="Days", ev*IF(dr>0, dr/$P4, hpday), IF(et="FTE", ev*hpw*w, ch))), IF(hrs="", "", hrs*hm))} | X4: =IF($P4="","", $P4*INDIRECT("R[0]C[-3]",FALSE)) | Y4: =IF(INDIRECT("R[0]C[-1]",FALSE)="","", INDIRECT("R[0]C[-2]",FALSE)*INDIRECT("R[0]C[-1]",FALSE)*(1+INDIRECT("R[0]C[-3]",FALSE))) | Z4: Product Owners, etc.
A5: 4 | B5: Change Readiness Assessment | C5: {=IFERROR(INDEX(Milestones!$A:$A, MATCH($B5, Milestones!$B:$B, 0)), "")} | D5: {=IFERROR(INDEX(Milestones!$A:$A, MATCH($B5, Milestones!$B:$B, 0)), "")} | E5: Assess cultural, technical, and operational readiness prior to implementation. | F5: {=IFERROR(INDEX(Milestones!$E:$E, MATCH($B5, Milestones!$B:$B, 0)), "")} | G5: Adobe | H5: CX Partner - Change Management SME | I5: FTE | J5: 0.03 | K5: Medium | L5: 16 | M5: =IF($I5="FTE", Assumptions!$B$3, "") | N5: {=IFERROR(INDEX(Milestones!$F:$F, MATCH($B5, Milestones!$B:$B, 0)), "")} | O5: {=IFERROR(INDEX(Milestones!$G:$G, MATCH($B5, Milestones!$B:$B, 0)), "")} | P5: {=IFERROR(INDEX('Lookups - Rates'!$D:$D, MATCH($G5&"|"&$H5, 'Lookups - Rates'!$Z:$Z, 0)), "")} | Q5: {=IFERROR(INDEX('Lookups - Rates'!$E:$E, MATCH($G5&"|"&$H5, 'Lookups - Rates'!$Z:$Z, 0)), "")} | R5: =LET(ev,$J5, ch,$L5, hr,$P5, dr,$Q5, hpday,Assumptions!$B$2, hpw,Assumptions!$B$3, w,$M5, hrs, IF($I5="Hours", ev, IF($I5="Days", ev*IF(dr>0, dr/hr, hpday), IF($I5="FTE", ev*hpw*w, ch))), IF(hrs="", "", hrs*hr)) | T5: {=XLOOKUP(Scenario_Selected, INDEX(Scenario_Table,0,1), INDEX(Scenario_Table,0,2))} | U5: {=XLOOKUP(Scenario_Selected, INDEX(Scenario_Table,0,1), INDEX(Scenario_Table,0,3))} | V5: {=XLOOKUP(Scenario_Selected, INDEX(Scenario_Table,0,1), INDEX(Scenario_Table,0,4))} | W5: {=LET(ev,$J5, ch,$L5, et,$I5, dr,$Q5, hpday,Assumptions!$B$2, hpw,Assumptions!$B$3, w,$M5,hm,INDIRECT("R[0]C[0]",FALSE),hrs, IF(et="Hours", ev, IF(et="Days", ev*IF(dr>0, dr/$P5, hpday), IF(et="FTE", ev*hpw*w, ch))), IF(hrs="", "", hrs*hm))} | X5: =IF($P5="","", $P5*INDIRECT("R[0]C[-3]",FALSE)) | Y5: =IF(INDIRECT("R[0]C[-1]",FALSE)="","", INDIRECT("R[0]C[-2]",FALSE)*INDIRECT("R[0]C[-1]",FALSE)*(1+INDIRECT("R[0]C[-3]",FALSE))) | Z5: The Spectrum team will be fine - external to Spectrum will be limited to the documentation. Programming is in place to support this | AA5: Amber to share the readiness survey
A6: 5 | B6: Program management and coordination | C6: {=IFERROR(INDEX(Milestones!$A:$A, MATCH($B6, Milestones!$B:$B, 0)), "")} | D6: {=IFERROR(INDEX(Milestones!$C:$C, MATCH($B6, Milestones!$B:$B, 0)), "")} | E6: Program coordination, kickoff, and phase review oversight | F6: {=IFERROR(INDEX(Milestones!$E:$E, MATCH($B6, Milestones!$B:$B, 0)), "")} | G6: Knapsack | H6: {=IFERROR(INDEX(Milestones!$E:$E, MATCH($B6, Milestones!$B:$B, 0)), "")} | I6: FTE | J6: 0.03 | K6: Medium | L6: {=IF($K6="","", IFERROR(IFS($K6="Low", INDEX('Lookups - Complexity'!$C:$C, MATCH($B6, 'Lookups - Complexity'!$B:$B,0)), $K6="Medium", INDEX('Lookups - Complexity'!$D:$D, MATCH($B6, 'Lookups - Complexity'!$B:$B,0)), $K6="High", INDEX('Lookups - Complexity'!$E:$E, MATCH($B6, 'Lookups - Complexity'!$B:$B,0))), ""))} | M6: =IF($I6="FTE", Assumptions!$B$3, "") | N6: {=IFERROR(INDEX(Milestones!$F:$F, MATCH($B6, Milestones!$B:$B, 0)), "")} | O6: {=IFERROR(INDEX(Milestones!$G:$G, MATCH($B6, Milestones!$B:$B, 0)), "")} | P6: {=IFERROR(INDEX('Lookups - Rates'!$D:$D, MATCH($G6&"|"&$H6, 'Lookups - Rates'!$Z:$Z, 0)), "")} | Q6: {=IFERROR(INDEX('Lookups - Rates'!$E:$E, MATCH($G6&"|"&$H6, 'Lookups - Rates'!$Z:$Z, 0)), "")} | R6: =LET(ev,$J6, ch,$L6, hr,$P6, dr,$Q6, hpday,Assumptions!$B$2, hpw,Assumptions!$B$3, w,$M6, hrs, IF($I6="Hours", ev, IF($I6="Days", ev*IF(dr>0, dr/hr, hpday), IF($I6="FTE", ev*hpw*w, ch))), IF(hrs="", "", hrs*hr)) | T6: {=XLOOKUP(Scenario_Selected, INDEX(Scenario_Table,0,1), INDEX(Scenario_Table,0,2))} | U6: {=XLOOKUP(Scenario_Selected, INDEX(Scenario_Table,0,1), INDEX(Scenario_Table,0,3))} | V6: {=XLOOKUP(Scenario_Selected, INDEX(Scenario_Table,0,1), INDEX(Scenario_Table,0,4))} | W6: {=LET(ev,$J6, ch,$L6, et,$I6, dr,$Q6, hpday,Assumptions!$B$2, hpw,Assumptions!$B$3, w,$M6,hm,INDIRECT("R[0]C[0]",FALSE),hrs, IF(et="Hours", ev, IF(et="Days", ev*IF(dr>0, dr/$P6, hpday), IF(et="FTE", ev*hpw*w, ch))), IF(hrs="", "", hrs*hm))} | X6: =IF($P6="","", $P6*INDIRECT("R[0]C[-3]",FALSE)) | Y6: =IF(INDIRECT("R[0]C[-1]",FALSE)="","", INDIRECT("R[0]C[-2]",FALSE)*INDIRECT("R[0]C[-1]",FALSE)*(1+INDIRECT("R[0]C[-3]",FALSE))) | Z6: @ADOBE - WE HAVE INCLUDED OUR PROJECT MANAGER RESOURCE HERE TO SUPPORT AND THEY WILL TAKE DIRECTION FROM ANDREW AND I AS CX PARTNERS TO KEEP COST DOWN AND STILL PROVIDE YOU WITH THE VALUE OF CX LED PROGRAM MANAGEMENT. THEY WILL NEED TO BE IN LOCK STEP WITH YOUR PROJECT MANAGER FROM ROW 1 OF THIS PLAN. 10.28 @ADOBE - what is the final answer on this? Is Adobe Accountable OR do you want/need Knapsack support. Notes from previous review. Our Program Managers are stretched quite thin - IF there is an opportunity to leverage a Project Manager alongside the FDE we can consider it - let's align on the terms. Option for contractor spend
A7: 6 | B7: Communication Launch Plan | C7: {=IFERROR(INDEX(Milestones!$A:$A, MATCH($B7, Milestones!$B:$B, 0)), "")} | D7: {=IFERROR(INDEX(Milestones!$C:$C, MATCH($B7, Milestones!$B:$B, 0)), "")} | E7: Launch program messaging, goals, and brand identity across teams. | F7: {=IFERROR(INDEX(Milestones!$E:$E, MATCH($B7, Milestones!$B:$B, 0)), "")} | G7: Adobe | H7: Adobe | I7: FTE | J7: 0.05 | K7: High | L7: {=IF($K7="","", IFERROR(IFS($K7="Low", INDEX('Lookups - Complexity'!$C:$C, MATCH($B7, 'Lookups - Complexity'!$B:$B,0)), $K7="Medium", INDEX('Lookups - Complexity'!$D:$D, MATCH($B7, 'Lookups - Complexity'!$B:$B,0)), $K7="High", INDEX('Lookups - Complexity'!$E:$E, MATCH($B7, 'Lookups - Complexity'!$B:$B,0))), ""))} | M7: =IF($I7="FTE", Assumptions!$B$3, "") | N7: {=IFERROR(INDEX(Milestones!$F:$F, MATCH($B7, Milestones!$B:$B, 0)), "")} | O7: {=IFERROR(INDEX(Milestones!$G:$G, MATCH($B7, Milestones!$B:$B, 0)), "")} | P7: {=IFERROR(INDEX('Lookups - Rates'!$D:$D, MATCH($G7&"|"&$H7, 'Lookups - Rates'!$Z:$Z, 0)), "")} | Q7: {=IFERROR(INDEX('Lookups - Rates'!$E:$E, MATCH($G7&"|"&$H7, 'Lookups - Rates'!$Z:$Z, 0)), "")} | R7: =LET(ev,$J7, ch,$L7, hr,$P7, dr,$Q7, hpday,Assumptions!$B$2, hpw,Assumptions!$B$3, w,$M7, hrs, IF($I7="Hours", ev, IF($I7="Days", ev*IF(dr>0, dr/hr, hpday), IF($I7="FTE", ev*hpw*w, ch))), IF(hrs="", "", hrs*hr)) | T7: {=XLOOKUP(Scenario_Selected, INDEX(Scenario_Table,0,1), INDEX(Scenario_Table,0,2))} | U7: {=XLOOKUP(Scenario_Selected, INDEX(Scenario_Table,0,1), INDEX(Scenario_Table,0,3))} | V7: {=XLOOKUP(Scenario_Selected, INDEX(Scenario_Table,0,1), INDEX(Scenario_Table,0,4))} | W7: {=LET(ev,$J7, ch,$L7, et,$I7, dr,$Q7, hpday,Assumptions!$B$2, hpw,Assumptions!$B$3, w,$M7,hm,INDIRECT("R[0]C[0]",FALSE),hrs, IF(et="Hours", ev, IF(et="Days", ev*IF(dr>0, dr/$P7, hpday), IF(et="FTE", ev*hpw*w, ch))), IF(hrs="", "", hrs*hm))} | X7: =IF($P7="","", $P7*INDIRECT("R[0]C[-3]",FALSE)) | Y7: =IF(INDIRECT("R[0]C[-1]",FALSE)="","", INDIRECT("R[0]C[-2]",FALSE)*INDIRECT("R[0]C[-1]",FALSE)*(1+INDIRECT("R[0]C[-3]",FALSE)))
A8: 7 | B8: Preparation | C8: {=IFERROR(INDEX(Milestones!$A:$A, MATCH($B8, Milestones!$B:$B, 0)), "")} | D8: {=IFERROR(INDEX(Milestones!$C:$C, MATCH($B8, Milestones!$B:$B, 0)), "")} | E8: Verify infrastructure readiness, environment setup, and permissions | F8: {=IFERROR(INDEX(Milestones!$E:$E, MATCH($B8, Milestones!$B:$B, 0)), "")} | G8: Knapsack | H8: {=IFERROR(INDEX(Milestones!$E:$E, MATCH($B8, Milestones!$B:$B, 0)), "")} | I8: FTE | J8: 0.025 | K8: Medium | L8: {=IF($K8="","", IFERROR(IFS($K8="Low", INDEX('Lookups - Complexity'!$C:$C, MATCH($B8, 'Lookups - Complexity'!$B:$B,0)), $K8="Medium", INDEX('Lookups - Complexity'!$D:$D, MATCH($B8, 'Lookups - Complexity'!$B:$B,0)), $K8="High", INDEX('Lookups - Complexity'!$E:$E, MATCH($B8, 'Lookups - Complexity'!$B:$B,0))), ""))} | M8: =IF($I8="FTE", Assumptions!$B$3, "") | N8: {=IFERROR(INDEX(Milestones!$F:$F, MATCH($B8, Milestones!$B:$B, 0)), "")} | O8: {=IFERROR(INDEX(Milestones!$G:$G, MATCH($B8, Milestones!$B:$B, 0)), "")} | P8: {=IFERROR(INDEX('Lookups - Rates'!$D:$D, MATCH($G8&"|"&$H8, 'Lookups - Rates'!$Z:$Z, 0)), "")} | Q8: {=IFERROR(INDEX('Lookups - Rates'!$E:$E, MATCH($G8&"|"&$H8, 'Lookups - Rates'!$Z:$Z, 0)), "")} | R8: =LET(ev,$J8, ch,$L8, hr,$P8, dr,$Q8, hpday,Assumptions!$B$2, hpw,Assumptions!$B$3, w,$M8, hrs, IF($I8="Hours", ev, IF($I8="Days", ev*IF(dr>0, dr/hr, hpday), IF($I8="FTE", ev*hpw*w, ch))), IF(hrs="", "", hrs*hr)) | T8: {=XLOOKUP(Scenario_Selected, INDEX(Scenario_Table,0,1), INDEX(Scenario_Table,0,2))} | U8: {=XLOOKUP(Scenario_Selected, INDEX(Scenario_Table,0,1), INDEX(Scenario_Table,0,3))} | V8: {=XLOOKUP(Scenario_Selected, INDEX(Scenario_Table,0,1), INDEX(Scenario_Table,0,4))} | W8: {=LET(ev,$J8, ch,$L8, et,$I8, dr,$Q8, hpday,Assumptions!$B$2, hpw,Assumptions!$B$3, w,$M8,hm,INDIRECT("R[0]C[0]",FALSE),hrs, IF(et="Hours", ev, IF(et="Days", ev*IF(dr>0, dr/$P8, hpday), IF(et="FTE", ev*hpw*w, ch))), IF(hrs="", "", hrs*hm))} | X8: =IF($P8="","", $P8*INDIRECT("R[0]C[-3]",FALSE)) | Y8: =IF(INDIRECT("R[0]C[-1]",FALSE)="","", INDIRECT("R[0]C[-2]",FALSE)*INDIRECT("R[0]C[-1]",FALSE)*(1+INDIRECT("R[0]C[-3]",FALSE)))
A9: 8 | B9: Local install support | C9: {=IFERROR(INDEX(Milestones!$A:$A, MATCH($B9, Milestones!$B:$B, 0)), "")} | D9: {=IFERROR(INDEX(Milestones!$C:$C, MATCH($B9, Milestones!$B:$B, 0)), "")} | E9: Validate local environment setup for Knapsack and IPE components | F9: {=IFERROR(INDEX(Milestones!$E:$E, MATCH($B9, Milestones!$B:$B, 0)), "")} | G9: Knapsack | H9: {=IFERROR(INDEX(Milestones!$E:$E, MATCH($B9, Milestones!$B:$B, 0)), "")} | I9: FTE | J9: 0.03 | K9: Medium | L9: {=IF($K9="","", IFERROR(IFS($K9="Low", INDEX('Lookups - Complexity'!$C:$C, MATCH($B9, 'Lookups - Complexity'!$B:$B,0)), $K9="Medium", INDEX('Lookups - Complexity'!$D:$D, MATCH($B9, 'Lookups - Complexity'!$B:$B,0)), $K9="High", INDEX('Lookups - Complexity'!$E:$E, MATCH($B9, 'Lookups - Complexity'!$B:$B,0))), ""))} | M9: =IF($I9="FTE", Assumptions!$B$3, "") | N9: {=IFERROR(INDEX(Milestones!$F:$F, MATCH($B9, Milestones!$B:$B, 0)), "")} | O9: {=IFERROR(INDEX(Milestones!$G:$G, MATCH($B9, Milestones!$B:$B, 0)), "")} | P9: {=IFERROR(INDEX('Lookups - Rates'!$D:$D, MATCH($G9&"|"&$H9, 'Lookups - Rates'!$Z:$Z, 0)), "")} | Q9: {=IFERROR(INDEX('Lookups - Rates'!$E:$E, MATCH($G9&"|"&$H9, 'Lookups - Rates'!$Z:$Z, 0)), "")} | R9: =LET(ev,$J9, ch,$L9, hr,$P9, dr,$Q9, hpday,Assumptions!$B$2, hpw,Assumptions!$B$3, w,$M9, hrs, IF($I9="Hours", ev, IF($I9="Days", ev*IF(dr>0, dr/hr, hpday), IF($I9="FTE", ev*hpw*w, ch))), IF(hrs="", "", hrs*hr)) | T9: {=XLOOKUP(Scenario_Selected, INDEX(Scenario_Table,0,1), INDEX(Scenario_Table,0,2))} | U9: {=XLOOKUP(Scenario_Selected, INDEX(Scenario_Table,0,1), INDEX(Scenario_Table,0,3))} | V9: {=XLOOKUP(Scenario_Selected, INDEX(Scenario_Table,0,1), INDEX(Scenario_Table,0,4))} | W9: {=LET(ev,$J9, ch,$L9, et,$I9, dr,$Q9, hpday,Assumptions!$B$2, hpw,Assumptions!$B$3, w,$M9,hm,INDIRECT("R[0]C[0]",FALSE),hrs, IF(et="Hours", ev, IF(et="Days", ev*IF(dr>0, dr/$P9, hpday), IF(et="FTE", ev*hpw*w, ch))), IF(hrs="", "", hrs*hm))} | X9: =IF($P9="","", $P9*INDIRECT("R[0]C[-3]",FALSE)) | Y9: =IF(INDIRECT("R[0]C[-1]",FALSE)="","", INDIRECT("R[0]C[-2]",FALSE)*INDIRECT("R[0]C[-1]",FALSE)*(1+INDIRECT("R[0]C[-3]",FALSE)))
A10: 9 | B10: Component rendering | C10: {=IFERROR(INDEX(Milestones!$A:$A, MATCH($B10, Milestones!$B:$B, 0)), "")} | D10: {=IFERROR(INDEX(Milestones!$C:$C, MATCH($B10, Milestones!$B:$B, 0)), "")} | E10: Validate successful rendering of Spectrum components across environments | F10: {=IFERROR(INDEX(Milestones!$E:$E, MATCH($B10, Milestones!$B:$B, 0)), "")} | G10: Knapsack | H10: {=IFERROR(INDEX(Milestones!$E:$E, MATCH($B10, Milestones!$B:$B, 0)), "")} | I10: FTE | J10: 0.05 | K10: High | L10: {=IF($K10="","", IFERROR(IFS($K10="Low", INDEX('Lookups - Complexity'!$C:$C, MATCH($B10, 'Lookups - Complexity'!$B:$B,0)), $K10="Medium", INDEX('Lookups - Complexity'!$D:$D, MATCH($B10, 'Lookups - Complexity'!$B:$B,0)), $K10="High", INDEX('Lookups - Complexity'!$E:$E, MATCH($B10, 'Lookups - Complexity'!$B:$B,0))), ""))} | M10: =IF($I10="FTE", Assumptions!$B$3, "") | N10: {=IFERROR(INDEX(Milestones!$F:$F, MATCH($B10, Milestones!$B:$B, 0)), "")} | O10: {=IFERROR(INDEX(Milestones!$G:$G, MATCH($B10, Milestones!$B:$B, 0)), "")} | P10: {=IFERROR(INDEX('Lookups - Rates'!$D:$D, MATCH($G10&"|"&$H10, 'Lookups - Rates'!$Z:$Z, 0)), "")} | Q10: {=IFERROR(INDEX('Lookups - Rates'!$E:$E, MATCH($G10&"|"&$H10, 'Lookups - Rates'!$Z:$Z, 0)), "")} | R10: =LET(ev,$J10, ch,$L10, hr,$P10, dr,$Q10, hpday,Assumptions!$B$2, hpw,Assumptions!$B$3, w,$M10, hrs, IF($I10="Hours", ev, IF($I10="Days", ev*IF(dr>0, dr/hr, hpday), IF($I10="FTE", ev*hpw*w, ch))), IF(hrs="", "", hrs*hr)) | T10: {=XLOOKUP(Scenario_Selected, INDEX(Scenario_Table,0,1), INDEX(Scenario_Table,0,2))} | U10: {=XLOOKUP(Scenario_Selected, INDEX(Scenario_Table,0,1), INDEX(Scenario_Table,0,3))} | V10: {=XLOOKUP(Scenario_Selected, INDEX(Scenario_Table,0,1), INDEX(Scenario_Table,0,4))} | W10: {=LET(ev,$J10, ch,$L10, et,$I10, dr,$Q10, hpday,Assumptions!$B$2, hpw,Assumptions!$B$3, w,$M10,hm,INDIRECT("R[0]C[0]",FALSE),hrs, IF(et="Hours", ev, IF(et="Days", ev*IF(dr>0, dr/$P10, hpday), IF(et="FTE", ev*hpw*w, ch))), IF(hrs="", "", hrs*hm))} | X10: =IF($P10="","", $P10*INDIRECT("R[0]C[-3]",FALSE)) | Y10: =IF(INDIRECT("R[0]C[-1]",FALSE)="","", INDIRECT("R[0]C[-2]",FALSE)*INDIRECT("R[0]C[-1]",FALSE)*(1+INDIRECT("R[0]C[-3]",FALSE)))
A11: 10 | B11: SME support for rendering | C11: {=IFERROR(INDEX(Milestones!$A:$A, MATCH($B11, Milestones!$B:$B, 0)), "")} | D11: {=IFERROR(INDEX(Milestones!$C:$C, MATCH($B11, Milestones!$B:$B, 0)), "")} | E11: SME oversight of rendering logic and architectural consistency | F11: {=IFERROR(INDEX(Milestones!$E:$E, MATCH($B11, Milestones!$B:$B, 0)), "")} | G11: Knapsack | H11: {=IFERROR(INDEX(Milestones!$E:$E, MATCH($B11, Milestones!$B:$B, 0)), "")} | I11: FTE | J11: 0.025 | K11: Medium | L11: {=IF($K11="","", IFERROR(IFS($K11="Low", INDEX('Lookups - Complexity'!$C:$C, MATCH($B11, 'Lookups - Complexity'!$B:$B,0)), $K11="Medium", INDEX('Lookups - Complexity'!$D:$D, MATCH($B11, 'Lookups - Complexity'!$B:$B,0)), $K11="High", INDEX('Lookups - Complexity'!$E:$E, MATCH($B11, 'Lookups - Complexity'!$B:$B,0))), ""))} | M11: =IF($I11="FTE", Assumptions!$B$3, "") | N11: {=IFERROR(INDEX(Milestones!$F:$F, MATCH($B11, Milestones!$B:$B, 0)), "")} | O11: {=IFERROR(INDEX(Milestones!$G:$G, MATCH($B11, Milestones!$B:$B, 0)), "")} | P11: {=IFERROR(INDEX('Lookups - Rates'!$D:$D, MATCH($G11&"|"&$H11, 'Lookups - Rates'!$Z:$Z, 0)), "")} | Q11: {=IFERROR(INDEX('Lookups - Rates'!$E:$E, MATCH($G11&"|"&$H11, 'Lookups - Rates'!$Z:$Z, 0)), "")} | R11: =LET(ev,$J11, ch,$L11, hr,$P11, dr,$Q11, hpday,Assumptions!$B$2, hpw,Assumptions!$B$3, w,$M11, hrs, IF($I11="Hours", ev, IF($I11="Days", ev*IF(dr>0, dr/hr, hpday), IF($I11="FTE", ev*hpw*w, ch))), IF(hrs="", "", hrs*hr)) | T11: {=XLOOKUP(Scenario_Selected, INDEX(Scenario_Table,0,1), INDEX(Scenario_Table,0,2))} | U11: {=XLOOKUP(Scenario_Selected, INDEX(Scenario_Table,0,1), INDEX(Scenario_Table,0,3))} | V11: {=XLOOKUP(Scenario_Selected, INDEX(Scenario_Table,0,1), INDEX(Scenario_Table,0,4))} | W11: {=LET(ev,$J11, ch,$L11, et,$I11, dr,$Q11, hpday,Assumptions!$B$2, hpw,Assumptions!$B$3, w,$M11,hm,INDIRECT("R[0]C[0]",FALSE),hrs, IF(et="Hours", ev, IF(et="Days", ev*IF(dr>0, dr/$P11, hpday), IF(et="FTE", ev*hpw*w, ch))), IF(hrs="", "", hrs*hm))} | X11: =IF($P11="","", $P11*INDIRECT("R[0]C[-3]",FALSE)) | Y11: =IF(INDIRECT("R[0]C[-1]",FALSE)="","", INDIRECT("R[0]C[-2]",FALSE)*INDIRECT("R[0]C[-1]",FALSE)*(1+INDIRECT("R[0]C[-3]",FALSE)))
A12: 11 | B12: Deployment support | C12: {=IFERROR(INDEX(Milestones!$A:$A, MATCH($B12, Milestones!$B:$B, 0)), "")} | D12: {=IFERROR(INDEX(Milestones!$C:$C, MATCH($B12, Milestones!$B:$B, 0)), "")} | E12: Plan and validate deployment pipelines with measurable success criteria | F12: {=IFERROR(INDEX(Milestones!$E:$E, MATCH($B12, Milestones!$B:$B, 0)), "")} | G12: Knapsack | H12: {=IFERROR(INDEX(Milestones!$E:$E, MATCH($B12, Milestones!$B:$B, 0)), "")} | I12: FTE | J12: 0.025 | K12: Medium | L12: {=IF($K12="","", IFERROR(IFS($K12="Low", INDEX('Lookups - Complexity'!$C:$C, MATCH($B12, 'Lookups - Complexity'!$B:$B,0)), $K12="Medium", INDEX('Lookups - Complexity'!$D:$D, MATCH($B12, 'Lookups - Complexity'!$B:$B,0)), $K12="High", INDEX('Lookups - Complexity'!$E:$E, MATCH($B12, 'Lookups - Complexity'!$B:$B,0))), ""))} | M12: =IF($I12="FTE", Assumptions!$B$3, "") | N12: {=IFERROR(INDEX(Milestones!$F:$F, MATCH($B12, Milestones!$B:$B, 0)), "")} | O12: {=IFERROR(INDEX(Milestones!$G:$G, MATCH($B12, Milestones!$B:$B, 0)), "")} | P12: {=IFERROR(INDEX('Lookups - Rates'!$D:$D, MATCH($G12&"|"&$H12, 'Lookups - Rates'!$Z:$Z, 0)), "")} | Q12: {=IFERROR(INDEX('Lookups - Rates'!$E:$E, MATCH($G12&"|"&$H12, 'Lookups - Rates'!$Z:$Z, 0)), "")} | R12: =LET(ev,$J12, ch,$L12, hr,$P12, dr,$Q12, hpday,Assumptions!$B$2, hpw,Assumptions!$B$3, w,$M12, hrs, IF($I12="Hours", ev, IF($I12="Days", ev*IF(dr>0, dr/hr, hpday), IF($I12="FTE", ev*hpw*w, ch))), IF(hrs="", "", hrs*hr)) | T12: {=XLOOKUP(Scenario_Selected, INDEX(Scenario_Table,0,1), INDEX(Scenario_Table,0,2))} | U12: {=XLOOKUP(Scenario_Selected, INDEX(Scenario_Table,0,1), INDEX(Scenario_Table,0,3))} | V12: {=XLOOKUP(Scenario_Selected, INDEX(Scenario_Table,0,1), INDEX(Scenario_Table,0,4))} | W12: {=LET(ev,$J12, ch,$L12, et,$I12, dr,$Q12, hpday,Assumptions!$B$2, hpw,Assumptions!$B$3, w,$M12,hm,INDIRECT("R[0]C[0]",FALSE),hrs, IF(et="Hours", ev, IF(et="Days", ev*IF(dr>0, dr/$P12, hpday), IF(et="FTE", ev*hpw*w, ch))), IF(hrs="", "", hrs*hm))} | X12: =IF($P12="","", $P12*INDIRECT("R[0]C[-3]",FALSE)) | Y12: =IF(INDIRECT("R[0]C[-1]",FALSE)="","", INDIRECT("R[0]C[-2]",FALSE)*INDIRECT("R[0]C[-1]",FALSE)*(1+INDIRECT("R[0]C[-3]",FALSE)))
A13: 12 | B13: FDE led Implementation + Architecture + Governance | C13: {=IFERROR(INDEX(Milestones!$A:$A, MATCH($B13, Milestones!$B:$B, 0)), "")} | D13: {=IFERROR(INDEX(Milestones!$C:$C, MATCH($B13, Milestones!$B:$B, 0)), "")} | E13: Define architecture, component contribution model, accessibility, governance framework | F13: {=IFERROR(INDEX(Milestones!$E:$E, MATCH($B13, Milestones!$B:$B, 0)), "")} | G13: Knapsack | H13: {=IFERROR(INDEX(Milestones!$E:$E, MATCH($B13, Milestones!$B:$B, 0)), "")} | I13: FTE | J13: 0.03 | K13: Medium | L13: {=IF($K13="","", IFERROR(IFS($K13="Low", INDEX('Lookups - Complexity'!$C:$C, MATCH($B13, 'Lookups - Complexity'!$B:$B,0)), $K13="Medium", INDEX('Lookups - Complexity'!$D:$D, MATCH($B13, 'Lookups - Complexity'!$B:$B,0)), $K13="High", INDEX('Lookups - Complexity'!$E:$E, MATCH($B13, 'Lookups - Complexity'!$B:$B,0))), ""))} | M13: =IF($I13="FTE", Assumptions!$B$3, "") | N13: {=IFERROR(INDEX(Milestones!$F:$F, MATCH($B13, Milestones!$B:$B, 0)), "")} | O13: {=IFERROR(INDEX(Milestones!$G:$G, MATCH($B13, Milestones!$B:$B, 0)), "")} | P13: {=IFERROR(INDEX('Lookups - Rates'!$D:$D, MATCH($G13&"|"&$H13, 'Lookups - Rates'!$Z:$Z, 0)), "")} | Q13: {=IFERROR(INDEX('Lookups - Rates'!$E:$E, MATCH($G13&"|"&$H13, 'Lookups - Rates'!$Z:$Z, 0)), "")} | R13: =LET(ev,$J13, ch,$L13, hr,$P13, dr,$Q13, hpday,Assumptions!$B$2, hpw,Assumptions!$B$3, w,$M13, hrs, IF($I13="Hours", ev, IF($I13="Days", ev*IF(dr>0, dr/hr, hpday), IF($I13="FTE", ev*hpw*w, ch))), IF(hrs="", "", hrs*hr)) | S13: This is your Forward Deployed Engineer who will be accountable for phased Milestone Activities. | T13: {=XLOOKUP(Scenario_Selected, INDEX(Scenario_Table,0,1), INDEX(Scenario_Table,0,2))} | U13: {=XLOOKUP(Scenario_Selected, INDEX(Scenario_Table,0,1), INDEX(Scenario_Table,0,3))} | V13: {=XLOOKUP(Scenario_Selected, INDEX(Scenario_Table,0,1), INDEX(Scenario_Table,0,4))} | W13: {=LET(ev,$J13, ch,$L13, et,$I13, dr,$Q13, hpday,Assumptions!$B$2, hpw,Assumptions!$B$3, w,$M13,hm,INDIRECT("R[0]C[0]",FALSE),hrs, IF(et="Hours", ev, IF(et="Days", ev*IF(dr>0, dr/$P13, hpday), IF(et="FTE", ev*hpw*w, ch))), IF(hrs="", "", hrs*hm))} | X13: =IF($P13="","", $P13*INDIRECT("R[0]C[-3]",FALSE)) | Y13: =IF(INDIRECT("R[0]C[-1]",FALSE)="","", INDIRECT("R[0]C[-2]",FALSE)*INDIRECT("R[0]C[-1]",FALSE)*(1+INDIRECT("R[0]C[-3]",FALSE)))
A14: 13 | B14: Stakeholder Interviews/Workshops | C14: {=IFERROR(INDEX(Milestones!$A:$A, MATCH($B14, Milestones!$B:$B, 0)), "")} | D14: {=IFERROR(INDEX(Milestones!$C:$C, MATCH($B14, Milestones!$B:$B, 0)), "")} | E14: Collect stakeholder inputs and align roadmap | F14: {=IFERROR(INDEX(Milestones!$E:$E, MATCH($B14, Milestones!$B:$B, 0)), "")} | G14: Knapsack | H14: {=IFERROR(INDEX(Milestones!$E:$E, MATCH($B14, Milestones!$B:$B, 0)), "")} | I14: FTE | J14: 0.025 | K14: Medium | L14: {=IF($K14="","", IFERROR(IFS($K14="Low", INDEX('Lookups - Complexity'!$C:$C, MATCH($B14, 'Lookups - Complexity'!$B:$B,0)), $K14="Medium", INDEX('Lookups - Complexity'!$D:$D, MATCH($B14, 'Lookups - Complexity'!$B:$B,0)), $K14="High", INDEX('Lookups - Complexity'!$E:$E, MATCH($B14, 'Lookups - Complexity'!$B:$B,0))), ""))} | M14: =IF($I14="FTE", Assumptions!$B$3, "") | N14: {=IFERROR(INDEX(Milestones!$F:$F, MATCH($B14, Milestones!$B:$B, 0)), "")} | O14: {=IFERROR(INDEX(Milestones!$G:$G, MATCH($B14, Milestones!$B:$B, 0)), "")} | P14: {=IFERROR(INDEX('Lookups - Rates'!$D:$D, MATCH($G14&"|"&$H14, 'Lookups - Rates'!$Z:$Z, 0)), "")} | Q14: {=IFERROR(INDEX('Lookups - Rates'!$E:$E, MATCH($G14&"|"&$H14, 'Lookups - Rates'!$Z:$Z, 0)), "")} | R14: =LET(ev,$J14, ch,$L14, hr,$P14, dr,$Q14, hpday,Assumptions!$B$2, hpw,Assumptions!$B$3, w,$M14, hrs, IF($I14="Hours", ev, IF($I14="Days", ev*IF(dr>0, dr/hr, hpday), IF($I14="FTE", ev*hpw*w, ch))), IF(hrs="", "", hrs*hr)) | T14: {=XLOOKUP(Scenario_Selected, INDEX(Scenario_Table,0,1), INDEX(Scenario_Table,0,2))} | U14: {=XLOOKUP(Scenario_Selected, INDEX(Scenario_Table,0,1), INDEX(Scenario_Table,0,3))} | V14: {=XLOOKUP(Scenario_Selected, INDEX(Scenario_Table,0,1), INDEX(Scenario_Table,0,4))} | W14: {=LET(ev,$J14, ch,$L14, et,$I14, dr,$Q14, hpday,Assumptions!$B$2, hpw,Assumptions!$B$3, w,$M14,hm,INDIRECT("R[0]C[0]",FALSE),hrs, IF(et="Hours", ev, IF(et="Days", ev*IF(dr>0, dr/$P14, hpday), IF(et="FTE", ev*hpw*w, ch))), IF(hrs="", "", hrs*hm))} | X14: =IF($P14="","", $P14*INDIRECT("R[0]C[-3]",FALSE)) | Y14: =IF(INDIRECT("R[0]C[-1]",FALSE)="","", INDIRECT("R[0]C[-2]",FALSE)*INDIRECT("R[0]C[-1]",FALSE)*(1+INDIRECT("R[0]C[-3]",FALSE)))
A15: 14 | B15: Pilot Enablement & Feedback Loop | C15: {=IFERROR(INDEX(Milestones!$A:$A, MATCH($B15, Milestones!$B:$B, 0)), "")} | D15: {=IFERROR(INDEX(Milestones!$C:$C, MATCH($B15, Milestones!$B:$B, 0)), "")} | E15: Gather early adopter feedback and adjust onboarding approach. | F15: {=IFERROR(INDEX(Milestones!$E:$E, MATCH($B15, Milestones!$B:$B, 0)), "")} | G15: Adobe | H15: Adobe | I15: FTE | J15: 0.05 | K15: High | L15: {=IF($K15="","", IFERROR(IFS($K15="Low", INDEX('Lookups - Complexity'!$C:$C, MATCH($B15, 'Lookups - Complexity'!$B:$B,0)), $K15="Medium", INDEX('Lookups - Complexity'!$D:$D, MATCH($B15, 'Lookups - Complexity'!$B:$B,0)), $K15="High", INDEX('Lookups - Complexity'!$E:$E, MATCH($B15, 'Lookups - Complexity'!$B:$B,0))), ""))} | M15: =IF($I15="FTE", Assumptions!$B$3, "") | N15: {=IFERROR(INDEX(Milestones!$F:$F, MATCH($B15, Milestones!$B:$B, 0)), "")} | O15: {=IFERROR(INDEX(Milestones!$G:$G, MATCH($B15, Milestones!$B:$B, 0)), "")} | P15: {=IFERROR(INDEX('Lookups - Rates'!$D:$D, MATCH($G15&"|"&$H15, 'Lookups - Rates'!$Z:$Z, 0)), "")} | Q15: {=IFERROR(INDEX('Lookups - Rates'!$E:$E, MATCH($G15&"|"&$H15, 'Lookups - Rates'!$Z:$Z, 0)), "")} | R15: =LET(ev,$J15, ch,$L15, hr,$P15, dr,$Q15, hpday,Assumptions!$B$2, hpw,Assumptions!$B$3, w,$M15, hrs, IF($I15="Hours", ev, IF($I15="Days", ev*IF(dr>0, dr/hr, hpday), IF($I15="FTE", ev*hpw*w, ch))), IF(hrs="", "", hrs*hr)) | T15: {=XLOOKUP(Scenario_Selected, INDEX(Scenario_Table,0,1), INDEX(Scenario_Table,0,2))} | U15: {=XLOOKUP(Scenario_Selected, INDEX(Scenario_Table,0,1), INDEX(Scenario_Table,0,3))} | V15: {=XLOOKUP(Scenario_Selected, INDEX(Scenario_Table,0,1), INDEX(Scenario_Table,0,4))} | W15: {=LET(ev,$J15, ch,$L15, et,$I15, dr,$Q15, hpday,Assumptions!$B$2, hpw,Assumptions!$B$3, w,$M15,hm,INDIRECT("R[0]C[0]",FALSE),hrs, IF(et="Hours", ev, IF(et="Days", ev*IF(dr>0, dr/$P15, hpday), IF(et="FTE", ev*hpw*w, ch))), IF(hrs="", "", hrs*hm))} | X15: =IF($P15="","", $P15*INDIRECT("R[0]C[-3]",FALSE)) | Y15: =IF(INDIRECT("R[0]C[-1]",FALSE)="","", INDIRECT("R[0]C[-2]",FALSE)*INDIRECT("R[0]C[-1]",FALSE)*(1+INDIRECT("R[0]C[-3]",FALSE)))
A16: 15 | B16: Role-Based Training Enablement | C16: {=IFERROR(INDEX(Milestones!$A:$A, MATCH($B16, Milestones!$B:$B, 0)), "")} | D16: {=IFERROR(INDEX(Milestones!$C:$C, MATCH($B16, Milestones!$B:$B, 0)), "")} | E16: Deliver tailored enablement by persona to improve comprehension and adoption. | F16: {=IFERROR(INDEX(Milestones!$E:$E, MATCH($B16, Milestones!$B:$B, 0)), "")} | G16: Adobe | H16: Adobe | I16: FTE | J16: 0.05 | K16: High | L16: {=IF($K16="","", IFERROR(IFS($K16="Low", INDEX('Lookups - Complexity'!$C:$C, MATCH($B16, 'Lookups - Complexity'!$B:$B,0)), $K16="Medium", INDEX('Lookups - Complexity'!$D:$D, MATCH($B16, 'Lookups - Complexity'!$B:$B,0)), $K16="High", INDEX('Lookups - Complexity'!$E:$E, MATCH($B16, 'Lookups - Complexity'!$B:$B,0))), ""))} | M16: =IF($I16="FTE", Assumptions!$B$3, "") | N16: {=IFERROR(INDEX(Milestones!$F:$F, MATCH($B16, Milestones!$B:$B, 0)), "")} | O16: {=IFERROR(INDEX(Milestones!$G:$G, MATCH($B16, Milestones!$B:$B, 0)), "")} | P16: {=IFERROR(INDEX('Lookups - Rates'!$D:$D, MATCH($G16&"|"&$H16, 'Lookups - Rates'!$Z:$Z, 0)), "")} | Q16: {=IFERROR(INDEX('Lookups - Rates'!$E:$E, MATCH($G16&"|"&$H16, 'Lookups - Rates'!$Z:$Z, 0)), "")} | R16: =LET(ev,$J16, ch,$L16, hr,$P16, dr,$Q16, hpday,Assumptions!$B$2, hpw,Assumptions!$B$3, w,$M16, hrs, IF($I16="Hours", ev, IF($I16="Days", ev*IF(dr>0, dr/hr, hpday), IF($I16="FTE", ev*hpw*w, ch))), IF(hrs="", "", hrs*hr)) | T16: {=XLOOKUP(Scenario_Selected, INDEX(Scenario_Table,0,1), INDEX(Scenario_Table,0,2))} | U16: {=XLOOKUP(Scenario_Selected, INDEX(Scenario_Table,0,1), INDEX(Scenario_Table,0,3))} | V16: {=XLOOKUP(Scenario_Selected, INDEX(Scenario_Table,0,1), INDEX(Scenario_Table,0,4))} | W16: {=LET(ev,$J16, ch,$L16, et,$I16, dr,$Q16, hpday,Assumptions!$B$2, hpw,Assumptions!$B$3, w,$M16,hm,INDIRECT("R[0]C[0]",FALSE),hrs, IF(et="Hours", ev, IF(et="Days", ev*IF(dr>0, dr/$P16, hpday), IF(et="FTE", ev*hpw*w, ch))), IF(hrs="", "", hrs*hm))} | X16: =IF($P16="","", $P16*INDIRECT("R[0]C[-3]",FALSE)) | Y16: =IF(INDIRECT("R[0]C[-1]",FALSE)="","", INDIRECT("R[0]C[-2]",FALSE)*INDIRECT("R[0]C[-1]",FALSE)*(1+INDIRECT("R[0]C[-3]",FALSE)))
A17: 16 | B17: SME support for Deployment/DevOps | C17: {=IFERROR(INDEX(Milestones!$A:$A, MATCH($B17, Milestones!$B:$B, 0)), "")} | D17: {=IFERROR(INDEX(Milestones!$C:$C, MATCH($B17, Milestones!$B:$B, 0)), "")} | E17: Validate CI/CD, cloud authoring, and deployment automation readiness | F17: {=IFERROR(INDEX(Milestones!$E:$E, MATCH($B17, Milestones!$B:$B, 0)), "")} | G17: Knapsack | H17: {=IFERROR(INDEX(Milestones!$E:$E, MATCH($B17, Milestones!$B:$B, 0)), "")} | I17: FTE | J17: 0.03 | K17: Medium | L17: {=IF($K17="","", IFERROR(IFS($K17="Low", INDEX('Lookups - Complexity'!$C:$C, MATCH($B17, 'Lookups - Complexity'!$B:$B,0)), $K17="Medium", INDEX('Lookups - Complexity'!$D:$D, MATCH($B17, 'Lookups - Complexity'!$B:$B,0)), $K17="High", INDEX('Lookups - Complexity'!$E:$E, MATCH($B17, 'Lookups - Complexity'!$B:$B,0))), ""))} | M17: =IF($I17="FTE", Assumptions!$B$3, "") | N17: {=IFERROR(INDEX(Milestones!$F:$F, MATCH($B17, Milestones!$B:$B, 0)), "")} | O17: {=IFERROR(INDEX(Milestones!$G:$G, MATCH($B17, Milestones!$B:$B, 0)), "")} | P17: {=IFERROR(INDEX('Lookups - Rates'!$D:$D, MATCH($G17&"|"&$H17, 'Lookups - Rates'!$Z:$Z, 0)), "")} | Q17: {=IFERROR(INDEX('Lookups - Rates'!$E:$E, MATCH($G17&"|"&$H17, 'Lookups - Rates'!$Z:$Z, 0)), "")} | R17: =LET(ev,$J17, ch,$L17, hr,$P17, dr,$Q17, hpday,Assumptions!$B$2, hpw,Assumptions!$B$3, w,$M17, hrs, IF($I17="Hours", ev, IF($I17="Days", ev*IF(dr>0, dr/hr, hpday), IF($I17="FTE", ev*hpw*w, ch))), IF(hrs="", "", hrs*hr)) | T17: {=XLOOKUP(Scenario_Selected, INDEX(Scenario_Table,0,1), INDEX(Scenario_Table,0,2))} | U17: {=XLOOKUP(Scenario_Selected, INDEX(Scenario_Table,0,1), INDEX(Scenario_Table,0,3))} | V17: {=XLOOKUP(Scenario_Selected, INDEX(Scenario_Table,0,1), INDEX(Scenario_Table,0,4))} | W17: {=LET(ev,$J17, ch,$L17, et,$I17, dr,$Q17, hpday,Assumptions!$B$2, hpw,Assumptions!$B$3, w,$M17,hm,INDIRECT("R[0]C[0]",FALSE),hrs, IF(et="Hours", ev, IF(et="Days", ev*IF(dr>0, dr/$P17, hpday), IF(et="FTE", ev*hpw*w, ch))), IF(hrs="", "", hrs*hm))} | X17: =IF($P17="","", $P17*INDIRECT("R[0]C[-3]",FALSE)) | Y17: =IF(INDIRECT("R[0]C[-1]",FALSE)="","", INDIRECT("R[0]C[-2]",FALSE)*INDIRECT("R[0]C[-1]",FALSE)*(1+INDIRECT("R[0]C[-3]",FALSE))) | Z17: Reference the playbook to support understanding here
A18: 17 | B18: Cloud authoring setup and testing | C18: {=IFERROR(INDEX(Milestones!$A:$A, MATCH($B18, Milestones!$B:$B, 0)), "")} | D18: {=IFERROR(INDEX(Milestones!$C:$C, MATCH($B18, Milestones!$B:$B, 0)), "")} | E18: Setup and validate authoring in cloud environments | F18: {=IFERROR(INDEX(Milestones!$E:$E, MATCH($B18, Milestones!$B:$B, 0)), "")} | G18: Knapsack | H18: {=IFERROR(INDEX(Milestones!$E:$E, MATCH($B18, Milestones!$B:$B, 0)), "")} | I18: FTE | J18: 0.05 | K18: High | L18: {=IF($K18="","", IFERROR(IFS($K18="Low", INDEX('Lookups - Complexity'!$C:$C, MATCH($B18, 'Lookups - Complexity'!$B:$B,0)), $K18="Medium", INDEX('Lookups - Complexity'!$D:$D, MATCH($B18, 'Lookups - Complexity'!$B:$B,0)), $K18="High", INDEX('Lookups - Complexity'!$E:$E, MATCH($B18, 'Lookups - Complexity'!$B:$B,0))), ""))} | M18: =IF($I18="FTE", Assumptions!$B$3, "") | N18: {=IFERROR(INDEX(Milestones!$F:$F, MATCH($B18, Milestones!$B:$B, 0)), "")} | O18: {=IFERROR(INDEX(Milestones!$G:$G, MATCH($B18, Milestones!$B:$B, 0)), "")} | P18: {=IFERROR(INDEX('Lookups - Rates'!$D:$D, MATCH($G18&"|"&$H18, 'Lookups - Rates'!$Z:$Z, 0)), "")} | Q18: {=IFERROR(INDEX('Lookups - Rates'!$E:$E, MATCH($G18&"|"&$H18, 'Lookups - Rates'!$Z:$Z, 0)), "")} | R18: =LET(ev,$J18, ch,$L18, hr,$P18, dr,$Q18, hpday,Assumptions!$B$2, hpw,Assumptions!$B$3, w,$M18, hrs, IF($I18="Hours", ev, IF($I18="Days", ev*IF(dr>0, dr/hr, hpday), IF($I18="FTE", ev*hpw*w, ch))), IF(hrs="", "", hrs*hr)) | T18: {=XLOOKUP(Scenario_Selected, INDEX(Scenario_Table,0,1), INDEX(Scenario_Table,0,2))} | U18: {=XLOOKUP(Scenario_Selected, INDEX(Scenario_Table,0,1), INDEX(Scenario_Table,0,3))} | V18: {=XLOOKUP(Scenario_Selected, INDEX(Scenario_Table,0,1), INDEX(Scenario_Table,0,4))} | W18: {=LET(ev,$J18, ch,$L18, et,$I18, dr,$Q18, hpday,Assumptions!$B$2, hpw,Assumptions!$B$3, w,$M18,hm,INDIRECT("R[0]C[0]",FALSE),hrs, IF(et="Hours", ev, IF(et="Days", ev*IF(dr>0, dr/$P18, hpday), IF(et="FTE", ev*hpw*w, ch))), IF(hrs="", "", hrs*hm))} | X18: =IF($P18="","", $P18*INDIRECT("R[0]C[-3]",FALSE)) | Y18: =IF(INDIRECT("R[0]C[-1]",FALSE)="","", INDIRECT("R[0]C[-2]",FALSE)*INDIRECT("R[0]C[-1]",FALSE)*(1+INDIRECT("R[0]C[-3]",FALSE)))
A19: 18 | B19: SSO setup and testing | C19: {=IFERROR(INDEX(Milestones!$A:$A, MATCH($B19, Milestones!$B:$B, 0)), "")} | D19: {=IFERROR(INDEX(Milestones!$C:$C, MATCH($B19, Milestones!$B:$B, 0)), "")} | E19: Configure and test single sign-on with enterprise identity provider | F19: {=IFERROR(INDEX(Milestones!$E:$E, MATCH($B19, Milestones!$B:$B, 0)), "")} | G19: Knapsack | H19: {=IFERROR(INDEX(Milestones!$E:$E, MATCH($B19, Milestones!$B:$B, 0)), "")} | I19: FTE | J19: 0.03 | K19: Medium | L19: {=IF($K19="","", IFERROR(IFS($K19="Low", INDEX('Lookups - Complexity'!$C:$C, MATCH($B19, 'Lookups - Complexity'!$B:$B,0)), $K19="Medium", INDEX('Lookups - Complexity'!$D:$D, MATCH($B19, 'Lookups - Complexity'!$B:$B,0)), $K19="High", INDEX('Lookups - Complexity'!$E:$E, MATCH($B19, 'Lookups - Complexity'!$B:$B,0))), ""))} | M19: =IF($I19="FTE", Assumptions!$B$3, "") | N19: {=IFERROR(INDEX(Milestones!$F:$F, MATCH($B19, Milestones!$B:$B, 0)), "")} | O19: {=IFERROR(INDEX(Milestones!$G:$G, MATCH($B19, Milestones!$B:$B, 0)), "")} | P19: {=IFERROR(INDEX('Lookups - Rates'!$D:$D, MATCH($G19&"|"&$H19, 'Lookups - Rates'!$Z:$Z, 0)), "")} | Q19: {=IFERROR(INDEX('Lookups - Rates'!$E:$E, MATCH($G19&"|"&$H19, 'Lookups - Rates'!$Z:$Z, 0)), "")} | R19: =LET(ev,$J19, ch,$L19, hr,$P19, dr,$Q19, hpday,Assumptions!$B$2, hpw,Assumptions!$B$3, w,$M19, hrs, IF($I19="Hours", ev, IF($I19="Days", ev*IF(dr>0, dr/hr, hpday), IF($I19="FTE", ev*hpw*w, ch))), IF(hrs="", "", hrs*hr)) | S19: This is a medium effort IF Adobe speaks vanilla SAML SSO | T19: {=XLOOKUP(Scenario_Selected, INDEX(Scenario_Table,0,1), INDEX(Scenario_Table,0,2))} | U19: {=XLOOKUP(Scenario_Selected, INDEX(Scenario_Table,0,1), INDEX(Scenario_Table,0,3))} | V19: {=XLOOKUP(Scenario_Selected, INDEX(Scenario_Table,0,1), INDEX(Scenario_Table,0,4))} | W19: {=LET(ev,$J19, ch,$L19, et,$I19, dr,$Q19, hpday,Assumptions!$B$2, hpw,Assumptions!$B$3, w,$M19,hm,INDIRECT("R[0]C[0]",FALSE),hrs, IF(et="Hours", ev, IF(et="Days", ev*IF(dr>0, dr/$P19, hpday), IF(et="FTE", ev*hpw*w, ch))), IF(hrs="", "", hrs*hm))} | X19: =IF($P19="","", $P19*INDIRECT("R[0]C[-3]",FALSE)) | Y19: =IF(INDIRECT("R[0]C[-1]",FALSE)="","", INDIRECT("R[0]C[-2]",FALSE)*INDIRECT("R[0]C[-1]",FALSE)*(1+INDIRECT("R[0]C[-3]",FALSE))) | Z19: Reference the playbook to support understanding here
A20: 19 | B20: Training - Eng / UX / Partners | C20: {=IFERROR(INDEX(Milestones!$A:$A, MATCH($B20, Milestones!$B:$B, 0)), "")} | D20: {=IFERROR(INDEX(Milestones!$C:$C, MATCH($B20, Milestones!$B:$B, 0)), "")} | E20: Integrated training for engineering, UX, and partner audiences | F20: {=IFERROR(INDEX(Milestones!$E:$E, MATCH($B20, Milestones!$B:$B, 0)), "")} | G20: Adobe | H20: {=IFERROR(INDEX(Milestones!$E:$E, MATCH($B20, Milestones!$B:$B, 0)), "")} | I20: FTE | J20: 0.05 | K20: High | L20: {=IF($K20="","", IFERROR(IFS($K20="Low", INDEX('Lookups - Complexity'!$C:$C, MATCH($B20, 'Lookups - Complexity'!$B:$B,0)), $K20="Medium", INDEX('Lookups - Complexity'!$D:$D, MATCH($B20, 'Lookups - Complexity'!$B:$B,0)), $K20="High", INDEX('Lookups - Complexity'!$E:$E, MATCH($B20, 'Lookups - Complexity'!$B:$B,0))), ""))} | M20: =IF($I20="FTE", Assumptions!$B$3, "") | N20: {=IFERROR(INDEX(Milestones!$F:$F, MATCH($B20, Milestones!$B:$B, 0)), "")} | O20: {=IFERROR(INDEX(Milestones!$G:$G, MATCH($B20, Milestones!$B:$B, 0)), "")} | P20: {=IFERROR(INDEX('Lookups - Rates'!$D:$D, MATCH($G20&"|"&$H20, 'Lookups - Rates'!$Z:$Z, 0)), "")} | Q20: {=IFERROR(INDEX('Lookups - Rates'!$E:$E, MATCH($G20&"|"&$H20, 'Lookups - Rates'!$Z:$Z, 0)), "")} | R20: =LET(ev,$J20, ch,$L20, hr,$P20, dr,$Q20, hpday,Assumptions!$B$2, hpw,Assumptions!$B$3, w,$M20, hrs, IF($I20="Hours", ev, IF($I20="Days", ev*IF(dr>0, dr/hr, hpday), IF($I20="FTE", ev*hpw*w, ch))), IF(hrs="", "", hrs*hr)) | T20: {=XLOOKUP(Scenario_Selected, INDEX(Scenario_Table,0,1), INDEX(Scenario_Table,0,2))} | U20: {=XLOOKUP(Scenario_Selected, INDEX(Scenario_Table,0,1), INDEX(Scenario_Table,0,3))} | V20: {=XLOOKUP(Scenario_Selected, INDEX(Scenario_Table,0,1), INDEX(Scenario_Table,0,4))} | W20: {=LET(ev,$J20, ch,$L20, et,$I20, dr,$Q20, hpday,Assumptions!$B$2, hpw,Assumptions!$B$3, w,$M20,hm,INDIRECT("R[0]C[0]",FALSE),hrs, IF(et="Hours", ev, IF(et="Days", ev*IF(dr>0, dr/$P20, hpday), IF(et="FTE", ev*hpw*w, ch))), IF(hrs="", "", hrs*hm))} | X20: =IF($P20="","", $P20*INDIRECT("R[0]C[-3]",FALSE)) | Y20: =IF(INDIRECT("R[0]C[-1]",FALSE)="","", INDIRECT("R[0]C[-2]",FALSE)*INDIRECT("R[0]C[-1]",FALSE)*(1+INDIRECT("R[0]C[-3]",FALSE))) | Z20: Adobe practice today
A21: 20 | B21: Workflow Diagrams | C21: {=IFERROR(INDEX(Milestones!$A:$A, MATCH($B21, Milestones!$B:$B, 0)), "")} | D21: {=IFERROR(INDEX(Milestones!$C:$C, MATCH($B21, Milestones!$B:$B, 0)), "")} | E21: Map self-service contribution and implementation workflows | F21: {=IFERROR(INDEX(Milestones!$E:$E, MATCH($B21, Milestones!$B:$B, 0)), "")} | G21: Knapsack | H21: {=IFERROR(INDEX(Milestones!$E:$E, MATCH($B21, Milestones!$B:$B, 0)), "")} | I21: FTE | J21: 0.025 | K21: Medium | L21: {=IF($K21="","", IFERROR(IFS($K21="Low", INDEX('Lookups - Complexity'!$C:$C, MATCH($B21, 'Lookups - Complexity'!$B:$B,0)), $K21="Medium", INDEX('Lookups - Complexity'!$D:$D, MATCH($B21, 'Lookups - Complexity'!$B:$B,0)), $K21="High", INDEX('Lookups - Complexity'!$E:$E, MATCH($B21, 'Lookups - Complexity'!$B:$B,0))), ""))} | M21: =IF($I21="FTE", Assumptions!$B$3, "") | N21: {=IFERROR(INDEX(Milestones!$F:$F, MATCH($B21, Milestones!$B:$B, 0)), "")} | O21: {=IFERROR(INDEX(Milestones!$G:$G, MATCH($B21, Milestones!$B:$B, 0)), "")} | P21: {=IFERROR(INDEX('Lookups - Rates'!$D:$D, MATCH($G21&"|"&$H21, 'Lookups - Rates'!$Z:$Z, 0)), "")} | Q21: {=IFERROR(INDEX('Lookups - Rates'!$E:$E, MATCH($G21&"|"&$H21, 'Lookups - Rates'!$Z:$Z, 0)), "")} | R21: =LET(ev,$J21, ch,$L21, hr,$P21, dr,$Q21, hpday,Assumptions!$B$2, hpw,Assumptions!$B$3, w,$M21, hrs, IF($I21="Hours", ev, IF($I21="Days", ev*IF(dr>0, dr/hr, hpday), IF($I21="FTE", ev*hpw*w, ch))), IF(hrs="", "", hrs*hr)) | T21: {=XLOOKUP(Scenario_Selected, INDEX(Scenario_Table,0,1), INDEX(Scenario_Table,0,2))} | U21: {=XLOOKUP(Scenario_Selected, INDEX(Scenario_Table,0,1), INDEX(Scenario_Table,0,3))} | V21: {=XLOOKUP(Scenario_Selected, INDEX(Scenario_Table,0,1), INDEX(Scenario_Table,0,4))} | W21: {=LET(ev,$J21, ch,$L21, et,$I21, dr,$Q21, hpday,Assumptions!$B$2, hpw,Assumptions!$B$3, w,$M21,hm,INDIRECT("R[0]C[0]",FALSE),hrs, IF(et="Hours", ev, IF(et="Days", ev*IF(dr>0, dr/$P21, hpday), IF(et="FTE", ev*hpw*w, ch))), IF(hrs="", "", hrs*hm))} | X21: =IF($P21="","", $P21*INDIRECT("R[0]C[-3]",FALSE)) | Y21: =IF(INDIRECT("R[0]C[-1]",FALSE)="","", INDIRECT("R[0]C[-2]",FALSE)*INDIRECT("R[0]C[-1]",FALSE)*(1+INDIRECT("R[0]C[-3]",FALSE))) | Z21: Adobe practice today - might be a better choice for Knapsack to own. Adobe Responsible for the intitial recommended workflows. To be tested and validated in support of the curriculum
A22: 21 | B22: Content planning and integration | C22: {=IFERROR(INDEX(Milestones!$A:$A, MATCH($B22, Milestones!$B:$B, 0)), "")} | D22: {=IFERROR(INDEX(Milestones!$C:$C, MATCH($B22, Milestones!$B:$B, 0)), "")} | E22: Documentation for web, React, iOS, Android implementations | F22: Adobe | G22: Knapsack | H22: {=IFERROR(INDEX(Milestones!$E:$E, MATCH($B22, Milestones!$B:$B, 0)), "")} | I22: FTE | J22: 0.05 | K22: High | L22: {=IF($K22="","", IFERROR(IFS($K22="Low", INDEX('Lookups - Complexity'!$C:$C, MATCH($B22, 'Lookups - Complexity'!$B:$B,0)), $K22="Medium", INDEX('Lookups - Complexity'!$D:$D, MATCH($B22, 'Lookups - Complexity'!$B:$B,0)), $K22="High", INDEX('Lookups - Complexity'!$E:$E, MATCH($B22, 'Lookups - Complexity'!$B:$B,0))), ""))} | M22: =IF($I22="FTE", Assumptions!$B$3, "") | N22: {=IFERROR(INDEX(Milestones!$F:$F, MATCH($B22, Milestones!$B:$B, 0)), "")} | O22: {=IFERROR(INDEX(Milestones!$G:$G, MATCH($B22, Milestones!$B:$B, 0)), "")} | P22: {=IFERROR(INDEX('Lookups - Rates'!$D:$D, MATCH($G22&"|"&$H22, 'Lookups - Rates'!$Z:$Z, 0)), "")} | Q22: {=IFERROR(INDEX('Lookups - Rates'!$E:$E, MATCH($G22&"|"&$H22, 'Lookups - Rates'!$Z:$Z, 0)), "")} | R22: =LET(ev,$J22, ch,$L22, hr,$P22, dr,$Q22, hpday,Assumptions!$B$2, hpw,Assumptions!$B$3, w,$M22, hrs, IF($I22="Hours", ev, IF($I22="Days", ev*IF(dr>0, dr/hr, hpday), IF($I22="FTE", ev*hpw*w, ch))), IF(hrs="", "", hrs*hr)) | T22: {=XLOOKUP(Scenario_Selected, INDEX(Scenario_Table,0,1), INDEX(Scenario_Table,0,2))} | U22: {=XLOOKUP(Scenario_Selected, INDEX(Scenario_Table,0,1), INDEX(Scenario_Table,0,3))} | V22: {=XLOOKUP(Scenario_Selected, INDEX(Scenario_Table,0,1), INDEX(Scenario_Table,0,4))} | W22: {=LET(ev,$J22, ch,$L22, et,$I22, dr,$Q22, hpday,Assumptions!$B$2, hpw,Assumptions!$B$3, w,$M22,hm,INDIRECT("R[0]C[0]",FALSE),hrs, IF(et="Hours", ev, IF(et="Days", ev*IF(dr>0, dr/$P22, hpday), IF(et="FTE", ev*hpw*w, ch))), IF(hrs="", "", hrs*hm))} | X22: =IF($P22="","", $P22*INDIRECT("R[0]C[-3]",FALSE)) | Y22: =IF(INDIRECT("R[0]C[-1]",FALSE)="","", INDIRECT("R[0]C[-2]",FALSE)*INDIRECT("R[0]C[-1]",FALSE)*(1+INDIRECT("R[0]C[-3]",FALSE))) | Z22: Adobe practice today - the content planning aspect is owned by Adobe - the documentation of the guides is driven by Knapsack. Shared Responsibility. Adobe is Accountable for authoring the the guides + FDE is Responsible for review. To be reflected in the RACI
A23: 22 | B23: Advanced Training - Partners + Contribution | C23: {=IFERROR(INDEX(Milestones!$A:$A, MATCH($B23, Milestones!$B:$B, 0)), "")} | D23: {=IFERROR(INDEX(Milestones!$C:$C, MATCH($B23, Milestones!$B:$B, 0)), "")} | E23: Deep-dive enablement for partner contributions | F23: {=IFERROR(INDEX(Milestones!$E:$E, MATCH($B23, Milestones!$B:$B, 0)), "")} | G23: Adobe | H23: {=IFERROR(INDEX(Milestones!$E:$E, MATCH($B23, Milestones!$B:$B, 0)), "")} | I23: FTE | J23: 0.03 | K23: Medium | L23: {=IF($K23="","", IFERROR(IFS($K23="Low", INDEX('Lookups - Complexity'!$C:$C, MATCH($B23, 'Lookups - Complexity'!$B:$B,0)), $K23="Medium", INDEX('Lookups - Complexity'!$D:$D, MATCH($B23, 'Lookups - Complexity'!$B:$B,0)), $K23="High", INDEX('Lookups - Complexity'!$E:$E, MATCH($B23, 'Lookups - Complexity'!$B:$B,0))), ""))} | M23: =IF($I23="FTE", Assumptions!$B$3, "") | N23: {=IFERROR(INDEX(Milestones!$F:$F, MATCH($B23, Milestones!$B:$B, 0)), "")} | O23: {=IFERROR(INDEX(Milestones!$G:$G, MATCH($B23, Milestones!$B:$B, 0)), "")} | P23: {=IFERROR(INDEX('Lookups - Rates'!$D:$D, MATCH($G23&"|"&$H23, 'Lookups - Rates'!$Z:$Z, 0)), "")} | Q23: {=IFERROR(INDEX('Lookups - Rates'!$E:$E, MATCH($G23&"|"&$H23, 'Lookups - Rates'!$Z:$Z, 0)), "")} | R23: =LET(ev,$J23, ch,$L23, hr,$P23, dr,$Q23, hpday,Assumptions!$B$2, hpw,Assumptions!$B$3, w,$M23, hrs, IF($I23="Hours", ev, IF($I23="Days", ev*IF(dr>0, dr/hr, hpday), IF($I23="FTE", ev*hpw*w, ch))), IF(hrs="", "", hrs*hr)) | T23: {=XLOOKUP(Scenario_Selected, INDEX(Scenario_Table,0,1), INDEX(Scenario_Table,0,2))} | U23: {=XLOOKUP(Scenario_Selected, INDEX(Scenario_Table,0,1), INDEX(Scenario_Table,0,3))} | V23: {=XLOOKUP(Scenario_Selected, INDEX(Scenario_Table,0,1), INDEX(Scenario_Table,0,4))} | W23: {=LET(ev,$J23, ch,$L23, et,$I23, dr,$Q23, hpday,Assumptions!$B$2, hpw,Assumptions!$B$3, w,$M23,hm,INDIRECT("R[0]C[0]",FALSE),hrs, IF(et="Hours", ev, IF(et="Days", ev*IF(dr>0, dr/$P23, hpday), IF(et="FTE", ev*hpw*w, ch))), IF(hrs="", "", hrs*hm))} | X23: =IF($P23="","", $P23*INDIRECT("R[0]C[-3]",FALSE)) | Y23: =IF(INDIRECT("R[0]C[-1]",FALSE)="","", INDIRECT("R[0]C[-2]",FALSE)*INDIRECT("R[0]C[-1]",FALSE)*(1+INDIRECT("R[0]C[-3]",FALSE))) | Z23: Knapsack to provide the fodder
A24: 23 | B24: Phase Gate Strategic Recommendations + Documentation | C24: {=IFERROR(INDEX(Milestones!$A:$A, MATCH($B24, Milestones!$B:$B, 0)), "")} | D24: {=IFERROR(INDEX(Milestones!$C:$C, MATCH($B24, Milestones!$B:$B, 0)), "")} | E24: Formal phase gate review and recommendations | F24: {=IFERROR(INDEX(Milestones!$E:$E, MATCH($B24, Milestones!$B:$B, 0)), "")} | G24: Knapsack | H24: {=IFERROR(INDEX(Milestones!$E:$E, MATCH($B24, Milestones!$B:$B, 0)), "")} | I24: FTE | J24: 0.025 | K24: Medium | L24: {=IF($K24="","", IFERROR(IFS($K24="Low", INDEX('Lookups - Complexity'!$C:$C, MATCH($B24, 'Lookups - Complexity'!$B:$B,0)), $K24="Medium", INDEX('Lookups - Complexity'!$D:$D, MATCH($B24, 'Lookups - Complexity'!$B:$B,0)), $K24="High", INDEX('Lookups - Complexity'!$E:$E, MATCH($B24, 'Lookups - Complexity'!$B:$B,0))), ""))} | M24: =IF($I24="FTE", Assumptions!$B$3, "") | N24: {=IFERROR(INDEX(Milestones!$F:$F, MATCH($B24, Milestones!$B:$B, 0)), "")} | O24: {=IFERROR(INDEX(Milestones!$G:$G, MATCH($B24, Milestones!$B:$B, 0)), "")} | P24: {=IFERROR(INDEX('Lookups - Rates'!$D:$D, MATCH($G24&"|"&$H24, 'Lookups - Rates'!$Z:$Z, 0)), "")} | Q24: {=IFERROR(INDEX('Lookups - Rates'!$E:$E, MATCH($G24&"|"&$H24, 'Lookups - Rates'!$Z:$Z, 0)), "")} | R24: =LET(ev,$J24, ch,$L24, hr,$P24, dr,$Q24, hpday,Assumptions!$B$2, hpw,Assumptions!$B$3, w,$M24, hrs, IF($I24="Hours", ev, IF($I24="Days", ev*IF(dr>0, dr/hr, hpday), IF($I24="FTE", ev*hpw*w, ch))), IF(hrs="", "", hrs*hr)) | T24: {=XLOOKUP(Scenario_Selected, INDEX(Scenario_Table,0,1), INDEX(Scenario_Table,0,2))} | U24: {=XLOOKUP(Scenario_Selected, INDEX(Scenario_Table,0,1), INDEX(Scenario_Table,0,3))} | V24: {=XLOOKUP(Scenario_Selected, INDEX(Scenario_Table,0,1), INDEX(Scenario_Table,0,4))} | W24: {=LET(ev,$J24, ch,$L24, et,$I24, dr,$Q24, hpday,Assumptions!$B$2, hpw,Assumptions!$B$3, w,$M24,hm,INDIRECT("R[0]C[0]",FALSE),hrs, IF(et="Hours", ev, IF(et="Days", ev*IF(dr>0, dr/$P24, hpday), IF(et="FTE", ev*hpw*w, ch))), IF(hrs="", "", hrs*hm))} | X24: =IF($P24="","", $P24*INDIRECT("R[0]C[-3]",FALSE)) | Y24: =IF(INDIRECT("R[0]C[-1]",FALSE)="","", INDIRECT("R[0]C[-2]",FALSE)*INDIRECT("R[0]C[-1]",FALSE)*(1+INDIRECT("R[0]C[-3]",FALSE)))
A25: 24 | B25: Pre-Cutover Readiness Review | C25: {=IFERROR(INDEX(Milestones!$A:$A, MATCH($B25, Milestones!$B:$B, 0)), "")} | D25: {=IFERROR(INDEX(Milestones!$C:$C, MATCH($B25, Milestones!$B:$B, 0)), "")} | E25: Validate all technical, operational, and training prerequisites; confirm SSO, component rendering, deployment readiness before final rollout. | F25: {=IFERROR(INDEX(Milestones!$E:$E, MATCH($B25, Milestones!$B:$B, 0)), "")} | G25: Knapsack | H25: {=IFERROR(INDEX(Milestones!$E:$E, MATCH($B25, Milestones!$B:$B, 0)), "")} | I25: FTE | J25: 0.025 | K25: Medium | L25: {=IF($K25="","", IFERROR(IFS($K25="Low", INDEX('Lookups - Complexity'!$C:$C, MATCH($B25, 'Lookups - Complexity'!$B:$B,0)), $K25="Medium", INDEX('Lookups - Complexity'!$D:$D, MATCH($B25, 'Lookups - Complexity'!$B:$B,0)), $K25="High", INDEX('Lookups - Complexity'!$E:$E, MATCH($B25, 'Lookups - Complexity'!$B:$B,0))), ""))} | M25: =IF($I25="FTE", Assumptions!$B$3, "") | N25: {=IFERROR(INDEX(Milestones!$F:$F, MATCH($B25, Milestones!$B:$B, 0)), "")} | O25: {=IFERROR(INDEX(Milestones!$G:$G, MATCH($B25, Milestones!$B:$B, 0)), "")} | P25: {=IFERROR(INDEX('Lookups - Rates'!$D:$D, MATCH($G25&"|"&$H25, 'Lookups - Rates'!$Z:$Z, 0)), "")} | Q25: {=IFERROR(INDEX('Lookups - Rates'!$E:$E, MATCH($G25&"|"&$H25, 'Lookups - Rates'!$Z:$Z, 0)), "")} | R25: =LET(ev,$J25, ch,$L25, hr,$P25, dr,$Q25, hpday,Assumptions!$B$2, hpw,Assumptions!$B$3, w,$M25, hrs, IF($I25="Hours", ev, IF($I25="Days", ev*IF(dr>0, dr/hr, hpday), IF($I25="FTE", ev*hpw*w, ch))), IF(hrs="", "", hrs*hr)) | T25: {=XLOOKUP(Scenario_Selected, INDEX(Scenario_Table,0,1), INDEX(Scenario_Table,0,2))} | U25: {=XLOOKUP(Scenario_Selected, INDEX(Scenario_Table,0,1), INDEX(Scenario_Table,0,3))} | V25: {=XLOOKUP(Scenario_Selected, INDEX(Scenario_Table,0,1), INDEX(Scenario_Table,0,4))} | W25: {=LET(ev,$J25, ch,$L25, et,$I25, dr,$Q25, hpday,Assumptions!$B$2, hpw,Assumptions!$B$3, w,$M25,hm,INDIRECT("R[0]C[0]",FALSE),hrs, IF(et="Hours", ev, IF(et="Days", ev*IF(dr>0, dr/$P25, hpday), IF(et="FTE", ev*hpw*w, ch))), IF(hrs="", "", hrs*hm))} | X25: =IF($P25="","", $P25*INDIRECT("R[0]C[-3]",FALSE)) | Y25: =IF(INDIRECT("R[0]C[-1]",FALSE)="","", INDIRECT("R[0]C[-2]",FALSE)*INDIRECT("R[0]C[-1]",FALSE)*(1+INDIRECT("R[0]C[-3]",FALSE)))
A26: 25 | B26: Data & Configuration Freeze | C26: {=IFERROR(INDEX(Milestones!$A:$A, MATCH($B26, Milestones!$B:$B, 0)), "")} | D26: {=IFERROR(INDEX(Milestones!$C:$C, MATCH($B26, Milestones!$B:$B, 0)), "")} | E26: Lock configuration and repositories; capture environment snapshot for rollback if needed before go-live. | F26: {=IFERROR(INDEX(Milestones!$E:$E, MATCH($B26, Milestones!$B:$B, 0)), "")} | G26: Knapsack | H26: {=IFERROR(INDEX(Milestones!$E:$E, MATCH($B26, Milestones!$B:$B, 0)), "")} | I26: FTE | J26: 0.025 | K26: Medium | L26: {=IF($K26="","", IFERROR(IFS($K26="Low", INDEX('Lookups - Complexity'!$C:$C, MATCH($B26, 'Lookups - Complexity'!$B:$B,0)), $K26="Medium", INDEX('Lookups - Complexity'!$D:$D, MATCH($B26, 'Lookups - Complexity'!$B:$B,0)), $K26="High", INDEX('Lookups - Complexity'!$E:$E, MATCH($B26, 'Lookups - Complexity'!$B:$B,0))), ""))} | M26: =IF($I26="FTE", Assumptions!$B$3, "") | N26: {=IFERROR(INDEX(Milestones!$F:$F, MATCH($B26, Milestones!$B:$B, 0)), "")} | O26: {=IFERROR(INDEX(Milestones!$G:$G, MATCH($B26, Milestones!$B:$B, 0)), "")} | P26: {=IFERROR(INDEX('Lookups - Rates'!$D:$D, MATCH($G26&"|"&$H26, 'Lookups - Rates'!$Z:$Z, 0)), "")} | Q26: {=IFERROR(INDEX('Lookups - Rates'!$E:$E, MATCH($G26&"|"&$H26, 'Lookups - Rates'!$Z:$Z, 0)), "")} | R26: =LET(ev,$J26, ch,$L26, hr,$P26, dr,$Q26, hpday,Assumptions!$B$2, hpw,Assumptions!$B$3, w,$M26, hrs, IF($I26="Hours", ev, IF($I26="Days", ev*IF(dr>0, dr/hr, hpday), IF($I26="FTE", ev*hpw*w, ch))), IF(hrs="", "", hrs*hr)) | T26: {=XLOOKUP(Scenario_Selected, INDEX(Scenario_Table,0,1), INDEX(Scenario_Table,0,2))} | U26: {=XLOOKUP(Scenario_Selected, INDEX(Scenario_Table,0,1), INDEX(Scenario_Table,0,3))} | V26: {=XLOOKUP(Scenario_Selected, INDEX(Scenario_Table,0,1), INDEX(Scenario_Table,0,4))} | W26: {=LET(ev,$J26, ch,$L26, et,$I26, dr,$Q26, hpday,Assumptions!$B$2, hpw,Assumptions!$B$3, w,$M26,hm,INDIRECT("R[0]C[0]",FALSE),hrs, IF(et="Hours", ev, IF(et="Days", ev*IF(dr>0, dr/$P26, hpday), IF(et="FTE", ev*hpw*w, ch))), IF(hrs="", "", hrs*hm))} | X26: =IF($P26="","", $P26*INDIRECT("R[0]C[-3]",FALSE)) | Y26: =IF(INDIRECT("R[0]C[-1]",FALSE)="","", INDIRECT("R[0]C[-2]",FALSE)*INDIRECT("R[0]C[-1]",FALSE)*(1+INDIRECT("R[0]C[-3]",FALSE)))
A27: 26 | B27: Final UAT & Stakeholder Acceptance | C27: {=IFERROR(INDEX(Milestones!$A:$A, MATCH($B27, Milestones!$B:$B, 0)), "")} | D27: {=IFERROR(INDEX(Milestones!$C:$C, MATCH($B27, Milestones!$B:$B, 0)), "")} | E27: Conduct final user acceptance testing with pilot teams; log and triage known issues before launch. | F27: {=IFERROR(INDEX(Milestones!$E:$E, MATCH($B27, Milestones!$B:$B, 0)), "")} | G27: Knapsack | H27: {=IFERROR(INDEX(Milestones!$E:$E, MATCH($B27, Milestones!$B:$B, 0)), "")} | I27: FTE | J27: 0.025 | K27: Medium | L27: {=IF($K27="","", IFERROR(IFS($K27="Low", INDEX('Lookups - Complexity'!$C:$C, MATCH($B27, 'Lookups - Complexity'!$B:$B,0)), $K27="Medium", INDEX('Lookups - Complexity'!$D:$D, MATCH($B27, 'Lookups - Complexity'!$B:$B,0)), $K27="High", INDEX('Lookups - Complexity'!$E:$E, MATCH($B27, 'Lookups - Complexity'!$B:$B,0))), ""))} | M27: =IF($I27="FTE", Assumptions!$B$3, "") | N27: {=IFERROR(INDEX(Milestones!$F:$F, MATCH($B27, Milestones!$B:$B, 0)), "")} | O27: {=IFERROR(INDEX(Milestones!$G:$G, MATCH($B27, Milestones!$B:$B, 0)), "")} | P27: {=IFERROR(INDEX('Lookups - Rates'!$D:$D, MATCH($G27&"|"&$H27, 'Lookups - Rates'!$Z:$Z, 0)), "")} | Q27: {=IFERROR(INDEX('Lookups - Rates'!$E:$E, MATCH($G27&"|"&$H27, 'Lookups - Rates'!$Z:$Z, 0)), "")} | R27: =LET(ev,$J27, ch,$L27, hr,$P27, dr,$Q27, hpday,Assumptions!$B$2, hpw,Assumptions!$B$3, w,$M27, hrs, IF($I27="Hours", ev, IF($I27="Days", ev*IF(dr>0, dr/hr, hpday), IF($I27="FTE", ev*hpw*w, ch))), IF(hrs="", "", hrs*hr)) | T27: {=XLOOKUP(Scenario_Selected, INDEX(Scenario_Table,0,1), INDEX(Scenario_Table,0,2))} | U27: {=XLOOKUP(Scenario_Selected, INDEX(Scenario_Table,0,1), INDEX(Scenario_Table,0,3))} | V27: {=XLOOKUP(Scenario_Selected, INDEX(Scenario_Table,0,1), INDEX(Scenario_Table,0,4))} | W27: {=LET(ev,$J27, ch,$L27, et,$I27, dr,$Q27, hpday,Assumptions!$B$2, hpw,Assumptions!$B$3, w,$M27,hm,INDIRECT("R[0]C[0]",FALSE),hrs, IF(et="Hours", ev, IF(et="Days", ev*IF(dr>0, dr/$P27, hpday), IF(et="FTE", ev*hpw*w, ch))), IF(hrs="", "", hrs*hm))} | X27: =IF($P27="","", $P27*INDIRECT("R[0]C[-3]",FALSE)) | Y27: =IF(INDIRECT("R[0]C[-1]",FALSE)="","", INDIRECT("R[0]C[-2]",FALSE)*INDIRECT("R[0]C[-1]",FALSE)*(1+INDIRECT("R[0]C[-3]",FALSE))) | Z27: Shared Responsibility. Adobe is Accountable for authoring the test scripts, identifying the UAT participants, and ensuring that timelines are kept, and Knapsack FDE is Responsible to ensure that bug/fixes are prioritized and addresssed.
A28: 27 | B28: Change Impact Analysis | C28: {=IFERROR(INDEX(Milestones!$A:$A, MATCH($B28, Milestones!$B:$B, 0)), "")} | D28: {=IFERROR(INDEX(Milestones!$C:$C, MATCH($B28, Milestones!$B:$B, 0)), "")} | E28: Evaluate and manage business unit impacts during scale-up. | F28: {=IFERROR(INDEX(Milestones!$E:$E, MATCH($B28, Milestones!$B:$B, 0)), "")} | G28: Knapsack | H28: {=IFERROR(INDEX(Milestones!$E:$E, MATCH($B28, Milestones!$B:$B, 0)), "")} | I28: FTE | J28: 0.05 | K28: High | L28: {=IF($K28="","", IFERROR(IFS($K28="Low", INDEX('Lookups - Complexity'!$C:$C, MATCH($B28, 'Lookups - Complexity'!$B:$B,0)), $K28="Medium", INDEX('Lookups - Complexity'!$D:$D, MATCH($B28, 'Lookups - Complexity'!$B:$B,0)), $K28="High", INDEX('Lookups - Complexity'!$E:$E, MATCH($B28, 'Lookups - Complexity'!$B:$B,0))), ""))} | M28: =IF($I28="FTE", Assumptions!$B$3, "") | N28: {=IFERROR(INDEX(Milestones!$F:$F, MATCH($B28, Milestones!$B:$B, 0)), "")} | O28: {=IFERROR(INDEX(Milestones!$G:$G, MATCH($B28, Milestones!$B:$B, 0)), "")} | P28: {=IFERROR(INDEX('Lookups - Rates'!$D:$D, MATCH($G28&"|"&$H28, 'Lookups - Rates'!$Z:$Z, 0)), "")} | Q28: {=IFERROR(INDEX('Lookups - Rates'!$E:$E, MATCH($G28&"|"&$H28, 'Lookups - Rates'!$Z:$Z, 0)), "")} | R28: =LET(ev,$J28, ch,$L28, hr,$P28, dr,$Q28, hpday,Assumptions!$B$2, hpw,Assumptions!$B$3, w,$M28, hrs, IF($I28="Hours", ev, IF($I28="Days", ev*IF(dr>0, dr/hr, hpday), IF($I28="FTE", ev*hpw*w, ch))), IF(hrs="", "", hrs*hr)) | T28: {=XLOOKUP(Scenario_Selected, INDEX(Scenario_Table,0,1), INDEX(Scenario_Table,0,2))} | U28: {=XLOOKUP(Scenario_Selected, INDEX(Scenario_Table,0,1), INDEX(Scenario_Table,0,3))} | V28: {=XLOOKUP(Scenario_Selected, INDEX(Scenario_Table,0,1), INDEX(Scenario_Table,0,4))} | W28: {=LET(ev,$J28, ch,$L28, et,$I28, dr,$Q28, hpday,Assumptions!$B$2, hpw,Assumptions!$B$3, w,$M28,hm,INDIRECT("R[0]C[0]",FALSE),hrs, IF(et="Hours", ev, IF(et="Days", ev*IF(dr>0, dr/$P28, hpday), IF(et="FTE", ev*hpw*w, ch))), IF(hrs="", "", hrs*hm))} | X28: =IF($P28="","", $P28*INDIRECT("R[0]C[-3]",FALSE)) | Y28: =IF(INDIRECT("R[0]C[-1]",FALSE)="","", INDIRECT("R[0]C[-2]",FALSE)*INDIRECT("R[0]C[-1]",FALSE)*(1+INDIRECT("R[0]C[-3]",FALSE))) | Z28: Knapsack CX Partner will sit on the Steering Committee to provide coaching for all Activities that Adobe is ACCOUNTABLE for (Column G) where KS Roles are typically in delivery (Column H) to be reflected in the Steering Committe/Governance Model + RACI
A29: 28 | B29: Adoption Acceleration Campaign | C29: {=IFERROR(INDEX(Milestones!$A:$A, MATCH($B29, Milestones!$B:$B, 0)), "")} | D29: {=IFERROR(INDEX(Milestones!$C:$C, MATCH($B29, Milestones!$B:$B, 0)), "")} | E29: Promote awareness and highlight early success stories to drive adoption. | F29: {=IFERROR(INDEX(Milestones!$E:$E, MATCH($B29, Milestones!$B:$B, 0)), "")} | G29: Adobe | H29: Adobe | I29: FTE | J29: 0.05 | K29: High | L29: {=IF($K29="","", IFERROR(IFS($K29="Low", INDEX('Lookups - Complexity'!$C:$C, MATCH($B29, 'Lookups - Complexity'!$B:$B,0)), $K29="Medium", INDEX('Lookups - Complexity'!$D:$D, MATCH($B29, 'Lookups - Complexity'!$B:$B,0)), $K29="High", INDEX('Lookups - Complexity'!$E:$E, MATCH($B29, 'Lookups - Complexity'!$B:$B,0))), ""))} | M29: =IF($I29="FTE", Assumptions!$B$3, "") | N29: {=IFERROR(INDEX(Milestones!$F:$F, MATCH($B29, Milestones!$B:$B, 0)), "")} | O29: {=IFERROR(INDEX(Milestones!$G:$G, MATCH($B29, Milestones!$B:$B, 0)), "")} | P29: {=IFERROR(INDEX('Lookups - Rates'!$D:$D, MATCH($G29&"|"&$H29, 'Lookups - Rates'!$Z:$Z, 0)), "")} | Q29: {=IFERROR(INDEX('Lookups - Rates'!$E:$E, MATCH($G29&"|"&$H29, 'Lookups - Rates'!$Z:$Z, 0)), "")} | R29: =LET(ev,$J29, ch,$L29, hr,$P29, dr,$Q29, hpday,Assumptions!$B$2, hpw,Assumptions!$B$3, w,$M29, hrs, IF($I29="Hours", ev, IF($I29="Days", ev*IF(dr>0, dr/hr, hpday), IF($I29="FTE", ev*hpw*w, ch))), IF(hrs="", "", hrs*hr)) | T29: {=XLOOKUP(Scenario_Selected, INDEX(Scenario_Table,0,1), INDEX(Scenario_Table,0,2))} | U29: {=XLOOKUP(Scenario_Selected, INDEX(Scenario_Table,0,1), INDEX(Scenario_Table,0,3))} | V29: {=XLOOKUP(Scenario_Selected, INDEX(Scenario_Table,0,1), INDEX(Scenario_Table,0,4))} | W29: {=LET(ev,$J29, ch,$L29, et,$I29, dr,$Q29, hpday,Assumptions!$B$2, hpw,Assumptions!$B$3, w,$M29,hm,INDIRECT("R[0]C[0]",FALSE),hrs, IF(et="Hours", ev, IF(et="Days", ev*IF(dr>0, dr/$P29, hpday), IF(et="FTE", ev*hpw*w, ch))), IF(hrs="", "", hrs*hm))} | X29: =IF($P29="","", $P29*INDIRECT("R[0]C[-3]",FALSE)) | Y29: =IF(INDIRECT("R[0]C[-1]",FALSE)="","", INDIRECT("R[0]C[-2]",FALSE)*INDIRECT("R[0]C[-1]",FALSE)*(1+INDIRECT("R[0]C[-3]",FALSE)))
A30: 29 | B30: Partner Enablement & Recognition | C30: {=IFERROR(INDEX(Milestones!$A:$A, MATCH($B30, Milestones!$B:$B, 0)), "")} | D30: {=IFERROR(INDEX(Milestones!$C:$C, MATCH($B30, Milestones!$B:$B, 0)), "")} | E30: Drive engagement through recognition and contribution metrics. | F30: {=IFERROR(INDEX(Milestones!$E:$E, MATCH($B30, Milestones!$B:$B, 0)), "")} | G30: Adobe | H30: Adobe | I30: FTE | J30: 0.05 | K30: High | L30: {=IF($K30="","", IFERROR(IFS($K30="Low", INDEX('Lookups - Complexity'!$C:$C, MATCH($B30, 'Lookups - Complexity'!$B:$B,0)), $K30="Medium", INDEX('Lookups - Complexity'!$D:$D, MATCH($B30, 'Lookups - Complexity'!$B:$B,0)), $K30="High", INDEX('Lookups - Complexity'!$E:$E, MATCH($B30, 'Lookups - Complexity'!$B:$B,0))), ""))} | M30: =IF($I30="FTE", Assumptions!$B$3, "") | N30: {=IFERROR(INDEX(Milestones!$F:$F, MATCH($B30, Milestones!$B:$B, 0)), "")} | O30: {=IFERROR(INDEX(Milestones!$G:$G, MATCH($B30, Milestones!$B:$B, 0)), "")} | P30: {=IFERROR(INDEX('Lookups - Rates'!$D:$D, MATCH($G30&"|"&$H30, 'Lookups - Rates'!$Z:$Z, 0)), "")} | Q30: {=IFERROR(INDEX('Lookups - Rates'!$E:$E, MATCH($G30&"|"&$H30, 'Lookups - Rates'!$Z:$Z, 0)), "")} | R30: =LET(ev,$J30, ch,$L30, hr,$P30, dr,$Q30, hpday,Assumptions!$B$2, hpw,Assumptions!$B$3, w,$M30, hrs, IF($I30="Hours", ev, IF($I30="Days", ev*IF(dr>0, dr/hr, hpday), IF($I30="FTE", ev*hpw*w, ch))), IF(hrs="", "", hrs*hr)) | T30: {=XLOOKUP(Scenario_Selected, INDEX(Scenario_Table,0,1), INDEX(Scenario_Table,0,2))} | U30: {=XLOOKUP(Scenario_Selected, INDEX(Scenario_Table,0,1), INDEX(Scenario_Table,0,3))} | V30: {=XLOOKUP(Scenario_Selected, INDEX(Scenario_Table,0,1), INDEX(Scenario_Table,0,4))} | W30: {=LET(ev,$J30, ch,$L30, et,$I30, dr,$Q30, hpday,Assumptions!$B$2, hpw,Assumptions!$B$3, w,$M30,hm,INDIRECT("R[0]C[0]",FALSE),hrs, IF(et="Hours", ev, IF(et="Days", ev*IF(dr>0, dr/$P30, hpday), IF(et="FTE", ev*hpw*w, ch))), IF(hrs="", "", hrs*hm))} | X30: =IF($P30="","", $P30*INDIRECT("R[0]C[-3]",FALSE)) | Y30: =IF(INDIRECT("R[0]C[-1]",FALSE)="","", INDIRECT("R[0]C[-2]",FALSE)*INDIRECT("R[0]C[-1]",FALSE)*(1+INDIRECT("R[0]C[-3]",FALSE)))
A31: 30 | B31: Transition support | C31: {=IFERROR(INDEX(Milestones!$A:$A, MATCH($B31, Milestones!$B:$B, 0)), "")} | D31: {=IFERROR(INDEX(Milestones!$C:$C, MATCH($B31, Milestones!$B:$B, 0)), "")} | E31: Continuous improvement plan with analytics and recommendations | F31: {=IFERROR(INDEX(Milestones!$E:$E, MATCH($B31, Milestones!$B:$B, 0)), "")} | G31: Knapsack | H31: {=IFERROR(INDEX(Milestones!$E:$E, MATCH($B31, Milestones!$B:$B, 0)), "")} | I31: FTE | J31: 0.025 | K31: Low | L31: {=IF($K31="","", IFERROR(IFS($K31="Low", INDEX('Lookups - Complexity'!$C:$C, MATCH($B31, 'Lookups - Complexity'!$B:$B,0)), $K31="Medium", INDEX('Lookups - Complexity'!$D:$D, MATCH($B31, 'Lookups - Complexity'!$B:$B,0)), $K31="High", INDEX('Lookups - Complexity'!$E:$E, MATCH($B31, 'Lookups - Complexity'!$B:$B,0))), ""))} | M31: =IF($I31="FTE", Assumptions!$B$3, "") | N31: {=IFERROR(INDEX(Milestones!$F:$F, MATCH($B31, Milestones!$B:$B, 0)), "")} | O31: {=IFERROR(INDEX(Milestones!$G:$G, MATCH($B31, Milestones!$B:$B, 0)), "")} | P31: {=IFERROR(INDEX('Lookups - Rates'!$D:$D, MATCH($G31&"|"&$H31, 'Lookups - Rates'!$Z:$Z, 0)), "")} | Q31: {=IFERROR(INDEX('Lookups - Rates'!$E:$E, MATCH($G31&"|"&$H31, 'Lookups - Rates'!$Z:$Z, 0)), "")} | R31: =LET(ev,$J31, ch,$L31, hr,$P31, dr,$Q31, hpday,Assumptions!$B$2, hpw,Assumptions!$B$3, w,$M31, hrs, IF($I31="Hours", ev, IF($I31="Days", ev*IF(dr>0, dr/hr, hpday), IF($I31="FTE", ev*hpw*w, ch))), IF(hrs="", "", hrs*hr)) | T31: {=XLOOKUP(Scenario_Selected, INDEX(Scenario_Table,0,1), INDEX(Scenario_Table,0,2))} | U31: {=XLOOKUP(Scenario_Selected, INDEX(Scenario_Table,0,1), INDEX(Scenario_Table,0,3))} | V31: {=XLOOKUP(Scenario_Selected, INDEX(Scenario_Table,0,1), INDEX(Scenario_Table,0,4))} | W31: {=LET(ev,$J31, ch,$L31, et,$I31, dr,$Q31, hpday,Assumptions!$B$2, hpw,Assumptions!$B$3, w,$M31,hm,INDIRECT("R[0]C[0]",FALSE),hrs, IF(et="Hours", ev, IF(et="Days", ev*IF(dr>0, dr/$P31, hpday), IF(et="FTE", ev*hpw*w, ch))), IF(hrs="", "", hrs*hm))} | X31: =IF($P31="","", $P31*INDIRECT("R[0]C[-3]",FALSE)) | Y31: =IF(INDIRECT("R[0]C[-1]",FALSE)="","", INDIRECT("R[0]C[-2]",FALSE)*INDIRECT("R[0]C[-1]",FALSE)*(1+INDIRECT("R[0]C[-3]",FALSE)))
A32: 31 | B32: Cutover Execution | C32: {=IFERROR(INDEX(Milestones!$A:$A, MATCH($B32, Milestones!$B:$B, 0)), "")} | D32: {=IFERROR(INDEX(Milestones!$C:$C, MATCH($B32, Milestones!$B:$B, 0)), "")} | E32: Execute production deployment; validate access controls, deployment integrity, and service health. | F32: {=IFERROR(INDEX(Milestones!$E:$E, MATCH($B32, Milestones!$B:$B, 0)), "")} | G32: Knapsack | H32: {=IFERROR(INDEX(Milestones!$E:$E, MATCH($B32, Milestones!$B:$B, 0)), "")} | I32: FTE | J32: 0.05 | K32: Low | L32: {=IF($K32="","", IFERROR(IFS($K32="Low", INDEX('Lookups - Complexity'!$C:$C, MATCH($B32, 'Lookups - Complexity'!$B:$B,0)), $K32="Medium", INDEX('Lookups - Complexity'!$D:$D, MATCH($B32, 'Lookups - Complexity'!$B:$B,0)), $K32="High", INDEX('Lookups - Complexity'!$E:$E, MATCH($B32, 'Lookups - Complexity'!$B:$B,0))), ""))} | M32: =IF($I32="FTE", Assumptions!$B$3, "") | N32: {=IFERROR(INDEX(Milestones!$F:$F, MATCH($B32, Milestones!$B:$B, 0)), "")} | O32: {=IFERROR(INDEX(Milestones!$G:$G, MATCH($B32, Milestones!$B:$B, 0)), "")} | P32: {=IFERROR(INDEX('Lookups - Rates'!$D:$D, MATCH($G32&"|"&$H32, 'Lookups - Rates'!$Z:$Z, 0)), "")} | Q32: {=IFERROR(INDEX('Lookups - Rates'!$E:$E, MATCH($G32&"|"&$H32, 'Lookups - Rates'!$Z:$Z, 0)), "")} | R32: =LET(ev,$J32, ch,$L32, hr,$P32, dr,$Q32, hpday,Assumptions!$B$2, hpw,Assumptions!$B$3, w,$M32, hrs, IF($I32="Hours", ev, IF($I32="Days", ev*IF(dr>0, dr/hr, hpday), IF($I32="FTE", ev*hpw*w, ch))), IF(hrs="", "", hrs*hr)) | T32: {=XLOOKUP(Scenario_Selected, INDEX(Scenario_Table,0,1), INDEX(Scenario_Table,0,2))} | U32: {=XLOOKUP(Scenario_Selected, INDEX(Scenario_Table,0,1), INDEX(Scenario_Table,0,3))} | V32: {=XLOOKUP(Scenario_Selected, INDEX(Scenario_Table,0,1), INDEX(Scenario_Table,0,4))} | W32: {=LET(ev,$J32, ch,$L32, et,$I32, dr,$Q32, hpday,Assumptions!$B$2, hpw,Assumptions!$B$3, w,$M32,hm,INDIRECT("R[0]C[0]",FALSE),hrs, IF(et="Hours", ev, IF(et="Days", ev*IF(dr>0, dr/$P32, hpday), IF(et="FTE", ev*hpw*w, ch))), IF(hrs="", "", hrs*hm))} | X32: =IF($P32="","", $P32*INDIRECT("R[0]C[-3]",FALSE)) | Y32: =IF(INDIRECT("R[0]C[-1]",FALSE)="","", INDIRECT("R[0]C[-2]",FALSE)*INDIRECT("R[0]C[-1]",FALSE)*(1+INDIRECT("R[0]C[-3]",FALSE)))
A33: 32 | B33: Go-Live Communication Launch | C33: {=IFERROR(INDEX(Milestones!$A:$A, MATCH($B33, Milestones!$B:$B, 0)), "")} | D33: {=IFERROR(INDEX(Milestones!$C:$C, MATCH($B33, Milestones!$B:$B, 0)), "")} | E33: Announce official go-live to stakeholders; provide communication templates and support channels. | F33: {=IFERROR(INDEX(Milestones!$E:$E, MATCH($B33, Milestones!$B:$B, 0)), "")} | G33: Adobe | H33: {=IFERROR(INDEX(Milestones!$E:$E, MATCH($B33, Milestones!$B:$B, 0)), "")} | I33: FTE | J33: 0.03 | K33: Medium | L33: {=IF($K33="","", IFERROR(IFS($K33="Low", INDEX('Lookups - Complexity'!$C:$C, MATCH($B33, 'Lookups - Complexity'!$B:$B,0)), $K33="Medium", INDEX('Lookups - Complexity'!$D:$D, MATCH($B33, 'Lookups - Complexity'!$B:$B,0)), $K33="High", INDEX('Lookups - Complexity'!$E:$E, MATCH($B33, 'Lookups - Complexity'!$B:$B,0))), ""))} | M33: =IF($I33="FTE", Assumptions!$B$3, "") | N33: {=IFERROR(INDEX(Milestones!$F:$F, MATCH($B33, Milestones!$B:$B, 0)), "")} | O33: {=IFERROR(INDEX(Milestones!$G:$G, MATCH($B33, Milestones!$B:$B, 0)), "")} | P33: {=IFERROR(INDEX('Lookups - Rates'!$D:$D, MATCH($G33&"|"&$H33, 'Lookups - Rates'!$Z:$Z, 0)), "")} | Q33: {=IFERROR(INDEX('Lookups - Rates'!$E:$E, MATCH($G33&"|"&$H33, 'Lookups - Rates'!$Z:$Z, 0)), "")} | R33: =LET(ev,$J33, ch,$L33, hr,$P33, dr,$Q33, hpday,Assumptions!$B$2, hpw,Assumptions!$B$3, w,$M33, hrs, IF($I33="Hours", ev, IF($I33="Days", ev*IF(dr>0, dr/hr, hpday), IF($I33="FTE", ev*hpw*w, ch))), IF(hrs="", "", hrs*hr)) | T33: {=XLOOKUP(Scenario_Selected, INDEX(Scenario_Table,0,1), INDEX(Scenario_Table,0,2))} | U33: {=XLOOKUP(Scenario_Selected, INDEX(Scenario_Table,0,1), INDEX(Scenario_Table,0,3))} | V33: {=XLOOKUP(Scenario_Selected, INDEX(Scenario_Table,0,1), INDEX(Scenario_Table,0,4))} | W33: {=LET(ev,$J33, ch,$L33, et,$I33, dr,$Q33, hpday,Assumptions!$B$2, hpw,Assumptions!$B$3, w,$M33,hm,INDIRECT("R[0]C[0]",FALSE),hrs, IF(et="Hours", ev, IF(et="Days", ev*IF(dr>0, dr/$P33, hpday), IF(et="FTE", ev*hpw*w, ch))), IF(hrs="", "", hrs*hm))} | X33: =IF($P33="","", $P33*INDIRECT("R[0]C[-3]",FALSE)) | Y33: =IF(INDIRECT("R[0]C[-1]",FALSE)="","", INDIRECT("R[0]C[-2]",FALSE)*INDIRECT("R[0]C[-1]",FALSE)*(1+INDIRECT("R[0]C[-3]",FALSE)))
A34: 33 | B34: Hypercare Phase (Post-Go-Live Support) | C34: {=IFERROR(INDEX(Milestones!$A:$A, MATCH($B34, Milestones!$B:$B, 0)), "")} | D34: {=IFERROR(INDEX(Milestones!$C:$C, MATCH($B34, Milestones!$B:$B, 0)), "")} | E34: Provide high-touch support for 30–90 days post go-live, track SLAs, and stabilize the system. | F34: {=IFERROR(INDEX(Milestones!$E:$E, MATCH($B34, Milestones!$B:$B, 0)), "")} | G34: Knapsack | H34: {=IFERROR(INDEX(Milestones!$E:$E, MATCH($B34, Milestones!$B:$B, 0)), "")} | I34: FTE | J34: 0.03 | K34: Medium | L34: {=IF($K34="","", IFERROR(IFS($K34="Low", INDEX('Lookups - Complexity'!$C:$C, MATCH($B34, 'Lookups - Complexity'!$B:$B,0)), $K34="Medium", INDEX('Lookups - Complexity'!$D:$D, MATCH($B34, 'Lookups - Complexity'!$B:$B,0)), $K34="High", INDEX('Lookups - Complexity'!$E:$E, MATCH($B34, 'Lookups - Complexity'!$B:$B,0))), ""))} | M34: =IF($I34="FTE", Assumptions!$B$3, "") | N34: {=IFERROR(INDEX(Milestones!$F:$F, MATCH($B34, Milestones!$B:$B, 0)), "")} | O34: {=IFERROR(INDEX(Milestones!$G:$G, MATCH($B34, Milestones!$B:$B, 0)), "")} | P34: {=IFERROR(INDEX('Lookups - Rates'!$D:$D, MATCH($G34&"|"&$H34, 'Lookups - Rates'!$Z:$Z, 0)), "")} | Q34: {=IFERROR(INDEX('Lookups - Rates'!$E:$E, MATCH($G34&"|"&$H34, 'Lookups - Rates'!$Z:$Z, 0)), "")} | R34: =LET(ev,$J34, ch,$L34, hr,$P34, dr,$Q34, hpday,Assumptions!$B$2, hpw,Assumptions!$B$3, w,$M34, hrs, IF($I34="Hours", ev, IF($I34="Days", ev*IF(dr>0, dr/hr, hpday), IF($I34="FTE", ev*hpw*w, ch))), IF(hrs="", "", hrs*hr)) | T34: {=XLOOKUP(Scenario_Selected, INDEX(Scenario_Table,0,1), INDEX(Scenario_Table,0,2))} | U34: {=XLOOKUP(Scenario_Selected, INDEX(Scenario_Table,0,1), INDEX(Scenario_Table,0,3))} | V34: {=XLOOKUP(Scenario_Selected, INDEX(Scenario_Table,0,1), INDEX(Scenario_Table,0,4))} | W34: {=LET(ev,$J34, ch,$L34, et,$I34, dr,$Q34, hpday,Assumptions!$B$2, hpw,Assumptions!$B$3, w,$M34,hm,INDIRECT("R[0]C[0]",FALSE),hrs, IF(et="Hours", ev, IF(et="Days", ev*IF(dr>0, dr/$P34, hpday), IF(et="FTE", ev*hpw*w, ch))), IF(hrs="", "", hrs*hm))} | X34: =IF($P34="","", $P34*INDIRECT("R[0]C[-3]",FALSE)) | Y34: =IF(INDIRECT("R[0]C[-1]",FALSE)="","", INDIRECT("R[0]C[-2]",FALSE)*INDIRECT("R[0]C[-1]",FALSE)*(1+INDIRECT("R[0]C[-3]",FALSE)))
A35: 34 | B35: Post-Implementation Review | C35: {=IFERROR(INDEX(Milestones!$A:$A, MATCH($B35, Milestones!$B:$B, 0)), "")} | D35: {=IFERROR(INDEX(Milestones!$C:$C, MATCH($B35, Milestones!$B:$B, 0)), "")} | E35: Evaluate performance, adoption, and partner satisfaction to inform optimization roadmap. | F35: {=IFERROR(INDEX(Milestones!$E:$E, MATCH($B35, Milestones!$B:$B, 0)), "")} | G35: Adobe | H35: {=IFERROR(INDEX(Milestones!$E:$E, MATCH($B35, Milestones!$B:$B, 0)), "")} | I35: FTE | J35: 0.03 | K35: Medium | L35: {=IF($K35="","", IFERROR(IFS($K35="Low", INDEX('Lookups - Complexity'!$C:$C, MATCH($B35, 'Lookups - Complexity'!$B:$B,0)), $K35="Medium", INDEX('Lookups - Complexity'!$D:$D, MATCH($B35, 'Lookups - Complexity'!$B:$B,0)), $K35="High", INDEX('Lookups - Complexity'!$E:$E, MATCH($B35, 'Lookups - Complexity'!$B:$B,0))), ""))} | M35: =IF($I35="FTE", Assumptions!$B$3, "") | N35: {=IFERROR(INDEX(Milestones!$F:$F, MATCH($B35, Milestones!$B:$B, 0)), "")} | O35: {=IFERROR(INDEX(Milestones!$G:$G, MATCH($B35, Milestones!$B:$B, 0)), "")} | P35: {=IFERROR(INDEX('Lookups - Rates'!$D:$D, MATCH($G35&"|"&$H35, 'Lookups - Rates'!$Z:$Z, 0)), "")} | Q35: {=IFERROR(INDEX('Lookups - Rates'!$E:$E, MATCH($G35&"|"&$H35, 'Lookups - Rates'!$Z:$Z, 0)), "")} | R35: =LET(ev,$J35, ch,$L35, hr,$P35, dr,$Q35, hpday,Assumptions!$B$2, hpw,Assumptions!$B$3, w,$M35, hrs, IF($I35="Hours", ev, IF($I35="Days", ev*IF(dr>0, dr/hr, hpday), IF($I35="FTE", ev*hpw*w, ch))), IF(hrs="", "", hrs*hr)) | T35: {=XLOOKUP(Scenario_Selected, INDEX(Scenario_Table,0,1), INDEX(Scenario_Table,0,2))} | U35: {=XLOOKUP(Scenario_Selected, INDEX(Scenario_Table,0,1), INDEX(Scenario_Table,0,3))} | V35: {=XLOOKUP(Scenario_Selected, INDEX(Scenario_Table,0,1), INDEX(Scenario_Table,0,4))} | W35: {=LET(ev,$J35, ch,$L35, et,$I35, dr,$Q35, hpday,Assumptions!$B$2, hpw,Assumptions!$B$3, w,$M35,hm,INDIRECT("R[0]C[0]",FALSE),hrs, IF(et="Hours", ev, IF(et="Days", ev*IF(dr>0, dr/$P35, hpday), IF(et="FTE", ev*hpw*w, ch))), IF(hrs="", "", hrs*hm))} | X35: =IF($P35="","", $P35*INDIRECT("R[0]C[-3]",FALSE)) | Y35: =IF(INDIRECT("R[0]C[-1]",FALSE)="","", INDIRECT("R[0]C[-2]",FALSE)*INDIRECT("R[0]C[-1]",FALSE)*(1+INDIRECT("R[0]C[-3]",FALSE)))
A36: 35 | B36: Transition to Steady-State Operations | C36: {=IFERROR(INDEX(Milestones!$A:$A, MATCH($B36, Milestones!$B:$B, 0)), "")} | D36: {=IFERROR(INDEX(Milestones!$C:$C, MATCH($B36, Milestones!$B:$B, 0)), "")} | E36: Transition ownership to internal design ops and engineering teams; confirm governance cadence. | F36: {=IFERROR(INDEX(Milestones!$E:$E, MATCH($B36, Milestones!$B:$B, 0)), "")} | G36: Adobe | H36: {=IFERROR(INDEX(Milestones!$E:$E, MATCH($B36, Milestones!$B:$B, 0)), "")} | I36: FTE | J36: 0.05 | K36: High | L36: {=IF($K36="","", IFERROR(IFS($K36="Low", INDEX('Lookups - Complexity'!$C:$C, MATCH($B36, 'Lookups - Complexity'!$B:$B,0)), $K36="Medium", INDEX('Lookups - Complexity'!$D:$D, MATCH($B36, 'Lookups - Complexity'!$B:$B,0)), $K36="High", INDEX('Lookups - Complexity'!$E:$E, MATCH($B36, 'Lookups - Complexity'!$B:$B,0))), ""))} | M36: =IF($I36="FTE", Assumptions!$B$3, "") | N36: {=IFERROR(INDEX(Milestones!$F:$F, MATCH($B36, Milestones!$B:$B, 0)), "")} | O36: {=IFERROR(INDEX(Milestones!$G:$G, MATCH($B36, Milestones!$B:$B, 0)), "")} | P36: {=IFERROR(INDEX('Lookups - Rates'!$D:$D, MATCH($G36&"|"&$H36, 'Lookups - Rates'!$Z:$Z, 0)), "")} | Q36: {=IFERROR(INDEX('Lookups - Rates'!$E:$E, MATCH($G36&"|"&$H36, 'Lookups - Rates'!$Z:$Z, 0)), "")} | R36: =LET(ev,$J36, ch,$L36, hr,$P36, dr,$Q36, hpday,Assumptions!$B$2, hpw,Assumptions!$B$3, w,$M36, hrs, IF($I36="Hours", ev, IF($I36="Days", ev*IF(dr>0, dr/hr, hpday), IF($I36="FTE", ev*hpw*w, ch))), IF(hrs="", "", hrs*hr)) | T36: {=XLOOKUP(Scenario_Selected, INDEX(Scenario_Table,0,1), INDEX(Scenario_Table,0,2))} | U36: {=XLOOKUP(Scenario_Selected, INDEX(Scenario_Table,0,1), INDEX(Scenario_Table,0,3))} | V36: {=XLOOKUP(Scenario_Selected, INDEX(Scenario_Table,0,1), INDEX(Scenario_Table,0,4))} | W36: {=LET(ev,$J36, ch,$L36, et,$I36, dr,$Q36, hpday,Assumptions!$B$2, hpw,Assumptions!$B$3, w,$M36,hm,INDIRECT("R[0]C[0]",FALSE),hrs, IF(et="Hours", ev, IF(et="Days", ev*IF(dr>0, dr/$P36, hpday), IF(et="FTE", ev*hpw*w, ch))), IF(hrs="", "", hrs*hm))} | X36: =IF($P36="","", $P36*INDIRECT("R[0]C[-3]",FALSE)) | Y36: =IF(INDIRECT("R[0]C[-1]",FALSE)="","", INDIRECT("R[0]C[-2]",FALSE)*INDIRECT("R[0]C[-1]",FALSE)*(1+INDIRECT("R[0]C[-3]",FALSE)))
A37: 36 | B37: Continuous Improvement Framework | C37: {=IFERROR(INDEX(Milestones!$A:$A, MATCH($B37, Milestones!$B:$B, 0)), "")} | D37: {=IFERROR(INDEX(Milestones!$C:$C, MATCH($B37, Milestones!$B:$B, 0)), "")} | E37: Maintain engagement and track long-term adoption trends. | F37: {=IFERROR(INDEX(Milestones!$E:$E, MATCH($B37, Milestones!$B:$B, 0)), "")} | G37: Adobe | H37: Adobe | I37: FTE | J37: 0.03 | K37: Medium | L37: {=IF($K37="","", IFERROR(IFS($K37="Low", INDEX('Lookups - Complexity'!$C:$C, MATCH($B37, 'Lookups - Complexity'!$B:$B,0)), $K37="Medium", INDEX('Lookups - Complexity'!$D:$D, MATCH($B37, 'Lookups - Complexity'!$B:$B,0)), $K37="High", INDEX('Lookups - Complexity'!$E:$E, MATCH($B37, 'Lookups - Complexity'!$B:$B,0))), ""))} | M37: =IF($I37="FTE", Assumptions!$B$3, "") | N37: {=IFERROR(INDEX(Milestones!$F:$F, MATCH($B37, Milestones!$B:$B, 0)), "")} | O37: {=IFERROR(INDEX(Milestones!$G:$G, MATCH($B37, Milestones!$B:$B, 0)), "")} | P37: {=IFERROR(INDEX('Lookups - Rates'!$D:$D, MATCH($G37&"|"&$H37, 'Lookups - Rates'!$Z:$Z, 0)), "")} | Q37: {=IFERROR(INDEX('Lookups - Rates'!$E:$E, MATCH($G37&"|"&$H37, 'Lookups - Rates'!$Z:$Z, 0)), "")} | R37: =LET(ev,$J37, ch,$L37, hr,$P37, dr,$Q37, hpday,Assumptions!$B$2, hpw,Assumptions!$B$3, w,$M37, hrs, IF($I37="Hours", ev, IF($I37="Days", ev*IF(dr>0, dr/hr, hpday), IF($I37="FTE", ev*hpw*w, ch))), IF(hrs="", "", hrs*hr)) | T37: {=XLOOKUP(Scenario_Selected, INDEX(Scenario_Table,0,1), INDEX(Scenario_Table,0,2))} | U37: {=XLOOKUP(Scenario_Selected, INDEX(Scenario_Table,0,1), INDEX(Scenario_Table,0,3))} | V37: {=XLOOKUP(Scenario_Selected, INDEX(Scenario_Table,0,1), INDEX(Scenario_Table,0,4))} | W37: {=LET(ev,$J37, ch,$L37, et,$I37, dr,$Q37, hpday,Assumptions!$B$2, hpw,Assumptions!$B$3, w,$M37,hm,INDIRECT("R[0]C[0]",FALSE),hrs, IF(et="Hours", ev, IF(et="Days", ev*IF(dr>0, dr/$P37, hpday), IF(et="FTE", ev*hpw*w, ch))), IF(hrs="", "", hrs*hm))} | X37: =IF($P37="","", $P37*INDIRECT("R[0]C[-3]",FALSE)) | Y37: =IF(INDIRECT("R[0]C[-1]",FALSE)="","", INDIRECT("R[0]C[-2]",FALSE)*INDIRECT("R[0]C[-1]",FALSE)*(1+INDIRECT("R[0]C[-3]",FALSE)))
A38: 37 | B38: Strategic Partnership Review | C38: {=IFERROR(INDEX(Milestones!$A:$A, MATCH($B38, Milestones!$B:$B, 0)), "")} | D38: {=IFERROR(INDEX(Milestones!$C:$C, MATCH($B38, Milestones!$B:$B, 0)), "")} | E38: Evaluate ongoing partnership alignment and strategic direction. | F38: {=IFERROR(INDEX(Milestones!$E:$E, MATCH($B38, Milestones!$B:$B, 0)), "")} | G38: Knapsack | H38: Adobe | I38: FTE | J38: 0.03 | K38: Medium | L38: {=IF($K38="","", IFERROR(IFS($K38="Low", INDEX('Lookups - Complexity'!$C:$C, MATCH($B38, 'Lookups - Complexity'!$B:$B,0)), $K38="Medium", INDEX('Lookups - Complexity'!$D:$D, MATCH($B38, 'Lookups - Complexity'!$B:$B,0)), $K38="High", INDEX('Lookups - Complexity'!$E:$E, MATCH($B38, 'Lookups - Complexity'!$B:$B,0))), ""))} | M38: =IF($I38="FTE", Assumptions!$B$3, "") | N38: {=IFERROR(INDEX(Milestones!$F:$F, MATCH($B38, Milestones!$B:$B, 0)), "")} | O38: {=IFERROR(INDEX(Milestones!$G:$G, MATCH($B38, Milestones!$B:$B, 0)), "")} | P38: {=IFERROR(INDEX('Lookups - Rates'!$D:$D, MATCH($G38&"|"&$H38, 'Lookups - Rates'!$Z:$Z, 0)), "")} | Q38: {=IFERROR(INDEX('Lookups - Rates'!$E:$E, MATCH($G38&"|"&$H38, 'Lookups - Rates'!$Z:$Z, 0)), "")} | R38: =LET(ev,$J38, ch,$L38, hr,$P38, dr,$Q38, hpday,Assumptions!$B$2, hpw,Assumptions!$B$3, w,$M38, hrs, IF($I38="Hours", ev, IF($I38="Days", ev*IF(dr>0, dr/hr, hpday), IF($I38="FTE", ev*hpw*w, ch))), IF(hrs="", "", hrs*hr)) | T38: {=XLOOKUP(Scenario_Selected, INDEX(Scenario_Table,0,1), INDEX(Scenario_Table,0,2))} | U38: {=XLOOKUP(Scenario_Selected, INDEX(Scenario_Table,0,1), INDEX(Scenario_Table,0,3))} | V38: {=XLOOKUP(Scenario_Selected, INDEX(Scenario_Table,0,1), INDEX(Scenario_Table,0,4))} | W38: {=LET(ev,$J38, ch,$L38, et,$I38, dr,$Q38, hpday,Assumptions!$B$2, hpw,Assumptions!$B$3, w,$M38,hm,INDIRECT("R[0]C[0]",FALSE),hrs, IF(et="Hours", ev, IF(et="Days", ev*IF(dr>0, dr/$P38, hpday), IF(et="FTE", ev*hpw*w, ch))), IF(hrs="", "", hrs*hm))} | X38: =IF($P38="","", $P38*INDIRECT("R[0]C[-3]",FALSE)) | Y38: =IF(INDIRECT("R[0]C[-1]",FALSE)="","", INDIRECT("R[0]C[-2]",FALSE)*INDIRECT("R[0]C[-1]",FALSE)*(1+INDIRECT("R[0]C[-3]",FALSE)))
A39: 38 | B39: Case Study Development | C39: {=IFERROR(INDEX(Milestones!$A:$A, MATCH($B39, Milestones!$B:$B, 0)), "")} | D39: {=IFERROR(INDEX(Milestones!$C:$C, MATCH($B39, Milestones!$B:$B, 0)), "")} | E39: Document program success and outcomes for future scaling. | F39: {=IFERROR(INDEX(Milestones!$E:$E, MATCH($B39, Milestones!$B:$B, 0)), "")} | G39: Adobe | H39: {=IFERROR(INDEX(Milestones!$E:$E, MATCH($B39, Milestones!$B:$B, 0)), "")} | I39: FTE | J39: 0.03 | K39: Medium | L39: {=IF($K39="","", IFERROR(IFS($K39="Low", INDEX('Lookups - Complexity'!$C:$C, MATCH($B39, 'Lookups - Complexity'!$B:$B,0)), $K39="Medium", INDEX('Lookups - Complexity'!$D:$D, MATCH($B39, 'Lookups - Complexity'!$B:$B,0)), $K39="High", INDEX('Lookups - Complexity'!$E:$E, MATCH($B39, 'Lookups - Complexity'!$B:$B,0))), ""))} | M39: =IF($I39="FTE", Assumptions!$B$3, "") | N39: {=IFERROR(INDEX(Milestones!$F:$F, MATCH($B39, Milestones!$B:$B, 0)), "")} | O39: {=IFERROR(INDEX(Milestones!$G:$G, MATCH($B39, Milestones!$B:$B, 0)), "")} | P39: {=IFERROR(INDEX('Lookups - Rates'!$D:$D, MATCH($G39&"|"&$H39, 'Lookups - Rates'!$Z:$Z, 0)), "")} | Q39: {=IFERROR(INDEX('Lookups - Rates'!$E:$E, MATCH($G39&"|"&$H39, 'Lookups - Rates'!$Z:$Z, 0)), "")} | R39: =LET(ev,$J39, ch,$L39, hr,$P39, dr,$Q39, hpday,Assumptions!$B$2, hpw,Assumptions!$B$3, w,$M39, hrs, IF($I39="Hours", ev, IF($I39="Days", ev*IF(dr>0, dr/hr, hpday), IF($I39="FTE", ev*hpw*w, ch))), IF(hrs="", "", hrs*hr)) | T39: {=XLOOKUP(Scenario_Selected, INDEX(Scenario_Table,0,1), INDEX(Scenario_Table,0,2))} | U39: {=XLOOKUP(Scenario_Selected, INDEX(Scenario_Table,0,1), INDEX(Scenario_Table,0,3))} | V39: {=XLOOKUP(Scenario_Selected, INDEX(Scenario_Table,0,1), INDEX(Scenario_Table,0,4))} | W39: {=LET(ev,$J39, ch,$L39, et,$I39, dr,$Q39, hpday,Assumptions!$B$2, hpw,Assumptions!$B$3, w,$M39,hm,INDIRECT("R[0]C[0]",FALSE),hrs, IF(et="Hours", ev, IF(et="Days", ev*IF(dr>0, dr/$P39, hpday), IF(et="FTE", ev*hpw*w, ch))), IF(hrs="", "", hrs*hm))} | X39: =IF($P39="","", $P39*INDIRECT("R[0]C[-3]",FALSE)) | Y39: =IF(INDIRECT("R[0]C[-1]",FALSE)="","", INDIRECT("R[0]C[-2]",FALSE)*INDIRECT("R[0]C[-1]",FALSE)*(1+INDIRECT("R[0]C[-3]",FALSE)))
A40: 39
A41: 40 | C41: {=IFERROR(INDEX(Milestones!$A:$A, MATCH($B41, Milestones!$B:$B, 0)), "")} | D41: {=IFERROR(INDEX(Milestones!$C:$C, MATCH($B41, Milestones!$B:$B, 0)), "")} | F41: {=IFERROR(INDEX(Milestones!$E:$E, MATCH($B41, Milestones!$B:$B, 0)), "")} | L41: {=IF($K41="","", IFERROR(IFS($K41="Low", INDEX('Lookups - Complexity'!$C:$C, MATCH($B41, 'Lookups - Complexity'!$B:$B,0)), $K41="Medium", INDEX('Lookups - Complexity'!$D:$D, MATCH($B41, 'Lookups - Complexity'!$B:$B,0)), $K41="High", INDEX('Lookups - Complexity'!$E:$E, MATCH($B41, 'Lookups - Complexity'!$B:$B,0))), ""))} | M41: =IF($I41="FTE", Assumptions!$B$3, "") | N41: {=IFERROR(INDEX(Milestones!$F:$F, MATCH($B41, Milestones!$B:$B, 0)), "")} | O41: {=IFERROR(INDEX(Milestones!$G:$G, MATCH($B41, Milestones!$B:$B, 0)), "")} | P41: {=IFERROR(INDEX('Lookups - Rates'!$D:$D, MATCH($G41&"|"&$H41, 'Lookups - Rates'!$Z:$Z, 0)), "")} | Q41: {=IFERROR(INDEX('Lookups - Rates'!$E:$E, MATCH($G41&"|"&$H41, 'Lookups - Rates'!$Z:$Z, 0)), "")} | R41: =LET(ev,$J41, ch,$L41, hr,$P41, dr,$Q41, hpday,Assumptions!$B$2, hpw,Assumptions!$B$3, w,$M41, hrs, IF($I41="Hours", ev, IF($I41="Days", ev*IF(dr>0, dr/hr, hpday), IF($I41="FTE", ev*hpw*w, ch))), IF(hrs="", "", hrs*hr)) | T41: {=XLOOKUP(Scenario_Selected, INDEX(Scenario_Table,0,1), INDEX(Scenario_Table,0,2))} | U41: {=XLOOKUP(Scenario_Selected, INDEX(Scenario_Table,0,1), INDEX(Scenario_Table,0,3))} | V41: {=XLOOKUP(Scenario_Selected, INDEX(Scenario_Table,0,1), INDEX(Scenario_Table,0,4))} | W41: {=LET(ev,$J41, ch,$L41, et,$I41, dr,$Q41, hpday,Assumptions!$B$2, hpw,Assumptions!$B$3, w,$M41,hm,INDIRECT("R[0]C[0]",FALSE),hrs, IF(et="Hours", ev, IF(et="Days", ev*IF(dr>0, dr/$P41, hpday), IF(et="FTE", ev*hpw*w, ch))), IF(hrs="", "", hrs*hm))} | X41: =IF($P41="","", $P41*INDIRECT("R[0]C[-3]",FALSE)) | Y41: =IF(INDIRECT("R[0]C[-1]",FALSE)="","", INDIRECT("R[0]C[-2]",FALSE)*INDIRECT("R[0]C[-1]",FALSE)*(1+INDIRECT("R[0]C[-3]",FALSE)))
A42: 41 | C42: {=IFERROR(INDEX(Milestones!$A:$A, MATCH($B42, Milestones!$B:$B, 0)), "")} | D42: {=IFERROR(INDEX(Milestones!$C:$C, MATCH($B42, Milestones!$B:$B, 0)), "")} | F42: {=IFERROR(INDEX(Milestones!$E:$E, MATCH($B42, Milestones!$B:$B, 0)), "")} | L42: {=IF($K42="","", IFERROR(IFS($K42="Low", INDEX('Lookups - Complexity'!$C:$C, MATCH($B42, 'Lookups - Complexity'!$B:$B,0)), $K42="Medium", INDEX('Lookups - Complexity'!$D:$D, MATCH($B42, 'Lookups - Complexity'!$B:$B,0)), $K42="High", INDEX('Lookups - Complexity'!$E:$E, MATCH($B42, 'Lookups - Complexity'!$B:$B,0))), ""))} | M42: =IF($I42="FTE", Assumptions!$B$3, "") | N42: {=IFERROR(INDEX(Milestones!$F:$F, MATCH($B42, Milestones!$B:$B, 0)), "")} | O42: {=IFERROR(INDEX(Milestones!$G:$G, MATCH($B42, Milestones!$B:$B, 0)), "")} | P42: {=IFERROR(INDEX('Lookups - Rates'!$D:$D, MATCH($G42&"|"&$H42, 'Lookups - Rates'!$Z:$Z, 0)), "")} | Q42: {=IFERROR(INDEX('Lookups - Rates'!$E:$E, MATCH($G42&"|"&$H42, 'Lookups - Rates'!$Z:$Z, 0)), "")} | R42: =LET(ev,$J42, ch,$L42, hr,$P42, dr,$Q42, hpday,Assumptions!$B$2, hpw,Assumptions!$B$3, w,$M42, hrs, IF($I42="Hours", ev, IF($I42="Days", ev*IF(dr>0, dr/hr, hpday), IF($I42="FTE", ev*hpw*w, ch))), IF(hrs="", "", hrs*hr)) | T42: {=XLOOKUP(Scenario_Selected, INDEX(Scenario_Table,0,1), INDEX(Scenario_Table,0,2))} | U42: {=XLOOKUP(Scenario_Selected, INDEX(Scenario_Table,0,1), INDEX(Scenario_Table,0,3))} | V42: {=XLOOKUP(Scenario_Selected, INDEX(Scenario_Table,0,1), INDEX(Scenario_Table,0,4))} | W42: {=LET(ev,$J42, ch,$L42, et,$I42, dr,$Q42, hpday,Assumptions!$B$2, hpw,Assumptions!$B$3, w,$M42,hm,INDIRECT("R[0]C[0]",FALSE),hrs, IF(et="Hours", ev, IF(et="Days", ev*IF(dr>0, dr/$P42, hpday), IF(et="FTE", ev*hpw*w, ch))), IF(hrs="", "", hrs*hm))} | X42: =IF($P42="","", $P42*INDIRECT("R[0]C[-3]",FALSE)) | Y42: =IF(INDIRECT("R[0]C[-1]",FALSE)="","", INDIRECT("R[0]C[-2]",FALSE)*INDIRECT("R[0]C[-1]",FALSE)*(1+INDIRECT("R[0]C[-3]",FALSE)))
A43: 42 | C43: {=IFERROR(INDEX(Milestones!$A:$A, MATCH($B43, Milestones!$B:$B, 0)), "")} | D43: {=IFERROR(INDEX(Milestones!$C:$C, MATCH($B43, Milestones!$B:$B, 0)), "")} | F43: {=IFERROR(INDEX(Milestones!$E:$E, MATCH($B43, Milestones!$B:$B, 0)), "")} | L43: {=IF($K43="","", IFERROR(IFS($K43="Low", INDEX('Lookups - Complexity'!$C:$C, MATCH($B43, 'Lookups - Complexity'!$B:$B,0)), $K43="Medium", INDEX('Lookups - Complexity'!$D:$D, MATCH($B43, 'Lookups - Complexity'!$B:$B,0)), $K43="High", INDEX('Lookups - Complexity'!$E:$E, MATCH($B43, 'Lookups - Complexity'!$B:$B,0))), ""))} | M43: =IF($I43="FTE", Assumptions!$B$3, "") | N43: {=IFERROR(INDEX(Milestones!$F:$F, MATCH($B43, Milestones!$B:$B, 0)), "")} | O43: {=IFERROR(INDEX(Milestones!$G:$G, MATCH($B43, Milestones!$B:$B, 0)), "")} | P43: {=IFERROR(INDEX('Lookups - Rates'!$D:$D, MATCH($G43&"|"&$H43, 'Lookups - Rates'!$Z:$Z, 0)), "")} | Q43: {=IFERROR(INDEX('Lookups - Rates'!$E:$E, MATCH($G43&"|"&$H43, 'Lookups - Rates'!$Z:$Z, 0)), "")} | R43: =LET(ev,$J43, ch,$L43, hr,$P43, dr,$Q43, hpday,Assumptions!$B$2, hpw,Assumptions!$B$3, w,$M43, hrs, IF($I43="Hours", ev, IF($I43="Days", ev*IF(dr>0, dr/hr, hpday), IF($I43="FTE", ev*hpw*w, ch))), IF(hrs="", "", hrs*hr)) | T43: {=XLOOKUP(Scenario_Selected, INDEX(Scenario_Table,0,1), INDEX(Scenario_Table,0,2))} | U43: {=XLOOKUP(Scenario_Selected, INDEX(Scenario_Table,0,1), INDEX(Scenario_Table,0,3))} | V43: {=XLOOKUP(Scenario_Selected, INDEX(Scenario_Table,0,1), INDEX(Scenario_Table,0,4))} | W43: {=LET(ev,$J43, ch,$L43, et,$I43, dr,$Q43, hpday,Assumptions!$B$2, hpw,Assumptions!$B$3, w,$M43,hm,INDIRECT("R[0]C[0]",FALSE),hrs, IF(et="Hours", ev, IF(et="Days", ev*IF(dr>0, dr/$P43, hpday), IF(et="FTE", ev*hpw*w, ch))), IF(hrs="", "", hrs*hm))} | X43: =IF($P43="","", $P43*INDIRECT("R[0]C[-3]",FALSE)) | Y43: =IF(INDIRECT("R[0]C[-1]",FALSE)="","", INDIRECT("R[0]C[-2]",FALSE)*INDIRECT("R[0]C[-1]",FALSE)*(1+INDIRECT("R[0]C[-3]",FALSE)))
A44: 43 | C44: {=IFERROR(INDEX(Milestones!$A:$A, MATCH($B44, Milestones!$B:$B, 0)), "")} | D44: {=IFERROR(INDEX(Milestones!$C:$C, MATCH($B44, Milestones!$B:$B, 0)), "")} | F44: {=IFERROR(INDEX(Milestones!$E:$E, MATCH($B44, Milestones!$B:$B, 0)), "")} | L44: {=IF($K44="","", IFERROR(IFS($K44="Low", INDEX('Lookups - Complexity'!$C:$C, MATCH($B44, 'Lookups - Complexity'!$B:$B,0)), $K44="Medium", INDEX('Lookups - Complexity'!$D:$D, MATCH($B44, 'Lookups - Complexity'!$B:$B,0)), $K44="High", INDEX('Lookups - Complexity'!$E:$E, MATCH($B44, 'Lookups - Complexity'!$B:$B,0))), ""))} | M44: =IF($I44="FTE", Assumptions!$B$3, "") | N44: {=IFERROR(INDEX(Milestones!$F:$F, MATCH($B44, Milestones!$B:$B, 0)), "")} | O44: {=IFERROR(INDEX(Milestones!$G:$G, MATCH($B44, Milestones!$B:$B, 0)), "")} | P44: {=IFERROR(INDEX('Lookups - Rates'!$D:$D, MATCH($G44&"|"&$H44, 'Lookups - Rates'!$Z:$Z, 0)), "")} | Q44: {=IFERROR(INDEX('Lookups - Rates'!$E:$E, MATCH($G44&"|"&$H44, 'Lookups - Rates'!$Z:$Z, 0)), "")} | R44: =LET(ev,$J44, ch,$L44, hr,$P44, dr,$Q44, hpday,Assumptions!$B$2, hpw,Assumptions!$B$3, w,$M44, hrs, IF($I44="Hours", ev, IF($I44="Days", ev*IF(dr>0, dr/hr, hpday), IF($I44="FTE", ev*hpw*w, ch))), IF(hrs="", "", hrs*hr)) | T44: {=XLOOKUP(Scenario_Selected, INDEX(Scenario_Table,0,1), INDEX(Scenario_Table,0,2))} | U44: {=XLOOKUP(Scenario_Selected, INDEX(Scenario_Table,0,1), INDEX(Scenario_Table,0,3))} | V44: {=XLOOKUP(Scenario_Selected, INDEX(Scenario_Table,0,1), INDEX(Scenario_Table,0,4))} | W44: {=LET(ev,$J44, ch,$L44, et,$I44, dr,$Q44, hpday,Assumptions!$B$2, hpw,Assumptions!$B$3, w,$M44,hm,INDIRECT("R[0]C[0]",FALSE),hrs, IF(et="Hours", ev, IF(et="Days", ev*IF(dr>0, dr/$P44, hpday), IF(et="FTE", ev*hpw*w, ch))), IF(hrs="", "", hrs*hm))} | X44: =IF($P44="","", $P44*INDIRECT("R[0]C[-3]",FALSE)) | Y44: =IF(INDIRECT("R[0]C[-1]",FALSE)="","", INDIRECT("R[0]C[-2]",FALSE)*INDIRECT("R[0]C[-1]",FALSE)*(1+INDIRECT("R[0]C[-3]",FALSE)))
A45: 44 | C45: {=IFERROR(INDEX(Milestones!$A:$A, MATCH($B45, Milestones!$B:$B, 0)), "")} | D45: {=IFERROR(INDEX(Milestones!$C:$C, MATCH($B45, Milestones!$B:$B, 0)), "")} | F45: {=IFERROR(INDEX(Milestones!$E:$E, MATCH($B45, Milestones!$B:$B, 0)), "")} | L45: {=IF($K45="","", IFERROR(IFS($K45="Low", INDEX('Lookups - Complexity'!$C:$C, MATCH($B45, 'Lookups - Complexity'!$B:$B,0)), $K45="Medium", INDEX('Lookups - Complexity'!$D:$D, MATCH($B45, 'Lookups - Complexity'!$B:$B,0)), $K45="High", INDEX('Lookups - Complexity'!$E:$E, MATCH($B45, 'Lookups - Complexity'!$B:$B,0))), ""))} | M45: =IF($I45="FTE", Assumptions!$B$3, "") | N45: {=IFERROR(INDEX(Milestones!$F:$F, MATCH($B45, Milestones!$B:$B, 0)), "")} | O45: {=IFERROR(INDEX(Milestones!$G:$G, MATCH($B45, Milestones!$B:$B, 0)), "")} | P45: {=IFERROR(INDEX('Lookups - Rates'!$D:$D, MATCH($G45&"|"&$H45, 'Lookups - Rates'!$Z:$Z, 0)), "")} | Q45: {=IFERROR(INDEX('Lookups - Rates'!$E:$E, MATCH($G45&"|"&$H45, 'Lookups - Rates'!$Z:$Z, 0)), "")} | R45: =LET(ev,$J45, ch,$L45, hr,$P45, dr,$Q45, hpday,Assumptions!$B$2, hpw,Assumptions!$B$3, w,$M45, hrs, IF($I45="Hours", ev, IF($I45="Days", ev*IF(dr>0, dr/hr, hpday), IF($I45="FTE", ev*hpw*w, ch))), IF(hrs="", "", hrs*hr)) | T45: {=XLOOKUP(Scenario_Selected, INDEX(Scenario_Table,0,1), INDEX(Scenario_Table,0,2))} | U45: {=XLOOKUP(Scenario_Selected, INDEX(Scenario_Table,0,1), INDEX(Scenario_Table,0,3))} | V45: {=XLOOKUP(Scenario_Selected, INDEX(Scenario_Table,0,1), INDEX(Scenario_Table,0,4))} | W45: {=LET(ev,$J45, ch,$L45, et,$I45, dr,$Q45, hpday,Assumptions!$B$2, hpw,Assumptions!$B$3, w,$M45,hm,INDIRECT("R[0]C[0]",FALSE),hrs, IF(et="Hours", ev, IF(et="Days", ev*IF(dr>0, dr/$P45, hpday), IF(et="FTE", ev*hpw*w, ch))), IF(hrs="", "", hrs*hm))} | X45: =IF($P45="","", $P45*INDIRECT("R[0]C[-3]",FALSE)) | Y45: =IF(INDIRECT("R[0]C[-1]",FALSE)="","", INDIRECT("R[0]C[-2]",FALSE)*INDIRECT("R[0]C[-1]",FALSE)*(1+INDIRECT("R[0]C[-3]",FALSE)))
A46: 45 | C46: {=IFERROR(INDEX(Milestones!$A:$A, MATCH($B46, Milestones!$B:$B, 0)), "")} | D46: {=IFERROR(INDEX(Milestones!$C:$C, MATCH($B46, Milestones!$B:$B, 0)), "")} | F46: {=IFERROR(INDEX(Milestones!$E:$E, MATCH($B46, Milestones!$B:$B, 0)), "")} | L46: {=IF($K46="","", IFERROR(IFS($K46="Low", INDEX('Lookups - Complexity'!$C:$C, MATCH($B46, 'Lookups - Complexity'!$B:$B,0)), $K46="Medium", INDEX('Lookups - Complexity'!$D:$D, MATCH($B46, 'Lookups - Complexity'!$B:$B,0)), $K46="High", INDEX('Lookups - Complexity'!$E:$E, MATCH($B46, 'Lookups - Complexity'!$B:$B,0))), ""))} | M46: =IF($I46="FTE", Assumptions!$B$3, "") | N46: {=IFERROR(INDEX(Milestones!$F:$F, MATCH($B46, Milestones!$B:$B, 0)), "")} | O46: {=IFERROR(INDEX(Milestones!$G:$G, MATCH($B46, Milestones!$B:$B, 0)), "")} | P46: {=IFERROR(INDEX('Lookups - Rates'!$D:$D, MATCH($G46&"|"&$H46, 'Lookups - Rates'!$Z:$Z, 0)), "")} | Q46: {=IFERROR(INDEX('Lookups - Rates'!$E:$E, MATCH($G46&"|"&$H46, 'Lookups - Rates'!$Z:$Z, 0)), "")} | R46: =LET(ev,$J46, ch,$L46, hr,$P46, dr,$Q46, hpday,Assumptions!$B$2, hpw,Assumptions!$B$3, w,$M46, hrs, IF($I46="Hours", ev, IF($I46="Days", ev*IF(dr>0, dr/hr, hpday), IF($I46="FTE", ev*hpw*w, ch))), IF(hrs="", "", hrs*hr)) | T46: {=XLOOKUP(Scenario_Selected, INDEX(Scenario_Table,0,1), INDEX(Scenario_Table,0,2))} | U46: {=XLOOKUP(Scenario_Selected, INDEX(Scenario_Table,0,1), INDEX(Scenario_Table,0,3))} | V46: {=XLOOKUP(Scenario_Selected, INDEX(Scenario_Table,0,1), INDEX(Scenario_Table,0,4))} | W46: {=LET(ev,$J46, ch,$L46, et,$I46, dr,$Q46, hpday,Assumptions!$B$2, hpw,Assumptions!$B$3, w,$M46,hm,INDIRECT("R[0]C[0]",FALSE),hrs, IF(et="Hours", ev, IF(et="Days", ev*IF(dr>0, dr/$P46, hpday), IF(et="FTE", ev*hpw*w, ch))), IF(hrs="", "", hrs*hm))} | X46: =IF($P46="","", $P46*INDIRECT("R[0]C[-3]",FALSE)) | Y46: =IF(INDIRECT("R[0]C[-1]",FALSE)="","", INDIRECT("R[0]C[-2]",FALSE)*INDIRECT("R[0]C[-1]",FALSE)*(1+INDIRECT("R[0]C[-3]",FALSE)))
A47: 46 | C47: {=IFERROR(INDEX(Milestones!$A:$A, MATCH($B47, Milestones!$B:$B, 0)), "")} | D47: {=IFERROR(INDEX(Milestones!$C:$C, MATCH($B47, Milestones!$B:$B, 0)), "")} | F47: {=IFERROR(INDEX(Milestones!$E:$E, MATCH($B47, Milestones!$B:$B, 0)), "")} | L47: {=IF($K47="","", IFERROR(IFS($K47="Low", INDEX('Lookups - Complexity'!$C:$C, MATCH($B47, 'Lookups - Complexity'!$B:$B,0)), $K47="Medium", INDEX('Lookups - Complexity'!$D:$D, MATCH($B47, 'Lookups - Complexity'!$B:$B,0)), $K47="High", INDEX('Lookups - Complexity'!$E:$E, MATCH($B47, 'Lookups - Complexity'!$B:$B,0))), ""))} | M47: =IF($I47="FTE", Assumptions!$B$3, "") | N47: {=IFERROR(INDEX(Milestones!$F:$F, MATCH($B47, Milestones!$B:$B, 0)), "")} | O47: {=IFERROR(INDEX(Milestones!$G:$G, MATCH($B47, Milestones!$B:$B, 0)), "")} | P47: {=IFERROR(INDEX('Lookups - Rates'!$D:$D, MATCH($G47&"|"&$H47, 'Lookups - Rates'!$Z:$Z, 0)), "")} | Q47: {=IFERROR(INDEX('Lookups - Rates'!$E:$E, MATCH($G47&"|"&$H47, 'Lookups - Rates'!$Z:$Z, 0)), "")} | R47: =LET(ev,$J47, ch,$L47, hr,$P47, dr,$Q47, hpday,Assumptions!$B$2, hpw,Assumptions!$B$3, w,$M47, hrs, IF($I47="Hours", ev, IF($I47="Days", ev*IF(dr>0, dr/hr, hpday), IF($I47="FTE", ev*hpw*w, ch))), IF(hrs="", "", hrs*hr)) | T47: {=XLOOKUP(Scenario_Selected, INDEX(Scenario_Table,0,1), INDEX(Scenario_Table,0,2))} | U47: {=XLOOKUP(Scenario_Selected, INDEX(Scenario_Table,0,1), INDEX(Scenario_Table,0,3))} | V47: {=XLOOKUP(Scenario_Selected, INDEX(Scenario_Table,0,1), INDEX(Scenario_Table,0,4))} | W47: {=LET(ev,$J47, ch,$L47, et,$I47, dr,$Q47, hpday,Assumptions!$B$2, hpw,Assumptions!$B$3, w,$M47,hm,INDIRECT("R[0]C[0]",FALSE),hrs, IF(et="Hours", ev, IF(et="Days", ev*IF(dr>0, dr/$P47, hpday), IF(et="FTE", ev*hpw*w, ch))), IF(hrs="", "", hrs*hm))} | X47: =IF($P47="","", $P47*INDIRECT("R[0]C[-3]",FALSE)) | Y47: =IF(INDIRECT("R[0]C[-1]",FALSE)="","", INDIRECT("R[0]C[-2]",FALSE)*INDIRECT("R[0]C[-1]",FALSE)*(1+INDIRECT("R[0]C[-3]",FALSE)))
A48: 47 | C48: {=IFERROR(INDEX(Milestones!$A:$A, MATCH($B48, Milestones!$B:$B, 0)), "")} | D48: {=IFERROR(INDEX(Milestones!$C:$C, MATCH($B48, Milestones!$B:$B, 0)), "")} | F48: {=IFERROR(INDEX(Milestones!$E:$E, MATCH($B48, Milestones!$B:$B, 0)), "")} | L48: {=IF($K48="","", IFERROR(IFS($K48="Low", INDEX('Lookups - Complexity'!$C:$C, MATCH($B48, 'Lookups - Complexity'!$B:$B,0)), $K48="Medium", INDEX('Lookups - Complexity'!$D:$D, MATCH($B48, 'Lookups - Complexity'!$B:$B,0)), $K48="High", INDEX('Lookups - Complexity'!$E:$E, MATCH($B48, 'Lookups - Complexity'!$B:$B,0))), ""))} | M48: =IF($I48="FTE", Assumptions!$B$3, "") | N48: {=IFERROR(INDEX(Milestones!$F:$F, MATCH($B48, Milestones!$B:$B, 0)), "")} | O48: {=IFERROR(INDEX(Milestones!$G:$G, MATCH($B48, Milestones!$B:$B, 0)), "")} | P48: {=IFERROR(INDEX('Lookups - Rates'!$D:$D, MATCH($G48&"|"&$H48, 'Lookups - Rates'!$Z:$Z, 0)), "")} | Q48: {=IFERROR(INDEX('Lookups - Rates'!$E:$E, MATCH($G48&"|"&$H48, 'Lookups - Rates'!$Z:$Z, 0)), "")} | R48: =LET(ev,$J48, ch,$L48, hr,$P48, dr,$Q48, hpday,Assumptions!$B$2, hpw,Assumptions!$B$3, w,$M48, hrs, IF($I48="Hours", ev, IF($I48="Days", ev*IF(dr>0, dr/hr, hpday), IF($I48="FTE", ev*hpw*w, ch))), IF(hrs="", "", hrs*hr)) | T48: {=XLOOKUP(Scenario_Selected, INDEX(Scenario_Table,0,1), INDEX(Scenario_Table,0,2))} | U48: {=XLOOKUP(Scenario_Selected, INDEX(Scenario_Table,0,1), INDEX(Scenario_Table,0,3))} | V48: {=XLOOKUP(Scenario_Selected, INDEX(Scenario_Table,0,1), INDEX(Scenario_Table,0,4))} | W48: {=LET(ev,$J48, ch,$L48, et,$I48, dr,$Q48, hpday,Assumptions!$B$2, hpw,Assumptions!$B$3, w,$M48,hm,INDIRECT("R[0]C[0]",FALSE),hrs, IF(et="Hours", ev, IF(et="Days", ev*IF(dr>0, dr/$P48, hpday), IF(et="FTE", ev*hpw*w, ch))), IF(hrs="", "", hrs*hm))} | X48: =IF($P48="","", $P48*INDIRECT("R[0]C[-3]",FALSE)) | Y48: =IF(INDIRECT("R[0]C[-1]",FALSE)="","", INDIRECT("R[0]C[-2]",FALSE)*INDIRECT("R[0]C[-1]",FALSE)*(1+INDIRECT("R[0]C[-3]",FALSE)))
A49: 48 | C49: {=IFERROR(INDEX(Milestones!$A:$A, MATCH($B49, Milestones!$B:$B, 0)), "")} | D49: {=IFERROR(INDEX(Milestones!$C:$C, MATCH($B49, Milestones!$B:$B, 0)), "")} | F49: {=IFERROR(INDEX(Milestones!$E:$E, MATCH($B49, Milestones!$B:$B, 0)), "")} | L49: {=IF($K49="","", IFERROR(IFS($K49="Low", INDEX('Lookups - Complexity'!$C:$C, MATCH($B49, 'Lookups - Complexity'!$B:$B,0)), $K49="Medium", INDEX('Lookups - Complexity'!$D:$D, MATCH($B49, 'Lookups - Complexity'!$B:$B,0)), $K49="High", INDEX('Lookups - Complexity'!$E:$E, MATCH($B49, 'Lookups - Complexity'!$B:$B,0))), ""))} | M49: =IF($I49="FTE", Assumptions!$B$3, "") | N49: {=IFERROR(INDEX(Milestones!$F:$F, MATCH($B49, Milestones!$B:$B, 0)), "")} | O49: {=IFERROR(INDEX(Milestones!$G:$G, MATCH($B49, Milestones!$B:$B, 0)), "")} | P49: {=IFERROR(INDEX('Lookups - Rates'!$D:$D, MATCH($G49&"|"&$H49, 'Lookups - Rates'!$Z:$Z, 0)), "")} | Q49: {=IFERROR(INDEX('Lookups - Rates'!$E:$E, MATCH($G49&"|"&$H49, 'Lookups - Rates'!$Z:$Z, 0)), "")} | R49: =LET(ev,$J49, ch,$L49, hr,$P49, dr,$Q49, hpday,Assumptions!$B$2, hpw,Assumptions!$B$3, w,$M49, hrs, IF($I49="Hours", ev, IF($I49="Days", ev*IF(dr>0, dr/hr, hpday), IF($I49="FTE", ev*hpw*w, ch))), IF(hrs="", "", hrs*hr)) | T49: {=XLOOKUP(Scenario_Selected, INDEX(Scenario_Table,0,1), INDEX(Scenario_Table,0,2))} | U49: {=XLOOKUP(Scenario_Selected, INDEX(Scenario_Table,0,1), INDEX(Scenario_Table,0,3))} | V49: {=XLOOKUP(Scenario_Selected, INDEX(Scenario_Table,0,1), INDEX(Scenario_Table,0,4))} | W49: {=LET(ev,$J49, ch,$L49, et,$I49, dr,$Q49, hpday,Assumptions!$B$2, hpw,Assumptions!$B$3, w,$M49,hm,INDIRECT("R[0]C[0]",FALSE),hrs, IF(et="Hours", ev, IF(et="Days", ev*IF(dr>0, dr/$P49, hpday), IF(et="FTE", ev*hpw*w, ch))), IF(hrs="", "", hrs*hm))} | X49: =IF($P49="","", $P49*INDIRECT("R[0]C[-3]",FALSE)) | Y49: =IF(INDIRECT("R[0]C[-1]",FALSE)="","", INDIRECT("R[0]C[-2]",FALSE)*INDIRECT("R[0]C[-1]",FALSE)*(1+INDIRECT("R[0]C[-3]",FALSE)))
A50: 49 | C50: {=IFERROR(INDEX(Milestones!$A:$A, MATCH($B50, Milestones!$B:$B, 0)), "")} | D50: {=IFERROR(INDEX(Milestones!$C:$C, MATCH($B50, Milestones!$B:$B, 0)), "")} | F50: {=IFERROR(INDEX(Milestones!$E:$E, MATCH($B50, Milestones!$B:$B, 0)), "")} | L50: {=IF($K50="","", IFERROR(IFS($K50="Low", INDEX('Lookups - Complexity'!$C:$C, MATCH($B50, 'Lookups - Complexity'!$B:$B,0)), $K50="Medium", INDEX('Lookups - Complexity'!$D:$D, MATCH($B50, 'Lookups - Complexity'!$B:$B,0)), $K50="High", INDEX('Lookups - Complexity'!$E:$E, MATCH($B50, 'Lookups - Complexity'!$B:$B,0))), ""))} | M50: =IF($I50="FTE", Assumptions!$B$3, "") | N50: {=IFERROR(INDEX(Milestones!$F:$F, MATCH($B50, Milestones!$B:$B, 0)), "")} | O50: {=IFERROR(INDEX(Milestones!$G:$G, MATCH($B50, Milestones!$B:$B, 0)), "")} | P50: {=IFERROR(INDEX('Lookups - Rates'!$D:$D, MATCH($G50&"|"&$H50, 'Lookups - Rates'!$Z:$Z, 0)), "")} | Q50: {=IFERROR(INDEX('Lookups - Rates'!$E:$E, MATCH($G50&"|"&$H50, 'Lookups - Rates'!$Z:$Z, 0)), "")} | R50: =LET(ev,$J50, ch,$L50, hr,$P50, dr,$Q50, hpday,Assumptions!$B$2, hpw,Assumptions!$B$3, w,$M50, hrs, IF($I50="Hours", ev, IF($I50="Days", ev*IF(dr>0, dr/hr, hpday), IF($I50="FTE", ev*hpw*w, ch))), IF(hrs="", "", hrs*hr)) | T50: {=XLOOKUP(Scenario_Selected, INDEX(Scenario_Table,0,1), INDEX(Scenario_Table,0,2))} | U50: {=XLOOKUP(Scenario_Selected, INDEX(Scenario_Table,0,1), INDEX(Scenario_Table,0,3))} | V50: {=XLOOKUP(Scenario_Selected, INDEX(Scenario_Table,0,1), INDEX(Scenario_Table,0,4))} | W50: {=LET(ev,$J50, ch,$L50, et,$I50, dr,$Q50, hpday,Assumptions!$B$2, hpw,Assumptions!$B$3, w,$M50,hm,INDIRECT("R[0]C[0]",FALSE),hrs, IF(et="Hours", ev, IF(et="Days", ev*IF(dr>0, dr/$P50, hpday), IF(et="FTE", ev*hpw*w, ch))), IF(hrs="", "", hrs*hm))} | X50: =IF($P50="","", $P50*INDIRECT("R[0]C[-3]",FALSE)) | Y50: =IF(INDIRECT("R[0]C[-1]",FALSE)="","", INDIRECT("R[0]C[-2]",FALSE)*INDIRECT("R[0]C[-1]",FALSE)*(1+INDIRECT("R[0]C[-3]",FALSE)))
A51: 50 | C51: {=IFERROR(INDEX(Milestones!$A:$A, MATCH($B51, Milestones!$B:$B, 0)), "")} | D51: {=IFERROR(INDEX(Milestones!$C:$C, MATCH($B51, Milestones!$B:$B, 0)), "")} | F51: {=IFERROR(INDEX(Milestones!$E:$E, MATCH($B51, Milestones!$B:$B, 0)), "")} | L51: {=IF($K51="","", IFERROR(IFS($K51="Low", INDEX('Lookups - Complexity'!$C:$C, MATCH($B51, 'Lookups - Complexity'!$B:$B,0)), $K51="Medium", INDEX('Lookups - Complexity'!$D:$D, MATCH($B51, 'Lookups - Complexity'!$B:$B,0)), $K51="High", INDEX('Lookups - Complexity'!$E:$E, MATCH($B51, 'Lookups - Complexity'!$B:$B,0))), ""))} | M51: =IF($I51="FTE", Assumptions!$B$3, "") | N51: {=IFERROR(INDEX(Milestones!$F:$F, MATCH($B51, Milestones!$B:$B, 0)), "")} | O51: {=IFERROR(INDEX(Milestones!$G:$G, MATCH($B51, Milestones!$B:$B, 0)), "")} | P51: {=IFERROR(INDEX('Lookups - Rates'!$D:$D, MATCH($G51&"|"&$H51, 'Lookups - Rates'!$Z:$Z, 0)), "")} | Q51: {=IFERROR(INDEX('Lookups - Rates'!$E:$E, MATCH($G51&"|"&$H51, 'Lookups - Rates'!$Z:$Z, 0)), "")} | R51: =LET(ev,$J51, ch,$L51, hr,$P51, dr,$Q51, hpday,Assumptions!$B$2, hpw,Assumptions!$B$3, w,$M51, hrs, IF($I51="Hours", ev, IF($I51="Days", ev*IF(dr>0, dr/hr, hpday), IF($I51="FTE", ev*hpw*w, ch))), IF(hrs="", "", hrs*hr)) | T51: {=XLOOKUP(Scenario_Selected, INDEX(Scenario_Table,0,1), INDEX(Scenario_Table,0,2))} | U51: {=XLOOKUP(Scenario_Selected, INDEX(Scenario_Table,0,1), INDEX(Scenario_Table,0,3))} | V51: {=XLOOKUP(Scenario_Selected, INDEX(Scenario_Table,0,1), INDEX(Scenario_Table,0,4))} | W51: {=LET(ev,$J51, ch,$L51, et,$I51, dr,$Q51, hpday,Assumptions!$B$2, hpw,Assumptions!$B$3, w,$M51,hm,INDIRECT("R[0]C[0]",FALSE),hrs, IF(et="Hours", ev, IF(et="Days", ev*IF(dr>0, dr/$P51, hpday), IF(et="FTE", ev*hpw*w, ch))), IF(hrs="", "", hrs*hm))} | X51: =IF($P51="","", $P51*INDIRECT("R[0]C[-3]",FALSE)) | Y51: =IF(INDIRECT("R[0]C[-1]",FALSE)="","", INDIRECT("R[0]C[-2]",FALSE)*INDIRECT("R[0]C[-1]",FALSE)*(1+INDIRECT("R[0]C[-3]",FALSE)))
A52: 51 | C52: {=IFERROR(INDEX(Milestones!$A:$A, MATCH($B52, Milestones!$B:$B, 0)), "")} | D52: {=IFERROR(INDEX(Milestones!$C:$C, MATCH($B52, Milestones!$B:$B, 0)), "")} | F52: {=IFERROR(INDEX(Milestones!$E:$E, MATCH($B52, Milestones!$B:$B, 0)), "")} | L52: {=IF($K52="","", IFERROR(IFS($K52="Low", INDEX('Lookups - Complexity'!$C:$C, MATCH($B52, 'Lookups - Complexity'!$B:$B,0)), $K52="Medium", INDEX('Lookups - Complexity'!$D:$D, MATCH($B52, 'Lookups - Complexity'!$B:$B,0)), $K52="High", INDEX('Lookups - Complexity'!$E:$E, MATCH($B52, 'Lookups - Complexity'!$B:$B,0))), ""))} | M52: =IF($I52="FTE", Assumptions!$B$3, "") | N52: {=IFERROR(INDEX(Milestones!$F:$F, MATCH($B52, Milestones!$B:$B, 0)), "")} | O52: {=IFERROR(INDEX(Milestones!$G:$G, MATCH($B52, Milestones!$B:$B, 0)), "")} | P52: {=IFERROR(INDEX('Lookups - Rates'!$D:$D, MATCH($G52&"|"&$H52, 'Lookups - Rates'!$Z:$Z, 0)), "")} | Q52: {=IFERROR(INDEX('Lookups - Rates'!$E:$E, MATCH($G52&"|"&$H52, 'Lookups - Rates'!$Z:$Z, 0)), "")} | R52: =LET(ev,$J52, ch,$L52, hr,$P52, dr,$Q52, hpday,Assumptions!$B$2, hpw,Assumptions!$B$3, w,$M52, hrs, IF($I52="Hours", ev, IF($I52="Days", ev*IF(dr>0, dr/hr, hpday), IF($I52="FTE", ev*hpw*w, ch))), IF(hrs="", "", hrs*hr)) | T52: {=XLOOKUP(Scenario_Selected, INDEX(Scenario_Table,0,1), INDEX(Scenario_Table,0,2))} | U52: {=XLOOKUP(Scenario_Selected, INDEX(Scenario_Table,0,1), INDEX(Scenario_Table,0,3))} | V52: {=XLOOKUP(Scenario_Selected, INDEX(Scenario_Table,0,1), INDEX(Scenario_Table,0,4))} | W52: {=LET(ev,$J52, ch,$L52, et,$I52, dr,$Q52, hpday,Assumptions!$B$2, hpw,Assumptions!$B$3, w,$M52,hm,INDIRECT("R[0]C[0]",FALSE),hrs, IF(et="Hours", ev, IF(et="Days", ev*IF(dr>0, dr/$P52, hpday), IF(et="FTE", ev*hpw*w, ch))), IF(hrs="", "", hrs*hm))} | X52: =IF($P52="","", $P52*INDIRECT("R[0]C[-3]",FALSE)) | Y52: =IF(INDIRECT("R[0]C[-1]",FALSE)="","", INDIRECT("R[0]C[-2]",FALSE)*INDIRECT("R[0]C[-1]",FALSE)*(1+INDIRECT("R[0]C[-3]",FALSE)))
... A400: 400 | C400: {=IFERROR(INDEX(Milestones!$A:$A, MATCH($B400, Milestones!$B:$B, 0)), "")} | D400: {=IFERROR(INDEX(Milestones!$C:$C, MATCH($B400, Milestones!$B:$B, 0)), "")} | F400: {=IFERROR(INDEX(Milestones!$E:$E, MATCH($B400, Milestones!$B:$B, 0)), "")} | L400: {=IF($K400="","", IFERROR(IFS($K400="Low", INDEX('Lookups - Complexity'!$C:$C, MATCH($B400, 'Lookups - Complexity'!$B:$B,0)), $K400="Medium", INDEX('Lookups - Complexity'!$D:$D, MATCH($B400, 'Lookups - Complexity'!$B:$B,0)), $K400="High", INDEX('Lookups - Complexity'!$E:$E, MATCH($B400, 'Lookups - Complexity'!$B:$B,0))), ""))} | M400: =IF($I400="FTE", Assumptions!$B$3, "") | N400: {=IFERROR(INDEX(Milestones!$F:$F, MATCH($B400, Milestones!$B:$B, 0)), "")} | O400: {=IFERROR(INDEX(Milestones!$G:$G, MATCH($B400, Milestones!$B:$B, 0)), "")} | P400: {=IFERROR(INDEX('Lookups - Rates'!$D:$D, MATCH($G400&"|"&$H400, 'Lookups - Rates'!$Z:$Z, 0)), "")} | Q400: {=IFERROR(INDEX('Lookups - Rates'!$E:$E, MATCH($G400&"|"&$H400, 'Lookups - Rates'!$Z:$Z, 0)), "")} | R400: =LET(ev,$J400, ch,$L400, hr,$P400, dr,$Q400, hpday,Assumptions!$B$2, hpw,Assumptions!$B$3, w,$M400, hrs, IF($I400="Hours", ev, IF($I400="Days", ev*IF(dr>0, dr/hr, hpday), IF($I400="FTE", ev*hpw*w, ch))), IF(hrs="", "", hrs*hr)) | T400: {=XLOOKUP(Scenario_Selected, INDEX(Scenario_Table,0,1), INDEX(Scenario_Table,0,2))} | U400: {=XLOOKUP(Scenario_Selected, INDEX(Scenario_Table,0,1), INDEX(Scenario_Table,0,3))} | V400: {=XLOOKUP(Scenario_Selected, INDEX(Scenario_Table,0,1), INDEX(Scenario_Table,0,4))} | W400: {=LET(ev,$J400, ch,$L400, et,$I400, dr,$Q400, hpday,Assumptions!$B$2, hpw,Assumptions!$B$3, w,$M400,hm,INDIRECT("R[0]C[0]",FALSE),hrs, IF(et="Hours", ev, IF(et="Days", ev*IF(dr>0, dr/$P400, hpday), IF(et="FTE", ev*hpw*w, ch))), IF(hrs="", "", hrs*hm))} | X400: =IF($P400="","", $P400*INDIRECT("R[0]C[-3]",FALSE)) | Y400: =IF(INDIRECT("R[0]C[-1]",FALSE)="","", INDIRECT("R[0]C[-2]",FALSE)*INDIRECT("R[0]C[-1]",FALSE)*(1+INDIRECT("R[0]C[-3]",FALSE)))

Sheet WBS
A1: Phase | B1: Activity / Milestone | C1: Subtask | D1: Deliverable | E1: Deliverable Description | F1: Knapsack Role Description | G1: Accountable Party | H1: Role | I1: Timeline (Weeks)
A2: Implementation + Onboarding | B2: Stakeholder Alignment Workshops | C2: Identify executive and operational stakeholders | F2: CX Partner - Change Management SME | G2: Adobe | H2: CX Partner | I2: 1–2
A3: Implementation + Onboarding | B3: Stakeholder Alignment Workshops | C3: Conduct alignment workshops and capture insights | F3: CX Partner - Change Management SME | G3: Adobe | H3: CX Partner | I3: 1–2
A4: Implementation + Onboarding | B4: Stakeholder Alignment Workshops | C4: Develop stakeholder map and influence matrix | F4: CX Partner - Change Management SME | G4: Adobe | H4: CX Partner | I4: 1–2
A5: Implementation + Onboarding | B5: Stakeholder Alignment Workshops | C5: Draft communication strategy and feedback cadence | F5: CX Partner - Change Management SME | G5: Adobe | H5: CX Partner | I5: 1–2
A6: Implementation + Onboarding | B6: Stakeholder Alignment Workshops | C6: Review and sign off communication plan with Steering Committee | D6: Stakeholder Map, Communication Strategy Draft | E6: Ensure executive and stakeholder alignment before kickoff. | F6: CX Partner - Change Management SME | G6: Adobe | H6: CX Partner | I6: 1–2
A7: Implementation + Onboarding | B7: Program management and coordination | C7: Establish governance tracker and cadence calendar | F7: Project Manager | G7: Knapsack | H7: Project Manager | I7: 1–20
A8: Implementation + Onboarding | B8: Program management and coordination | C8: Schedule weekly syncs and milestone reviews | F8: Project Manager | G8: Knapsack | H8: Project Manager | I8: 1–20
A9: Implementation + Onboarding | B9: Program management and coordination | C9: Maintain RAID log | F9: Project Manager | G9: Knapsack | H9: Project Manager | I9: 1–20
A10: Implementation + Onboarding | B10: Program management and coordination | C10: Prepare Phase 1 exit and readiness report | F10: Project Manager | G10: Knapsack | H10: Project Manager | I10: 1–20
A11: Implementation + Onboarding | B11: Program management and coordination | C11: Present status updates to Adobe Steering Committee | D11: Project Governance Tracker, Phase 1 Exit Report | E11: Program coordination, kickoff, and phase review oversight. | F11: Project Manager | G11: Knapsack | H11: Project Manager | I11: 1–20
A12: Implementation + Onboarding | B12: Communication Launch Plan | C12: Create internal messaging and visual identity kit | F12: CX Partner - Change Management SME | G12: Adobe | H12: CX Partner | I12: 3–6
A13: Implementation + Onboarding | B13: Communication Launch Plan | C13: Develop launch materials (FAQ, deck, announcement) | F13: CX Partner - Change Management SME | G13: Adobe | H13: CX Partner | I13: 3–6
A14: Implementation + Onboarding | B14: Communication Launch Plan | C14: Align with design ops for internal brand tone and channels | F14: CX Partner - Change Management SME | G14: Adobe | H14: CX Partner | I14: 3–6
A15: Implementation + Onboarding | B15: Communication Launch Plan | C15: Distribute campaign via Adobe internal comms | F15: CX Partner - Change Management SME | G15: Adobe | H15: CX Partner | I15: 3–6
A16: Implementation + Onboarding | B16: Communication Launch Plan | C16: Gather feedback and refine messaging | D16: Internal Communication Plan, Branding Package | E16: Launch program messaging, goals, and brand identity across teams. | F16: CX Partner - Change Management SME | G16: Adobe | H16: CX Partner | I16: 3–6
A17: Implementation + Onboarding | B17: Preparation | C17: Conduct environment readiness check | F17: Project Manager | G17: Knapsack | H17: Project Manager | I17: 7–10
A18: Implementation + Onboarding | B18: Preparation | C18: Validate API and endpoint configuration | F18: Project Manager | G18: Knapsack | H18: Project Manager | I18: 7–10
A19: Implementation + Onboarding | B19: Preparation | C19: Verify authentication and permissions access | F19: Project Manager | G19: Knapsack | H19: Project Manager | I19: 7–10
A20: Implementation + Onboarding | B20: Preparation | C20: Confirm hosting and network compliance | F20: Project Manager | G20: Knapsack | H20: Project Manager | I20: 7–10
A21: Implementation + Onboarding | B21: Preparation | C21: Document results in Technical Readiness Checklist | D21: Technical Readiness Checklist | E21: Verify infrastructure readiness, environment setup, and permissions. | F21: Project Manager | G21: Knapsack | H21: Project Manager | I21: 7–10
A22: Implementation + Onboarding | B22: Local install support | C22: Provide installation guide and validation checklist | F22: Senior Solutions Engineer | G22: Knapsack | H22: Engineer | I22: 7–10
A23: Implementation + Onboarding | B23: Local install support | C23: Support local environment configuration | F23: Senior Solutions Engineer | G23: Knapsack | H23: Engineer | I23: 7–10
A24: Implementation + Onboarding | B24: Local install support | C24: Troubleshoot integration issues | F24: Senior Solutions Engineer | G24: Knapsack | H24: Engineer | I24: 7–10
A25: Implementation + Onboarding | B25: Local install support | C25: Validate connectivity with IPE components | F25: Senior Solutions Engineer | G25: Knapsack | H25: Engineer | I25: 7–10
A26: Implementation + Onboarding | B26: Local install support | C26: Log and close install-related tickets | D26: Installation Validation Report | E26: Validate local environment setup for Knapsack and IPE components. | F26: Senior Solutions Engineer | G26: Knapsack | H26: Engineer | I26: 7–10
A27: Implementation + Onboarding | B27: Component rendering | C27: Validate core Spectrum components rendering | F27: Senior Solutions Engineer | G27: Knapsack | H27: Engineer | I27: 7–10
A28: Implementation + Onboarding | B28: Component rendering | C28: Conduct visual and functional QA across environments | F28: Senior Solutions Engineer | G28: Knapsack | H28: Engineer | I28: 7–10
A29: Implementation + Onboarding | B29: Component rendering | C29: Compare results with baseline expectations | F29: Senior Solutions Engineer | G29: Knapsack | H29: Engineer | I29: 7–10
A30: Implementation + Onboarding | B30: Component rendering | C30: Document rendering test summary report | F30: Senior Solutions Engineer | G30: Knapsack | H30: Engineer | I30: 7–10
A31: Implementation + Onboarding | B31: Component rendering | C31: Submit remediation recommendations | D31: Rendering QA Report | E31: Validate successful rendering of Spectrum components across environments. | F31: Senior Solutions Engineer | G31: Knapsack | H31: Engineer | I31: 7–10
A32: Implementation + Onboarding | B32: SME support for rendering | C32: Review component architecture and consistency | F32: Subject Matter Expert | G32: Knapsack | H32: SME | I32: 7–10
A33: Implementation + Onboarding | B33: SME support for rendering | C33: Audit rendering pipeline and dependency mapping | F33: Subject Matter Expert | G33: Knapsack | H33: SME | I33: 7–10
A34: Implementation + Onboarding | B34: SME support for rendering | C34: Validate accessibility compliance | F34: Subject Matter Expert | G34: Knapsack | H34: SME | I34: 7–10
A35: Implementation + Onboarding | B35: SME support for rendering | C35: Provide expert input to engineering team | F35: Subject Matter Expert | G35: Knapsack | H35: SME | I35: 7–10
A36: Implementation + Onboarding | B36: SME support for rendering | C36: Approve Architecture Validation Log | D36: Architecture Validation Log | E36: SME oversight of rendering logic and architectural consistency. | F36: Subject Matter Expert | G36: Knapsack | H36: SME | I36: 7–10
A37: Implementation + Onboarding | B37: Deployment support | C37: Define deployment workflow and CI/CD configuration | F37: Senior Solutions Engineer | G37: Knapsack | H37: Engineer | I37: 15–20
A38: Implementation + Onboarding | B38: Deployment support | C38: Create rollback and versioning process | F38: Senior Solutions Engineer | G38: Knapsack | H38: Engineer | I38: 15–20
A39: Implementation + Onboarding | B39: Deployment support | C39: Run initial deployment test | F39: Senior Solutions Engineer | G39: Knapsack | H39: Engineer | I39: 15–20
A40: Implementation + Onboarding | B40: Deployment support | C40: Record metrics against success criteria | F40: Senior Solutions Engineer | G40: Knapsack | H40: Engineer | I40: 15–20
